Workbook

Sheet LDL
D2: CONTRACT / PO | P2: PHÂN LOẠI | T2: THÔNG TIN HÀNG HÓA | AD2: EUR | AE2: 32000 | AJ2: THÔNG TIN VẬN CHUYỂN | BD2: {="Max Lô "&MAX(IFERROR(IF(VALUE(SUBSTITUTE($BD$5:$BD$12797,"Lô ",""))<1000, VALUE(SUBSTITUTE($BD$5:$BD$12797,"Lô ",""))), ""))} -> Max Lô 121 | BH2: PHÍ VẬN CHUYỂN / LÔ | BS2: PHÍ VẬN CHUYỂN / MÃ | BZ2: GIÁ NHẬP KHO | CC2: =SUBTOTAL(9,$CF$960:$CF$1832) -> 2.4678681e+10 | CD2: =SUBTOTAL(9,$BZ$960:$BZ$1832) -> 2.5425752e+10 | CF2: =CD2-CC2 -> 7.4707159e+08 | CG2: =SUBTOTAL(9,BX960:BX1832) -> 6.8183813e+08 | CH2: =CG2/CC2 -> 0.02762863
U3: =SUBTOTAL(9,U5:U96855) -> 61959.42 | AB3: =SUBTOTAL(9,AB5:AB96855) -> 2702174.7 | AC3: =SUBTOTAL(9,AC5:AC96855) -> 2729429.1 | AD3: USD | AE3: 27000 | BD3: {="Max Lô "&MAX(IFERROR(IF(VALUE(SUBSTITUTE($BD$5:$BD$12797,"Lô ",""))>1000, VALUE(SUBSTITUTE($BD$5:$BD$12797,"Lô ",""))), ""))} -> Max Lô 0 | BF3: Cost 1 | BI3: Cost 2 | BJ3: Cost 3 | BL3: Cost 4 | BN3: Cost 5 | BO3: (+OF) | BX3: =SUBTOTAL(109,BX5:BX12824) -> 2.302903e+09 | BY3: =SUBTOTAL(109,BY5:BY1018144) -> 3.1958355e+10 | BZ3: =SUBTOTAL(109,BZ5:BZ1018144) -> 6.3065272e+10 | CA3: =SUBTOTAL(109,CA5:CA1018144) -> 3.257055e+10
B4: TÌNH TRẠNG | C4: NCC | D4: HỢP ĐỒNG | E4: SỐ PO | F4: NGÀY PO | G4: BRAND | H4: PRE-ORDER/STOCK | I4: SỐ DH | J4: NGÀY KHÁCH ĐẶT HÀNG | K4: NGÀY GIAO HÀNG | L4: PHƯƠNG THỨC THANH TOÁN | M4: PAYMENT TERM | N4: NGÀY THANH TOÁN | O4: CATEGORY | P4: SUB-CATEGORY | Q4: SERIES | R4: MODEL | S4: MÃ MISA | T4: TÊN HÀNG HÓA | U4: SL | V4: NGOẠI TỆ | W4: PRICE LIST | X4: GIÁ TRỊ GROSS | Y4: DISCOUNT | Z4: PRICE ORDER | AA4: F.O.C | AB4: GIÁ TRỊ NET/HỢP ĐỒNG (-FOC) | AC4: GIÁ TRỊ NET/HỢP ĐỒNG | AD4: Tỷ giá cho Đơn giá nhập | AE4: Tỷ giá tờ khai | AF4: Thuế nhập khẩu + thuế CBPG | AG4: Giá trị thuế nhập khẩu | AH4: VAT | AI4: Giá trị VAT | AJ4: SỐ INVOICE | AK4: NGÀY INVOICE | AL4: SỐ BILL | AM4: SỐ CONTS/SEAL | AN4: SL CONT/CBM (20/40) | AO4: PHƯƠNG THỨC VẬN CHUYỂN | AP4: ETD S/O | AQ4: ETD/ATD | AR4: ETA | AS4: POL | AT4: POD | AU4: FWD | AV4: SỐ TỜ KHAI | AW4: NGÀY TỜ KHAI | AX4: NGÀY THÔNG QUAN | AY4: DIỄN GIẢI TỜ KHAI | AZ4: HS CODE | BA4: GHI CHÚ HÀNG HÓA | BB4: KHO | BC4: NGÀY NHẬP KHO | BD4: Số lô | BE4: % Tỷ lệ | BF4: Phí lấy hàng EXW/FCA + OF | BG4: Phí lấy hàng FCA | BH4: OF | AF | BI4: Local charge+PVHN+Lưu kho+ Trucking (Chưa VAT) | BJ4: Insurance fee (Chưa VAT) | BK4: D/O / THỬ NGHIỆM/ CP KHÁC | BL4: Phí CSHT+ Lệ phí HQ VND | BM4: TRUCKING FEE | BN4: CHI PHÍ HẢI QUAN (Chưa VAT) | BO4: Phí thủ tục lấy hàng EXW /mã | BP4: Phí thủ tục lấy hàng FCA /mã | BQ4: OF | AF /mã | BR4: Local charge+PVHN+Lưu kho+ Trucking Chưa VAT | BS4: INS FEE /mã (Chưa VAT) | BT4: D/O / THỬ NGHIỆM/ CP KHÁC / mã | BU4: Phí CSHT /mã | BV4: Trucking /mã | BW4: Khai hải quan /mã | BX4: TOTAL COST Vận chuyển | BY4: Giá nhập kho (chưa VAT) | BZ4: Giá trị nhập kho (theo SL) | CA4: Giá vốn max theo mã misa | CB4: Giá bán lẻ | CC4: Giá bán ck | CD4: LN net | CE4: Biên lãi gộp | CF4: Giá trị net vnd
B5: Done | C5: LOUIS POULSEN | D5: SC-LPS-03-091023- DH-0001464&1471&1379 | E5: =D5 -> SC-LPS-03-091023- DH-0001464&1471&1379 | F5: 45208 | G5: Louis Poulsen | H5: PRE-ORDER | I5: DH-0001464&1471&1379 | J5: 27/10/2023 | K5: 16/12/2023 | L5: 100% BEFORE PICK UP | M5: EXW | O5: DECOR LIGHTING | P5: pendant | Q5: PH 5 Ø500mm Pendant | R5: 5741099980 | S5: LPLLP00049 | T5: Đèn Thả PH 5, kích thước: phi 500 x H267 mm, Bằng Aluminum, Màu Đồng Brass (không kèm bóng), hiệu: Louis Poulsen, mã hàng: 5741099980, mới 100% | U5: 2 | V5: EUR | X5: =W5*U5 -> 0 | Z5: 620 | AB5: =IF(AA5="F.O.C", 0, Z5*U5) -> 1240 | AC5: =Z5*U5 -> 1240 | AE5: 25700.56 | AF5: 0 | AG5: =(AC5*AE5+BO5+BP5+BQ5+BS5)*AF5 -> 0 | AI5: =(AC5*AE5+AG5+BF5+BG5+BH5+BJ5)*AH5 -> 0 | AJ5: 1019010048 | AK5: 27/11/2023 | AO5: AIR | AQ5: 10/12/2023 | AV5: 105951072360 | AW5: 45272 | AX5: 12/12/2023 | BA5: Xong | BB5: BÌNH PHÚ | BC5: 45274 | BD5: Lô 1 | BE5: {=IF(BD5="","",AC5/SUMPRODUCT(--(BD5=$BD$4:$BD$12824),$AC$4:$AC$12824))} -> 0.58907363 | BI5: 11951100 | BN5: 600000 | BO5: =VLOOKUP(BD5,$BD$4:$BN$12824,3,0)*BE5 -> 0 | BR5: =VLOOKUP(BD5,$BD$4:$BN$12824,6,0)*BE5 -> 7040077.9 | BS5: =VLOOKUP(BD5,$BD$4:$BN$12824,7,0)*BE5 -> 0 | BU5: =VLOOKUP(BD5,$BD$4:$BN$12824,9,0)*BE5 -> 0 | BW5: =VLOOKUP(BD5,$BD$4:$BN$12824,11,0)*BE5 -> 353444.18 | BX5: =SUM(BO5:BW5) -> 7393522.1 | BY5: =(AB5*AE5+AG5+BX5)/U5 -> 19631108 | BZ5: =BY5*U5 -> 39262216 | CA5: =_xlfn.MAXIFS($BY$4:$BY$12824,$S$4:$S$12824,$S5) -> 19631108 | CF5: =AC5*AE5 -> 31868694
B6: Done | C6: LOUIS POULSEN | D6: SC-LPS-03-091023- DH-0001464&1471&1379 | E6: =D6 -> SC-LPS-03-091023- DH-0001464&1471&1379 | F6: 45208 | G6: Louis Poulsen | H6: PRE-ORDER | I6: DH-0001464&1471&1379 | J6: 27/10/2023 | K6: 16/12/2023 | L6: 100% BEFORE PICK UP | M6: EXW | O6: DECOR LIGHTING | P6: Spare part | Q6: Sparepart | R6: 5744610722 | S6: SPALP00007 | T6: Chụp Đèn PH 4 1/2 - 3 1/2 Top Shade, kích thước : DK 45 cm, bằng thủy tinh, màu trắng, hiệu: Louis Poulsen, mã hàng: 5744610722, mới 100% | U6: 1 | V6: EUR | X6: =W6*U6 -> 0 | Z6: 755 | AB6: =IF(AA6="F.O.C", 0, Z6*U6) -> 755 | AC6: =Z6*U6 -> 755 | AE6: 25700.56 | AF6: 0 | AG6: =(AC6*AE6+BO6+BP6+BQ6+BS6)*AF6 -> 0 | AI6: =(AC6*AE6+AG6+BF6+BG6+BH6+BJ6)*AH6 -> 0 | AJ6: 1019010048 | AK6: 27/11/2023 | AO6: AIR | AQ6: 10/12/2023 | AV6: 105951072360 | AW6: 45272 | AX6: 12/12/2023 | BA6: Xong | BB6: BÌNH PHÚ | BC6: 45274 | BD6: Lô 1 | BE6: {=IF(BD6="","",AC6/SUMPRODUCT(--(BD6=$BD$4:$BD$12824),$AC$4:$AC$12824))} -> 0.35866983 | BO6: =VLOOKUP(BD6,$BD$4:$BN$12824,3,0)*BE6 -> 0 | BR6: =VLOOKUP(BD6,$BD$4:$BN$12824,6,0)*BE6 -> 4286499 | BS6: =VLOOKUP(BD6,$BD$4:$BN$12824,7,0)*BE6 -> 0 | BU6: =VLOOKUP(BD6,$BD$4:$BN$12824,9,0)*BE6 -> 0 | BW6: =VLOOKUP(BD6,$BD$4:$BN$12824,11,0)*BE6 -> 215201.9 | BX6: =SUM(BO6:BW6) -> 4501701 | BY6: =(AB6*AE6+AG6+BX6)/U6 -> 23905624 | BZ6: =BY6*U6 -> 23905624 | CA6: =_xlfn.MAXIFS($BY$4:$BY$12824,$S$4:$S$12824,$S6) -> 23905624 | CF6: =AC6*AE6 -> 19403923
B7: Done | C7: LOUIS POULSEN | D7: SC-LPS-03-091023- DH-0001464&1471&1379 | E7: =D7 -> SC-LPS-03-091023- DH-0001464&1471&1379 | F7: 45208 | G7: Louis Poulsen | H7: PRE-ORDER | I7: DH-0001464&1471&1379 | J7: 27/10/2023 | K7: 16/12/2023 | L7: 100% BEFORE PICK UP | M7: EXW | O7: DECOR LIGHTING | P7: Spare part | Q7: Sparepart | R7: 5741481598 | S7: SPALP00008 | T7: Chụp Đèn PH 3-2 middle shade, kích thước DK 14.4 cm, bằng thủy tinh, màu trắng, hiệu: Louis Poulsen, mã hàng: 5741481598, mới 100% | U7: 1 | V7: EUR | X7: =W7*U7 -> 0 | Z7: 110 | AB7: =IF(AA7="F.O.C", 0, Z7*U7) -> 110 | AC7: =Z7*U7 -> 110 | AE7: 25700.56 | AF7: 0 | AG7: =(AC7*AE7+BO7+BP7+BQ7+BS7)*AF7 -> 0 | AI7: =(AC7*AE7+AG7+BF7+BG7+BH7+BJ7)*AH7 -> 0 | AJ7: 1019010048 | AK7: 27/11/2023 | AO7: AIR | AQ7: 10/12/2023 | AV7: 105951072360 | AW7: 45272 | AX7: 12/12/2023 | BA7: Xong | BB7: BÌNH PHÚ | BC7: 45274 | BD7: Lô 1 | BE7: {=IF(BD7="","",AC7/SUMPRODUCT(--(BD7=$BD$4:$BD$12824),$AC$4:$AC$12824))} -> 0.052256532 | BO7: =VLOOKUP(BD7,$BD$4:$BN$12824,3,0)*BE7 -> 0 | BR7: =VLOOKUP(BD7,$BD$4:$BN$12824,6,0)*BE7 -> 624523.04 | BS7: =VLOOKUP(BD7,$BD$4:$BN$12824,7,0)*BE7 -> 0 | BU7: =VLOOKUP(BD7,$BD$4:$BN$12824,9,0)*BE7 -> 0 | BW7: =VLOOKUP(BD7,$BD$4:$BN$12824,11,0)*BE7 -> 31353.919 | BX7: =SUM(BO7:BW7) -> 655876.96 | BY7: =(AB7*AE7+AG7+BX7)/U7 -> 3482938.6 | BZ7: =BY7*U7 -> 3482938.6 | CA7: =_xlfn.MAXIFS($BY$4:$BY$12824,$S$4:$S$12824,$S7) -> 3482938.6 | CF7: =AC7*AE7 -> 2827061.6
B8: Done | C8: NINE UNITED | D8: SC-NINE UNITED-120923-Ms Thao & Stock | E8: =D8 -> SC-NINE UNITED-120923-Ms Thao & Stock | F8: 45181 | G8: HAY | H8: STOCK | L8: 100% BEFORE PICK UP | M8: EXW | O8: ACCESSORIES | P8: Cushion | R8: AB562-B289-AB30 | S8: SPAHA00017 | T8: Đệm PALISSADE CHAISE LOUNGE QUILTED CUSHION,(D195 xR49.5 xC1)cm,Bằng Mút xốp,Bọc vải Olefin,Màu xám(Sky Grey).Hiệu:HAY.Model:AB562-B289-AB30.Mới 100% | U8: 1 | V8: USD | X8: =W8*U8 -> 0 | Z8: 83.22 | AB8: =IF(AA8="F.O.C", 0, Z8*U8) -> 83.22 | AC8: =Z8*U8 -> 83.22 | AE8: 24090 | AF8: 0 | AG8: =(AC8*AE8+BO8+BP8+BQ8+BS8)*AF8 -> 0 | AI8: =(AC8*AE8+AG8+BF8+BG8+BH8+BJ8)*AH8 -> 0 | AJ8: IN231027082720 | AK8: 45226 | AO8: SEA | AQ8: 23/10/2023 | AV8: 105946807302 | AW8: 45269 | AX8: 09/12/2023 | BA8: Xong | BB8: BÌNH PHÚ | BC8: 45150 | BD8: Lô 2 | BE8: {=IF(BD8="","",AC8/SUMPRODUCT(--(BD8=$BD$4:$BD$12824),$AC$4:$AC$12824))} -> 0.0092820312 | BF8: 21196560 | BI8: 10647120 | BJ8: 450000 | BL8: 500000 | BN8: 1890000 | BO8: =VLOOKUP(BD8,$BD$4:$BN$12824,3,0)*BE8 -> 196747.13 | BR8: =VLOOKUP(BD8,$BD$4:$BN$12824,6,0)*BE8 -> 98826.9 | BS8: =VLOOKUP(BD8,$BD$4:$BN$12824,7,0)*BE8 -> 4176.914 | BU8: =VLOOKUP(BD8,$BD$4:$BN$12824,9,0)*BE8 -> 4641.0156 | BW8: =VLOOKUP(BD8,$BD$4:$BN$12824,11,0)*BE8 -> 17543.039 | BX8: =SUM(BO8:BW8) -> 321935 | BY8: =(AB8*AE8+AG8+BX8)/U8 -> 2326704.8 | BZ8: =BY8*U8 -> 2326704.8 | CA8: =_xlfn.MAXIFS($BY$4:$BY$12824,$S$4:$S$12824,$S8) -> 2945788.5 | CF8: =AC8*AE8 -> 2004769.8
B9: Done | C9: NINE UNITED | D9: SC-NINE UNITED-120923-Ms Thao & Stock | E9: =D9 -> SC-NINE UNITED-120923-Ms Thao & Stock | F9: 45181 | G9: HAY | H9: STOCK | L9: 100% BEFORE PICK UP | M9: EXW | O9: ACCESSORIES | P9: Cushion | R9: AB562-B293-AB30 | S9: SPAHA00016 | T9: Đệm PALISSADE-LOUNGE CHAIR LOW QUILTED CUSHION,(D117xR49.5xC1)cm,Bằng Mút xốp,Bọc vải Olefin,Màu xám(Sky Grey).Hiệu:HAY.Model:AB562-B293-AB30.Mới 100% | U9: 1 | V9: USD | X9: =W9*U9 -> 0 | Z9: 51.87 | AB9: =IF(AA9="F.O.C", 0, Z9*U9) -> 51.87 | AC9: =Z9*U9 -> 51.87 | AE9: 24090 | AF9: 0 | AG9: =(AC9*AE9+BO9+BP9+BQ9+BS9)*AF9 -> 0 | AI9: =(AC9*AE9+AG9+BF9+BG9+BH9+BJ9)*AH9 -> 0 | AJ9: IN231027082720 | AK9: 45226 | AO9: SEA | AQ9: 23/10/2023 | AV9: 105946807302 | AW9: 45269 | AX9: 09/12/2023 | BA9: Xong | BB9: BÌNH PHÚ | BC9: 45150 | BD9: Lô 2 | BE9: {=IF(BD9="","",AC9/SUMPRODUCT(--(BD9=$BD$4:$BD$12824),$AC$4:$AC$12824))} -> 0.0057853756 | BO9: =VLOOKUP(BD9,$BD$4:$BN$12824,3,0)*BE9 -> 122630.06 | BR9: =VLOOKUP(BD9,$BD$4:$BN$12824,6,0)*BE9 -> 61597.588 | BS9: =VLOOKUP(BD9,$BD$4:$BN$12824,7,0)*BE9 -> 2603.419 | BU9: =VLOOKUP(BD9,$BD$4:$BN$12824,9,0)*BE9 -> 2892.6878 | BW9: =VLOOKUP(BD9,$BD$4:$BN$12824,11,0)*BE9 -> 10934.36 | BX9: =SUM(BO9:BW9) -> 200658.12 | BY9: =(AB9*AE9+AG9+BX9)/U9 -> 1450206.4 | BZ9: =BY9*U9 -> 1450206.4 | CA9: =_xlfn.MAXIFS($BY$4:$BY$12824,$S$4:$S$12824,$S9) -> 1450206.4 | CF9: =AC9*AE9 -> 1249548.3
B10: Done | C10: NINE UNITED | D10: SC-NINE UNITED-120923-Ms Thao & Stock | E10: =D10 -> SC-NINE UNITED-120923-Ms Thao & Stock | F10: 45181 | G10: VERPAN | H10: STOCK | L10: 100% BEFORE PICK UP | M10: EXW | O10: FURNITURE | P10: Chairs | R10: V9112018800219 | S10: CLGVP00001 | T10: Ghế EASY CHAIR, DI80 x H84 cm, Bằng Vải Dedar Karandash (004), Màu Vàng.Hiệu:Verpan.Model:V911201 8800219.Mới 100% | U10: 1 | V10: USD | X10: =W10*U10 -> 0 | Z10: 2259.5 | AB10: =IF(AA10="F.O.C", 0, Z10*U10) -> 2259.5 | AC10: =Z10*U10 -> 2259.5 | AE10: 24090 | AF10: 0.25 | AG10: =(AC10*AE10+BO10+BP10+BQ10+BS10)*AF10 -> 14971657 | AI10: =(AC10*AE10+AG10+BF10+BG10+BH10+BJ10)*AH10 -> 0 | AJ10: IN231027082720 | AK10: 45226 | AO10: SEA | AQ10: 23/10/2023 | AV10: 105946807302 | AW10: 45269 | AX10: 09/12/2023 | BA10: Xong | BB10: BÌNH PHÚ | BC10: 45150 | BD10: Lô 2 | BE10: {=IF(BD10="","",AC10/SUMPRODUCT(--(BD10=$BD$4:$BD$12824),$AC$4:$AC$12824))} -> 0.25201574 | BO10: =VLOOKUP(BD10,$BD$4:$BN$12824,3,0)*BE10 -> 5341866.7 | BR10: =VLOOKUP(BD10,$BD$4:$BN$12824,6,0)*BE10 -> 2683241.8 | BS10: =VLOOKUP(BD10,$BD$4:$BN$12824,7,0)*BE10 -> 113407.08 | BU10: =VLOOKUP(BD10,$BD$4:$BN$12824,9,0)*BE10 -> 126007.87 | BW10: =VLOOKUP(BD10,$BD$4:$BN$12824,11,0)*BE10 -> 476309.74 | BX10: =SUM(BO10:BW10) -> 8740833.1 | BY10: =(AB10*AE10+AG10+BX10)/U10 -> 78143845 | BZ10: =BY10*U10 -> 78143845 | CA10: =_xlfn.MAXIFS($BY$4:$BY$12824,$S$4:$S$12824,$S10) -> 78143845 | CF10: =AC10*AE10 -> 54431355
B11: Done | C11: NINE UNITED | D11: SC-NINE UNITED-120923-Ms Thao & Stock | E11: =D11 -> SC-NINE UNITED-120923-Ms Thao & Stock | F11: 45181 | G11: &Tradition | H11: STOCK | L11: 100% BEFORE PICK UP | M11: EXW | O11: FURNITURE | P11: table | R11: 701031 | S11: TBLAT00002 | T11: Bàn trang trí SHUFFLE MH1, mặt bàn tròn, Phi45xH69cm, Bằng Gỗ Lacquered MDF,solid wood, màu quang phổ(spectrum).Hiệu:&Tradition.Model:701031.Mới 100% | U11: 1 | V11: USD | X11: =W11*U11 -> 0 | Z11: 268.4 | AB11: =IF(AA11="F.O.C", 0, Z11*U11) -> 268.4 | AC11: =Z11*U11 -> 268.4 | AE11: 24090 | AF11: 0.05 | AG11: =(AC11*AE11+BO11+BP11+BQ11+BS11)*AF11 -> 355688.67 | AI11: =(AC11*AE11+AG11+BF11+BG11+BH11+BJ11)*AH11 -> 0 | AJ11: IN231027082720 | AK11: 45226 | AO11: SEA | AQ11: 23/10/2023 | AV11: 105946807302 | AW11: 45269 | AX11: 09/12/2023 | BA11: Xong | BB11: BÌNH PHÚ | BC11: 45150 | BD11: Lô 2 | BE11: {=IF(BD11="","",AC11/SUMPRODUCT(--(BD11=$BD$4:$BD$12824),$AC$4:$AC$12824))} -> 0.029936279 | BO11: =VLOOKUP(BD11,$BD$4:$BN$12824,3,0)*BE11 -> 634546.14 | BR11: =VLOOKUP(BD11,$BD$4:$BN$12824,6,0)*BE11 -> 318735.16 | BS11: =VLOOKUP(BD11,$BD$4:$BN$12824,7,0)*BE11 -> 13471.326 | BU11: =VLOOKUP(BD11,$BD$4:$BN$12824,9,0)*BE11 -> 14968.14 | BW11: =VLOOKUP(BD11,$BD$4:$BN$12824,11,0)*BE11 -> 56579.568 | BX11: =SUM(BO11:BW11) -> 1038300.3 | BY11: =(AB11*AE11+AG11+BX11)/U11 -> 7859745 | BZ11: =BY11*U11 -> 7859745 | CA11: =_xlfn.MAXIFS($BY$4:$BY$12824,$S$4:$S$12824,$S11) -> 7859745 | CF11: =AC11*AE11 -> 6465756
B12: Done | C12: NINE UNITED | D12: SC-NINE UNITED-120923-Ms Thao & Stock | E12: =D12 -> SC-NINE UNITED-120923-Ms Thao & Stock | F12: 45181 | G12: &Tradition | H12: STOCK | L12: 100% BEFORE PICK UP | M12: EXW | O12: DECOR LIGHTING | P12: Table lamp | R12: 20712201 | S12: LTLAT00009 | T12: Đèn trang trí FLOWERPOT VP9,công nghệ LED,(Phi 16 x cao 29.5)cm,3W 2700K,bằng PC và thép,màu vàng(Mustard).Hiệu:&Tradition.Model:20712201.Mới 100% | U12: 6 | V12: USD | X12: =W12*U12 -> 0 | Z12: 100.1 | AB12: =IF(AA12="F.O.C", 0, Z12*U12) -> 600.6 | AC12: =Z12*U12 -> 600.6 | AE12: 24090 | AF12: 0 | AG12: =(AC12*AE12+BO12+BP12+BQ12+BS12)*AF12 -> 0 | AI12: =(AC12*AE12+AG12+BF12+BG12+BH12+BJ12)*AH12 -> 0 | AJ12: IN231027082720 | AK12: 45226 | AO12: SEA | AQ12: 23/10/2023 | AV12: 105946807302 | AW12: 45269 | AX12: 09/12/2023 | BA12: Xong | BB12: BÌNH PHÚ | BC12: 45269 | BD12: Lô 2 | BE12: {=IF(BD12="","",AC12/SUMPRODUCT(--(BD12=$BD$4:$BD$12824),$AC$4:$AC$12824))} -> 0.06698856 | BO12: =VLOOKUP(BD12,$BD$4:$BN$12824,3,0)*BE12 -> 1419927 | BR12: =VLOOKUP(BD12,$BD$4:$BN$12824,6,0)*BE12 -> 713235.23 | BS12: =VLOOKUP(BD12,$BD$4:$BN$12824,7,0)*BE12 -> 30144.852 | BU12: =VLOOKUP(BD12,$BD$4:$BN$12824,9,0)*BE12 -> 33494.28 | BW12: =VLOOKUP(BD12,$BD$4:$BN$12824,11,0)*BE12 -> 126608.38 | BX12: =SUM(BO12:BW12) -> 2323409.8 | BY12: =(AB12*AE12+AG12+BX12)/U12 -> 2798644 | BZ12: =BY12*U12 -> 16791864 | CA12: =_xlfn.MAXIFS($BY$4:$BY$12824,$S$4:$S$12824,$S12) -> 4101317.8 | CF12: =AC12*AE12 -> 14468454
B13: Done | C13: NINE UNITED | D13: SC-NINE UNITED-120923-Ms Thao & Stock | E13: =D13 -> SC-NINE UNITED-120923-Ms Thao & Stock | F13: 45181 | G13: &Tradition | H13: STOCK | L13: 100% BEFORE PICK UP | M13: EXW | O13: DECOR LIGHTING | P13: Table lamp | R13: 20713501 | S13: LTLAT00015 | T13: Đèn trang trí FLOWERPOT VP9,công nghệ LED,(Phi 16 x cao 29.5)cm,3W 2700K,bằng PC và thép,Màu hồng(Tangy Pink).Hiệu:&Tradition.Model:20713501.Mới 100% | U13: 2 | V13: USD | X13: =W13*U13 -> 0 | Z13: 100.1 | AB13: =IF(AA13="F.O.C", 0, Z13*U13) -> 200.2 | AC13: =Z13*U13 -> 200.2 | AE13: 24090 | AF13: 0 | AG13: =(AC13*AE13+BO13+BP13+BQ13+BS13)*AF13 -> 0 | AI13: =(AC13*AE13+AG13+BF13+BG13+BH13+BJ13)*AH13 -> 0 | AJ13: IN231027082720 | AK13: 45226 | AO13: SEA | AQ13: 23/10/2023 | AV13: 105946807302 | AW13: 45269 | AX13: 09/12/2023 | BA13: Xong | BB13: BÌNH PHÚ | BC13: 45269 | BD13: Lô 2 | BE13: {=IF(BD13="","",AC13/SUMPRODUCT(--(BD13=$BD$4:$BD$12824),$AC$4:$AC$12824))} -> 0.02232952 | BO13: =VLOOKUP(BD13,$BD$4:$BN$12824,3,0)*BE13 -> 473309.01 | BR13: =VLOOKUP(BD13,$BD$4:$BN$12824,6,0)*BE13 -> 237745.08 | BS13: =VLOOKUP(BD13,$BD$4:$BN$12824,7,0)*BE13 -> 10048.284 | BU13: =VLOOKUP(BD13,$BD$4:$BN$12824,9,0)*BE13 -> 11164.76 | BW13: =VLOOKUP(BD13,$BD$4:$BN$12824,11,0)*BE13 -> 42202.793 | BX13: =SUM(BO13:BW13) -> 774469.92 | BY13: =(AB13*AE13+AG13+BX13)/U13 -> 2798644 | BZ13: =BY13*U13 -> 5597287.9 | CA13: =_xlfn.MAXIFS($BY$4:$BY$12824,$S$4:$S$12824,$S13) -> 2798644 | CF13: =AC13*AE13 -> 4822818
B14: Done | C14: NINE UNITED | D14: SC-NINE UNITED-120923-Ms Thao & Stock | E14: =D14 -> SC-NINE UNITED-120923-Ms Thao & Stock | F14: 45181 | G14: &Tradition | H14: STOCK | L14: 100% BEFORE PICK UP | M14: EXW | O14: DECOR LIGHTING | P14: Table lamp | R14: 20713601 | S14: LTLAT00014 | T14: Đèn trang trí FLOWERPOT VP9,công nghệ LED,(Phi 16 x cao 29.5)cm,3W 2700K,bằng PC và thép,Màu đỏ (Dark Plum).Hiệu:&Tradition.Model:20713601.Mới 100% | U14: 2 | V14: USD | X14: =W14*U14 -> 0 | Z14: 100.1 | AB14: =IF(AA14="F.O.C", 0, Z14*U14) -> 200.2 | AC14: =Z14*U14 -> 200.2 | AE14: 24090 | AF14: 0 | AG14: =(AC14*AE14+BO14+BP14+BQ14+BS14)*AF14 -> 0 | AI14: =(AC14*AE14+AG14+BF14+BG14+BH14+BJ14)*AH14 -> 0 | AJ14: IN231027082720 | AK14: 45226 | AO14: SEA | AQ14: 23/10/2023 | AV14: 105946807302 | AW14: 45269 | AX14: 09/12/2023 | BA14: Xong | BB14: BÌNH PHÚ | BC14: 45269 | BD14: Lô 2 | BE14: {=IF(BD14="","",AC14/SUMPRODUCT(--(BD14=$BD$4:$BD$12824),$AC$4:$AC$12824))} -> 0.02232952 | BO14: =VLOOKUP(BD14,$BD$4:$BN$12824,3,0)*BE14 -> 473309.01 | BR14: =VLOOKUP(BD14,$BD$4:$BN$12824,6,0)*BE14 -> 237745.08 | BS14: =VLOOKUP(BD14,$BD$4:$BN$12824,7,0)*BE14 -> 10048.284 | BU14: =VLOOKUP(BD14,$BD$4:$BN$12824,9,0)*BE14 -> 11164.76 | BW14: =VLOOKUP(BD14,$BD$4:$BN$12824,11,0)*BE14 -> 42202.793 | BX14: =SUM(BO14:BW14) -> 774469.92 | BY14: =(AB14*AE14+AG14+BX14)/U14 -> 2798644 | BZ14: =BY14*U14 -> 5597287.9 | CA14: =_xlfn.MAXIFS($BY$4:$BY$12824,$S$4:$S$12824,$S14) -> 2798644 | CF14: =AC14*AE14 -> 4822818
B15: Done | C15: NINE UNITED | D15: SC-NINE UNITED-120923-Ms Thao & Stock | E15: =D15 -> SC-NINE UNITED-120923-Ms Thao & Stock | F15: 45181 | G15: &Tradition | H15: STOCK | L15: 100% BEFORE PICK UP | M15: EXW | O15: DECOR LIGHTING | P15: Table lamp | R15: 20718901 | S15: LTLAT00002 | T15: Đèn trang trí FLOWERPOT VP9,công nghệ LED,(Phi 16 x cao 29.5)cm,3W 2700K,bằng PC và thép,Màu be (Grey Beige).Hiệu:&Tradition.Model:20718901.Mới 100% | U15: 2 | V15: USD | X15: =W15*U15 -> 0 | Z15: 100.1 | AB15: =IF(AA15="F.O.C", 0, Z15*U15) -> 200.2 | AC15: =Z15*U15 -> 200.2 | AE15: 24090 | AF15: 0 | AG15: =(AC15*AE15+BO15+BP15+BQ15+BS15)*AF15 -> 0 | AI15: =(AC15*AE15+AG15+BF15+BG15+BH15+BJ15)*AH15 -> 0 | AJ15: IN231027082720 | AK15: 45226 | AO15: SEA | AQ15: 23/10/2023 | AV15: 105946807302 | AW15: 45269 | AX15: 09/12/2023 | BA15: Xong | BB15: BÌNH PHÚ | BC15: 45269 | BD15: Lô 2 | BE15: {=IF(BD15="","",AC15/SUMPRODUCT(--(BD15=$BD$4:$BD$12824),$AC$4:$AC$12824))} -> 0.02232952 | BO15: =VLOOKUP(BD15,$BD$4:$BN$12824,3,0)*BE15 -> 473309.01 | BR15: =VLOOKUP(BD15,$BD$4:$BN$12824,6,0)*BE15 -> 237745.08 | BS15: =VLOOKUP(BD15,$BD$4:$BN$12824,7,0)*BE15 -> 10048.284 | BU15: =VLOOKUP(BD15,$BD$4:$BN$12824,9,0)*BE15 -> 11164.76 | BW15: =VLOOKUP(BD15,$BD$4:$BN$12824,11,0)*BE15 -> 42202.793 | BX15: =SUM(BO15:BW15) -> 774469.92 | BY15: =(AB15*AE15+AG15+BX15)/U15 -> 2798644 | BZ15: =BY15*U15 -> 5597287.9 | CA15: =_xlfn.MAXIFS($BY$4:$BY$12824,$S$4:$S$12824,$S15) -> 4101317.8 | CF15: =AC15*AE15 -> 4822818
B16: Done | C16: NINE UNITED | D16: SC-NINE UNITED-120923-Ms Thao & Stock | E16: =D16 -> SC-NINE UNITED-120923-Ms Thao & Stock | F16: 45181 | G16: &Tradition | H16: STOCK | L16: 100% BEFORE PICK UP | M16: EXW | O16: DECOR LIGHTING | P16: Table lamp | R16: 20719201 | S16: LTLAT00001 | T16: Đèn trang trí FLOWERPOT VP9,công nghệ LED,(Phi 16 x cao 29.5)cm,3W 2700K,bằng PC và thép,Màu Lục(Signal Green).Hiệu:&Tradition.Model:20719201.Mới 100% | U16: 6 | V16: USD | X16: =W16*U16 -> 0 | Z16: 100.1 | AB16: =IF(AA16="F.O.C", 0, Z16*U16) -> 600.6 | AC16: =Z16*U16 -> 600.6 | AE16: 24090 | AF16: 0 | AG16: =(AC16*AE16+BO16+BP16+BQ16+BS16)*AF16 -> 0 | AI16: =(AC16*AE16+AG16+BF16+BG16+BH16+BJ16)*AH16 -> 0 | AJ16: IN231027082720 | AK16: 45226 | AO16: SEA | AQ16: 23/10/2023 | AV16: 105946807302 | AW16: 45269 | AX16: 09/12/2023 | BA16: Xong | BB16: BÌNH PHÚ | BC16: 45269 | BD16: Lô 2 | BE16: {=IF(BD16="","",AC16/SUMPRODUCT(--(BD16=$BD$4:$BD$12824),$AC$4:$AC$12824))} -> 0.06698856 | BO16: =VLOOKUP(BD16,$BD$4:$BN$12824,3,0)*BE16 -> 1419927 | BR16: =VLOOKUP(BD16,$BD$4:$BN$12824,6,0)*BE16 -> 713235.23 | BS16: =VLOOKUP(BD16,$BD$4:$BN$12824,7,0)*BE16 -> 30144.852 | BU16: =VLOOKUP(BD16,$BD$4:$BN$12824,9,0)*BE16 -> 33494.28 | BW16: =VLOOKUP(BD16,$BD$4:$BN$12824,11,0)*BE16 -> 126608.38 | BX16: =SUM(BO16:BW16) -> 2323409.8 | BY16: =(AB16*AE16+AG16+BX16)/U16 -> 2798644 | BZ16: =BY16*U16 -> 16791864 | CA16: =_xlfn.MAXIFS($BY$4:$BY$12824,$S$4:$S$12824,$S16) -> 4101317.8 | CF16: =AC16*AE16 -> 14468454
B17: Done | C17: NINE UNITED | D17: SC-NINE UNITED-120923-Ms Thao & Stock | E17: =D17 -> SC-NINE UNITED-120923-Ms Thao & Stock | F17: 45181 | G17: &Tradition | H17: STOCK | L17: 100% BEFORE PICK UP | M17: EXW | O17: FURNITURE | P17: table | R17: 86202005 | S17: TBLAT00003 | T17: Bàn LATO, LN8, Phi 40 x H50 cm, Mặt Bàn tròn bằng kim loại màu trắng Ivory White , Bệ Đá Crema Diva Marble.Hiệu:&Tradition.Model:86202005, 1SET= 1 MẶT BÀN+ 1 CHÂN BÀN.Mới 100% | U17: 1 | V17: USD | X17: =W17*U17 -> 0 | Z17: 251.9 | AB17: =IF(AA17="F.O.C", 0, Z17*U17) -> 251.9 | AC17: =Z17*U17 -> 251.9 | AE17: 24090 | AF17: 0.05 | AG17: =(AC17*AE17+BO17+BP17+BQ17+BS17)*AF17 -> 333822.57 | AI17: =(AC17*AE17+AG17+BF17+BG17+BH17+BJ17)*AH17 -> 0 | AJ17: IN231027082720 | AK17: 45226 | AO17: SEA | AQ17: 23/10/2023 | AV17: 105946807302 | AW17: 45269 | AX17: 09/12/2023 | BA17: Xong | BB17: BÌNH PHÚ | BC17: 45150 | BD17: Lô 2 | BE17: {=IF(BD17="","",AC17/SUMPRODUCT(--(BD17=$BD$4:$BD$12824),$AC$4:$AC$12824))} -> 0.028095934 | BO17: =VLOOKUP(BD17,$BD$4:$BN$12824,3,0)*BE17 -> 595537.16 | BR17: =VLOOKUP(BD17,$BD$4:$BN$12824,6,0)*BE17 -> 299140.79 | BS17: =VLOOKUP(BD17,$BD$4:$BN$12824,7,0)*BE17 -> 12643.17 | BU17: =VLOOKUP(BD17,$BD$4:$BN$12824,9,0)*BE17 -> 14047.967 | BW17: =VLOOKUP(BD17,$BD$4:$BN$12824,11,0)*BE17 -> 53101.316 | BX17: =SUM(BO17:BW17) -> 974470.4 | BY17: =(AB17*AE17+AG17+BX17)/U17 -> 7376564 | BZ17: =BY17*U17 -> 7376564 | CA17: =_xlfn.MAXIFS($BY$4:$BY$12824,$S$4:$S$12824,$S17) -> 7376564 | CF17: =AC17*AE17 -> 6068271
B18: Done | C18: NINE UNITED | D18: SC-NINE UNITED-120923-Ms Thao & Stock | E18: =D18 -> SC-NINE UNITED-120923-Ms Thao & Stock | F18: 45181 | G18: &Tradition | H18: STOCK | L18: 100% BEFORE PICK UP | M18: EXW | O18: FURNITURE | P18: table | R18: 86202015 | S18: TBLAT00004 | T18: Bàn LATO, LN9, L50 x W40 x H45 cm, Mặt Bàn bằng kim loại màu trắng Ivory White , Bệ Đá Crema Diva Marble.Hiệu:&Tradition.Model:86202015 .1SET= 1 MẶT BÀN+ 1 CHÂN BÀN.Mới 100% | U18: 1 | V18: USD | X18: =W18*U18 -> 0 | Z18: 251.9 | AB18: =IF(AA18="F.O.C", 0, Z18*U18) -> 251.9 | AC18: =Z18*U18 -> 251.9 | AE18: 24090 | AF18: 0.05 | AG18: =(AC18*AE18+BO18+BP18+BQ18+BS18)*AF18 -> 333822.57 | AI18: =(AC18*AE18+AG18+BF18+BG18+BH18+BJ18)*AH18 -> 0 | AJ18: IN231027082720 | AK18: 45226 | AO18: SEA | AQ18: 23/10/2023 | AV18: 105946807302 | AW18: 45269 | AX18: 09/12/2023 | BA18: Xong | BB18: BÌNH PHÚ | BC18: 45150 | BD18: Lô 2 | BE18: {=IF(BD18="","",AC18/SUMPRODUCT(--(BD18=$BD$4:$BD$12824),$AC$4:$AC$12824))} -> 0.028095934 | BO18: =VLOOKUP(BD18,$BD$4:$BN$12824,3,0)*BE18 -> 595537.16 | BR18: =VLOOKUP(BD18,$BD$4:$BN$12824,6,0)*BE18 -> 299140.79 | BS18: =VLOOKUP(BD18,$BD$4:$BN$12824,7,0)*BE18 -> 12643.17 | BU18: =VLOOKUP(BD18,$BD$4:$BN$12824,9,0)*BE18 -> 14047.967 | BW18: =VLOOKUP(BD18,$BD$4:$BN$12824,11,0)*BE18 -> 53101.316 | BX18: =SUM(BO18:BW18) -> 974470.4 | BY18: =(AB18*AE18+AG18+BX18)/U18 -> 7376564 | BZ18: =BY18*U18 -> 7376564 | CA18: =_xlfn.MAXIFS($BY$4:$BY$12824,$S$4:$S$12824,$S18) -> 7376564 | CF18: =AC18*AE18 -> 6068271
B19: Done | C19: NINE UNITED | D19: SC-NINE UNITED-120923-Ms Thao & Stock | E19: =D19 -> SC-NINE UNITED-120923-Ms Thao & Stock | F19: 45181 | G19: HAY | H19: STOCK | L19: 100% BEFORE PICK UP | M19: EXW | O19: ACCESSORIES | P19: Vase | R19: 508041 | S19: ACCHA00236 | T19: Bình Hoa Bottoms Up Vase S, H21 x W11 x L11 cm, Bằng thủy tinh, Màu xanh Electric Blue.Hiệu:HAY.Model:508041.Mới 100% | U19: 4 | V19: USD | X19: =W19*U19 -> 0 | Z19: 31.6 | AB19: =IF(AA19="F.O.C", 0, Z19*U19) -> 126.4 | AC19: =Z19*U19 -> 126.4 | AE19: 24090 | AF19: 0.15 | AG19: =(AC19*AE19+BO19+BP19+BQ19+BS19)*AF19 -> 502522.89 | AI19: =(AC19*AE19+AG19+BF19+BG19+BH19+BJ19)*AH19 -> 0 | AJ19: IN231027082720 | AK19: 45226 | AO19: SEA | AQ19: 23/10/2023 | AV19: 105946807302 | AW19: 45269 | AX19: 09/12/2023 | BA19: Xong | BB19: BÌNH PHÚ | BC19: 45150 | BD19: Lô 2 | BE19: {=IF(BD19="","",AC19/SUMPRODUCT(--(BD19=$BD$4:$BD$12824),$AC$4:$AC$12824))} -> 0.014098158 | BO19: =VLOOKUP(BD19,$BD$4:$BN$12824,3,0)*BE19 -> 298832.46 | BR19: =VLOOKUP(BD19,$BD$4:$BN$12824,6,0)*BE19 -> 150104.78 | BS19: =VLOOKUP(BD19,$BD$4:$BN$12824,7,0)*BE19 -> 6344.1713 | BU19: =VLOOKUP(BD19,$BD$4:$BN$12824,9,0)*BE19 -> 7049.0792 | BW19: =VLOOKUP(BD19,$BD$4:$BN$12824,11,0)*BE19 -> 26645.519 | BX19: =SUM(BO19:BW19) -> 488976.02 | BY19: =(AB19*AE19+AG19+BX19)/U19 -> 1009118.7 | BZ19: =BY19*U19 -> 4036474.9 | CA19: =_xlfn.MAXIFS($BY$4:$BY$12824,$S$4:$S$12824,$S19) -> 1009118.7 | CF19: =AC19*AE19 -> 3044976
B20: Done | C20: NINE UNITED | D20: SC-NINE UNITED-120923-Ms Thao & Stock | E20: =D20 -> SC-NINE UNITED-120923-Ms Thao & Stock | F20: 45181 | G20: HAY | H20: STOCK | L20: 100% BEFORE PICK UP | M20: EXW | O20: ACCESSORIES | P20: Organizer | R20: 541441 | S20: ACCHA00227 | T20: Hộp Đa Năng COLOUR CRATE, Cỡ S, L26.5 x W17 x H10.5 cm, Bằngnhựa recycled PP, Màu xanh Dusty blue.Hiệu:HAY.Model:541441.Mới 100% | U20: 24 | V20: USD | X20: =W20*U20 -> 0 | Z20: 2.4 | AB20: =IF(AA20="F.O.C", 0, Z20*U20) -> 57.6 | AC20: =Z20*U20 -> 57.6 | AE20: 24090 | AF20: 0 | AG20: =(AC20*AE20+BO20+BP20+BQ20+BS20)*AF20 -> 0 | AI20: =(AC20*AE20+AG20+BF20+BG20+BH20+BJ20)*AH20 -> 0 | AJ20: IN231027082720 | AK20: 45226 | AO20: SEA | AQ20: 23/10/2023 | AV20: 105946807302 | AW20: 45269 | AX20: 09/12/2023 | BA20: Xong | BB20: BÌNH PHÚ | BC20: 45150 | BD20: Lô 2 | BE20: {=IF(BD20="","",AC20/SUMPRODUCT(--(BD20=$BD$4:$BD$12824),$AC$4:$AC$12824))} -> 0.0064244773 | BO20: =VLOOKUP(BD20,$BD$4:$BN$12824,3,0)*BE20 -> 136176.82 | BR20: =VLOOKUP(BD20,$BD$4:$BN$12824,6,0)*BE20 -> 68402.18 | BS20: =VLOOKUP(BD20,$BD$4:$BN$12824,7,0)*BE20 -> 2891.0148 | BU20: =VLOOKUP(BD20,$BD$4:$BN$12824,9,0)*BE20 -> 3212.2386 | BW20: =VLOOKUP(BD20,$BD$4:$BN$12824,11,0)*BE20 -> 12142.262 | BX20: =SUM(BO20:BW20) -> 222824.51 | BY20: =(AB20*AE20+AG20+BX20)/U20 -> 67100.355 | BZ20: =BY20*U20 -> 1610408.5 | CA20: =_xlfn.MAXIFS($BY$4:$BY$12824,$S$4:$S$12824,$S20) -> 67100.355 | CF20: =AC20*AE20 -> 1387584
... B38: Done | C38: NINE UNITED | D38: SC-NINE UNITED-120923-Ms Thao & Stock | E38: =D38 -> SC-NINE UNITED-120923-Ms Thao & Stock | F38: 45181 | G38: HAY | H38: STOCK | L38: 100% BEFORE PICK UP | M38: EXW | O38: ACCESSORIES | P38: Organizer | R38: 542170 | S38: ACCHA00222 | T38: Hộp Đa Năng COLOUR CRATE, Cỡ M, L40 x W30 x H14.5 cm, Bằng nhựa recycled PP, Màu hỗn hợp Mix Powder.Hiệu:HAY.Model:542170.Mới 100% | U38: 12 | V38: USD | X38: =W38*U38 -> 0 | Z38: 6 | AB38: =IF(AA38="F.O.C", 0, Z38*U38) -> 72 | AC38: =Z38*U38 -> 72 | AE38: 24090 | AF38: 0 | AG38: =(AC38*AE38+BO38+BP38+BQ38+BS38)*AF38 -> 0 | AI38: =(AC38*AE38+AG38+BF38+BG38+BH38+BJ38)*AH38 -> 0 | AJ38: IN231027082720 | AK38: 45226 | AO38: SEA | AQ38: 23/10/2023 | AV38: 105946807302 | AW38: 45269 | AX38: 09/12/2023 | BA38: Xong | BB38: BÌNH PHÚ | BC38: 45150 | BD38: Lô 2 | BE38: {=IF(BD38="","",AC38/SUMPRODUCT(--(BD38=$BD$4:$BD$12824),$AC$4:$AC$12824))} -> 0.0080305966 | BO38: =VLOOKUP(BD38,$BD$4:$BN$12824,3,0)*BE38 -> 170221.02 | BR38: =VLOOKUP(BD38,$BD$4:$BN$12824,6,0)*BE38 -> 85502.725 | BS38: =VLOOKUP(BD38,$BD$4:$BN$12824,7,0)*BE38 -> 3613.7685 | BU38: =VLOOKUP(BD38,$BD$4:$BN$12824,9,0)*BE38 -> 4015.2983 | BW38: =VLOOKUP(BD38,$BD$4:$BN$12824,11,0)*BE38 -> 15177.828 | BX38: =SUM(BO38:BW38) -> 278530.64 | BY38: =(AB38*AE38+AG38+BX38)/U38 -> 167750.89 | BZ38: =BY38*U38 -> 2013010.6 | CA38: =_xlfn.MAXIFS($BY$4:$BY$12824,$S$4:$S$12824,$S38) -> 167750.89 | CF38: =AC38*AE38 -> 1734480
B39: Done | C39: NINE UNITED | D39: SC-Nine United-271023- DH-00014531303 | E39: =D39 -> SC-Nine United-271023- DH-00014531303 | F39: 45226 | G39: HAY | H39: PRE-ORDER | I39: DH-0001453 | J39: 24/10/2023 | K39: 20/12/2023 | L39: 100% BEFORE PICK UP | M39: EXW | O39: FURNITURE | P39: Chairs | R39: AA610-A237 | S39: OUTHA00013 | T39: Ghế PALISSADE BENCH, Kích thước (Dài 120 x Rộng 42 x Cao 45) cm, Bằng Thép, Màu lục (OLIVE).Hiệu:HAY.Model:AA610-A237.Mới 100% | U39: 16 | V39: USD | X39: =W39*U39 -> 0 | Z39: 148.77 | AB39: =IF(AA39="F.O.C", 0, Z39*U39) -> 2380.32 | AC39: =Z39*U39 -> 2380.32 | AE39: 24090 | AF39: 0 | AG39: =(AC39*AE39+BO39+BP39+BQ39+BS39)*AF39 -> 0 | AI39: =(AC39*AE39+AG39+BF39+BG39+BH39+BJ39)*AH39 -> 0 | AJ39: IN231027082720 | AK39: 45226 | AO39: SEA | AQ39: 23/10/2023 | AV39: 105946807302 | AW39: 45269 | AX39: 09/12/2023 | BA39: Xong | BB39: BÌNH PHÚ | BC39: 45150 | BD39: Lô 2 | BE39: {=IF(BD39="","",AC39/SUMPRODUCT(--(BD39=$BD$4:$BD$12824),$AC$4:$AC$12824))} -> 0.26549152 | BO39: =VLOOKUP(BD39,$BD$4:$BN$12824,3,0)*BE39 -> 5627507 | BR39: =VLOOKUP(BD39,$BD$4:$BN$12824,6,0)*BE39 -> 2826720.1 | BS39: =VLOOKUP(BD39,$BD$4:$BN$12824,7,0)*BE39 -> 119471.19 | BU39: =VLOOKUP(BD39,$BD$4:$BN$12824,9,0)*BE39 -> 132745.76 | BW39: =VLOOKUP(BD39,$BD$4:$BN$12824,11,0)*BE39 -> 501778.98 | BX39: =SUM(BO39:BW39) -> 9208223 | BY39: =(AB39*AE39+AG39+BX39)/U39 -> 4159383.2 | BZ39: =BY39*U39 -> 66550132 | CA39: =_xlfn.MAXIFS($BY$4:$BY$12824,$S$4:$S$12824,$S39) -> 4159383.2 | CF39: =AC39*AE39 -> 57341909
B40: Done | C40: NINE UNITED | D40: SC-Nine United-271023- DH-00014531303 | E40: =D40 -> SC-Nine United-271023- DH-00014531303 | F40: 45226 | G40: &Tradition | H40: PRE-ORDER | I40: DH-0001453 | J40: 24/10/2023 | K40: 20/12/2023 | L40: 100% BEFORE PICK UP | M40: EXW | O40: DECOR LIGHTING | P40: pendant | R40: 200600 | S40: LPLAT00004 | T40: Đèn thả Mega Bulb SR2, DI18 x H23cm, Bằng Thủy tinh, Sứ, màu Vàng, dây nhựa Trong suốt (không kèm bóng).Hiệu:&Tradition.Model:200600.Mới 100% | U40: 2 | V40: USD | X40: =W40*U40 -> 0 | Z40: 92.4 | AB40: =IF(AA40="F.O.C", 0, Z40*U40) -> 184.8 | AC40: =Z40*U40 -> 184.8 | AE40: 24090 | AF40: 0 | AG40: =(AC40*AE40+BO40+BP40+BQ40+BS40)*AF40 -> 0 | AI40: =(AC40*AE40+AG40+BF40+BG40+BH40+BJ40)*AH40 -> 0 | AJ40: IN231027082720 | AK40: 45226 | AO40: SEA | AQ40: 23/10/2023 | AV40: 105946807302 | AW40: 45269 | AX40: 09/12/2023 | BA40: Xong | BB40: BÌNH PHÚ | BC40: 45150 | BD40: Lô 2 | BE40: {=IF(BD40="","",AC40/SUMPRODUCT(--(BD40=$BD$4:$BD$12824),$AC$4:$AC$12824))} -> 0.020611865 | BO40: =VLOOKUP(BD40,$BD$4:$BN$12824,3,0)*BE40 -> 436900.62 | BR40: =VLOOKUP(BD40,$BD$4:$BN$12824,6,0)*BE40 -> 219457 | BS40: =VLOOKUP(BD40,$BD$4:$BN$12824,7,0)*BE40 -> 9275.339 | BU40: =VLOOKUP(BD40,$BD$4:$BN$12824,9,0)*BE40 -> 10305.932 | BW40: =VLOOKUP(BD40,$BD$4:$BN$12824,11,0)*BE40 -> 38956.424 | BX40: =SUM(BO40:BW40) -> 714895.31 | BY40: =(AB40*AE40+AG40+BX40)/U40 -> 2583363.7 | BZ40: =BY40*U40 -> 5166727.3 | CA40: =_xlfn.MAXIFS($BY$4:$BY$12824,$S$4:$S$12824,$S40) -> 2583363.7 | CF40: =AC40*AE40 -> 4451832
B41: Done | C41: FLOS | D41: SC-FLOS-110923-STOCK&MR HIEN | E41: =D41 -> SC-FLOS-110923-STOCK&MR HIEN | F41: 45180 | G41: FLOS | H41: STOCK | L41: 100% BEFORE PICK UP | M41: EXW | O41: DECOR LIGHTING | P41: pendant | R41: F9800009 | S41: LPLFL00046 | T41: Đèn Trang Trí ZEPPELIN 1, Phi 1100 x H740 mm, không kèm bóng, màu trắng, hiệu: FLOS. Model: F9800009. mới 100%. | U41: 2 | V41: EUR | X41: =W41*U41 -> 0 | Z41: 1893.65 | AB41: =IF(AA41="F.O.C", 0, Z41*U41) -> 3787.3 | AC41: =Z41*U41 -> 3787.3 | AE41: 26199.57 | AF41: 0 | AG41: =(AC41*AE41+BO41+BP41+BQ41+BS41)*AF41 -> 0 | AI41: =(AC41*AE41+AG41+BF41+BG41+BH41+BJ41)*AH41 -> 0 | AJ41: 2303002821 | AK41: 45203 | AO41: SEA | AQ41: 23/10/2023 | AV41: 105938436551 | AW41: 45266 | AX41: 06/12/2023 | BA41: Xong | BB41: BÌNH PHÚ | BC41: 45150 | BD41: Lô 3 | BE41: {=IF(BD41="","",AC41/SUMPRODUCT(--(BD41=$BD$4:$BD$12824),$AC$4:$AC$12824))} -> 0.38016894 | BF41: 7649033 | BI41: 5093772 | BN41: 600000 | BO41: =VLOOKUP(BD41,$BD$4:$BN$12824,3,0)*BE41 -> 2907924.8 | BR41: =VLOOKUP(BD41,$BD$4:$BN$12824,6,0)*BE41 -> 1936493.9 | BS41: =VLOOKUP(BD41,$BD$4:$BN$12824,7,0)*BE41 -> 0 | BU41: =VLOOKUP(BD41,$BD$4:$BN$12824,9,0)*BE41 -> 0 | BW41: =VLOOKUP(BD41,$BD$4:$BN$12824,11,0)*BE41 -> 228101.36 | BX41: =SUM(BO41:BW41) -> 5072520 | BY41: =(AB41*AE41+AG41+BX41)/U41 -> 52149076 | BZ41: =BY41*U41 -> 1.0429815e+08 | CA41: =_xlfn.MAXIFS($BY$4:$BY$12824,$S$4:$S$12824,$S41) -> 52511523 | CF41: =AC41*AE41 -> 99225631
B42: Done | C42: FLOS | D42: SC-FLOS-110923-STOCK&MR HIEN | E42: =D42 -> SC-FLOS-110923-STOCK&MR HIEN | F42: 45180 | G42: FLOS | H42: STOCK | L42: 100% BEFORE PICK UP | M42: EXW | O42: DECOR LIGHTING | P42: pendant | R42: F8001009 | S42: LPLFL00045 | T42: Đèn trang trí Viscontea, Phi 68 cm x H49 cm, không kèm bóng, bằng thép, cocoon, màu trắng. Hiệu: FLOS. Model: F8001009. mới 100%. | U42: 4 | V42: EUR | X42: =W42*U42 -> 0 | Z42: 811.25 | AB42: =IF(AA42="F.O.C", 0, Z42*U42) -> 3245 | AC42: =Z42*U42 -> 3245 | AE42: 26199.57 | AF42: 0 | AG42: =(AC42*AE42+BO42+BP42+BQ42+BS42)*AF42 -> 0 | AI42: =(AC42*AE42+AG42+BF42+BG42+BH42+BJ42)*AH42 -> 0 | AJ42: 2303002821 | AK42: 45203 | AO42: SEA | AQ42: 23/10/2023 | AV42: 105938436551 | AW42: 45266 | AX42: 06/12/2023 | BA42: Xong | BB42: BÌNH PHÚ | BC42: 45150 | BD42: Lô 3 | BE42: {=IF(BD42="","",AC42/SUMPRODUCT(--(BD42=$BD$4:$BD$12824),$AC$4:$AC$12824))} -> 0.3257329 | BO42: =VLOOKUP(BD42,$BD$4:$BN$12824,3,0)*BE42 -> 2491541.7 | BR42: =VLOOKUP(BD42,$BD$4:$BN$12824,6,0)*BE42 -> 1659209.1 | BS42: =VLOOKUP(BD42,$BD$4:$BN$12824,7,0)*BE42 -> 0 | BU42: =VLOOKUP(BD42,$BD$4:$BN$12824,9,0)*BE42 -> 0 | BW42: =VLOOKUP(BD42,$BD$4:$BN$12824,11,0)*BE42 -> 195439.74 | BX42: =SUM(BO42:BW42) -> 4346190.6 | BY42: =(AB42*AE42+AG42+BX42)/U42 -> 22340949 | BZ42: =BY42*U42 -> 89363795 | CA42: =_xlfn.MAXIFS($BY$4:$BY$12824,$S$4:$S$12824,$S42) -> 22340949 | CF42: =AC42*AE42 -> 85017605
B43: Done | C43: FLOS | D43: SC-FLOS-110923-STOCK&MR HIEN | E43: =D43 -> SC-FLOS-110923-STOCK&MR HIEN | F43: 45180 | G43: FLOS | H43: STOCK | L43: 100% BEFORE PICK UP | M43: EXW | O43: DECOR LIGHTING | P43: pendant | R43: F7402009 | S43: LPLFL00051 | T43: Đèn Thả TARAXACUM S2, phi 870 x H640 mm, Không kèm bóng, Khung Kim Loại, Cocoon, Màu Trắng Bianco White.Hiệu: FLOS, Model: F7402009, mới 100%. | U43: 1 | V43: EUR | X43: =W43*U43 -> 0 | Z43: 1036.75 | AB43: =IF(AA43="F.O.C", 0, Z43*U43) -> 1036.75 | AC43: =Z43*U43 -> 1036.75 | AE43: 26199.57 | AF43: 0 | AG43: =(AC43*AE43+BO43+BP43+BQ43+BS43)*AF43 -> 0 | AI43: =(AC43*AE43+AG43+BF43+BG43+BH43+BJ43)*AH43 -> 0 | AJ43: 2303002821 | AK43: 45203 | AO43: SEA | AQ43: 23/10/2023 | AV43: 105938436551 | AW43: 45266 | AX43: 06/12/2023 | BA43: Xong | BB43: BÌNH PHÚ | BC43: 45150 | BD43: Lô 3 | BE43: {=IF(BD43="","",AC43/SUMPRODUCT(--(BD43=$BD$4:$BD$12824),$AC$4:$AC$12824))} -> 0.1040689 | BO43: =VLOOKUP(BD43,$BD$4:$BN$12824,3,0)*BE43 -> 796026.46 | BR43: =VLOOKUP(BD43,$BD$4:$BN$12824,6,0)*BE43 -> 530103.25 | BS43: =VLOOKUP(BD43,$BD$4:$BN$12824,7,0)*BE43 -> 0 | BU43: =VLOOKUP(BD43,$BD$4:$BN$12824,9,0)*BE43 -> 0 | BW43: =VLOOKUP(BD43,$BD$4:$BN$12824,11,0)*BE43 -> 62441.34 | BX43: =SUM(BO43:BW43) -> 1388571 | BY43: =(AB43*AE43+AG43+BX43)/U43 -> 28550975 | BZ43: =BY43*U43 -> 28550975 | CA43: =_xlfn.MAXIFS($BY$4:$BY$12824,$S$4:$S$12824,$S43) -> 29844310 | CF43: =AC43*AE43 -> 27162404
B44: Done | C44: FLOS | D44: SC-FLOS-110923-STOCK&MR HIEN | E44: =D44 -> SC-FLOS-110923-STOCK&MR HIEN | F44: 45180 | G44: FLOS | H44: STOCK | L44: 100% BEFORE PICK UP | M44: EXW | O44: DECOR LIGHTING | P44: Floor lamp | R44: F1590056 | S44: LFLFL00025 | T44: Đèn Sàn CHIARA F, Phi 720 x L1450 mm, Không kèm bóng, Bằng Thép Stainless, Màu Trắng Viền Đen.Hiệu: FLOS, Model: F1590056, mới 100% | U44: 2 | V44: EUR | X44: =W44*U44 -> 0 | Z44: 946.55 | AB44: =IF(AA44="F.O.C", 0, Z44*U44) -> 1893.1 | AC44: =Z44*U44 -> 1893.1 | AE44: 26199.57 | AF44: 0 | AG44: =(AC44*AE44+BO44+BP44+BQ44+BS44)*AF44 -> 0 | AI44: =(AC44*AE44+AG44+BF44+BG44+BH44+BJ44)*AH44 -> 0 | AJ44: 2303002821 | AK44: 45203 | AO44: SEA | AQ44: 23/10/2023 | AV44: 105938436551 | AW44: 45266 | AX44: 06/12/2023 | BA44: Xong | BB44: BÌNH PHÚ | BC44: 45150 | BD44: Lô 3 | BE44: {=IF(BD44="","",AC44/SUMPRODUCT(--(BD44=$BD$4:$BD$12824),$AC$4:$AC$12824))} -> 0.19002926 | BO44: =VLOOKUP(BD44,$BD$4:$BN$12824,3,0)*BE44 -> 1453540.1 | BR44: =VLOOKUP(BD44,$BD$4:$BN$12824,6,0)*BE44 -> 967965.73 | BS44: =VLOOKUP(BD44,$BD$4:$BN$12824,7,0)*BE44 -> 0 | BU44: =VLOOKUP(BD44,$BD$4:$BN$12824,9,0)*BE44 -> 0 | BW44: =VLOOKUP(BD44,$BD$4:$BN$12824,11,0)*BE44 -> 114017.56 | BX44: =SUM(BO44:BW44) -> 2535523.4 | BY44: =(AB44*AE44+AG44+BX44)/U44 -> 26066965 | BZ44: =BY44*U44 -> 52133929 | CA44: =_xlfn.MAXIFS($BY$4:$BY$12824,$S$4:$S$12824,$S44) -> 26066965 | CF44: =AC44*AE44 -> 49598406
B45: Done | C45: USM | D45: SC-USM-15-220823-A TAI&CAMPAIGN | E45: =D45 -> SC-USM-15-220823-A TAI&CAMPAIGN | F45: 45160 | G45: USM | H45: STOCK | L45: 100% BEFORE PICK UP | M45: FCA | O45: FURNITURE | P45: Cabinet | R45: USMUS00368 | S45: USMUS00368 | T45: Tủ nội thất văn phòng USM HALLER, USMUS00368, Kích thước (dài 773 x rộng 373 x cao 1090 mm), Bằng Kim loại, Màu Olive. Hiệu USM | U45: 1 | V45: EUR | X45: =W45*U45 -> 0 | Z45: 746.2 | AB45: =IF(AA45="F.O.C", 0, Z45*U45) -> 746.2 | AC45: =Z45*U45 -> 746.2 | AE45: 25889.59 | AF45: 0.1 | AG45: =(AC45*AE45+BO45+BP45+BQ45+BS45)*AF45 -> 2499664.6 | AI45: =(AC45*AE45+AG45+BF45+BG45+BH45+BJ45)*AH45 -> 0 | AJ45: 102083254 | AK45: 45244 | AO45: AIR | AQ45: 17/11/2023 | AV45: 105902755340 | AW45: 45252 | AX45: 22/11/2023 | BA45: Xong | BB45: BÌNH PHÚ | BC45: 45253 | BD45: Lô 4 | BE45: {=IF(BD45="","",AC45/SUMPRODUCT(--(BD45=$BD$4:$BD$12824),$AC$4:$AC$12824))} -> 0.28697572 | BF45: 19785068 | BI45: =(486480+851340+ 467360) -> 1805180 | BN45: 600000 | BO45: =VLOOKUP(BD45,$BD$4:$BN$12824,3,0)*BE45 -> 5677834.1 | BR45: =VLOOKUP(BD45,$BD$4:$BN$12824,6,0)*BE45 -> 518042.83 | BS45: =VLOOKUP(BD45,$BD$4:$BN$12824,7,0)*BE45 -> 0 | BU45: =VLOOKUP(BD45,$BD$4:$BN$12824,9,0)*BE45 -> 0 | BW45: =VLOOKUP(BD45,$BD$4:$BN$12824,11,0)*BE45 -> 172185.43 | BX45: =SUM(BO45:BW45) -> 6368062.3 | BY45: =(AB45*AE45+AG45+BX45)/U45 -> 28186539 | BZ45: =BY45*U45 -> 28186539 | CA45: =_xlfn.MAXIFS($BY$4:$BY$12824,$S$4:$S$12824,$S45) -> 28186539 | CF45: =AC45*AE45 -> 19318812
B46: Done | C46: USM | D46: SC-USM-15-220823-A TAI&CAMPAIGN | E46: =D46 -> SC-USM-15-220823-A TAI&CAMPAIGN | F46: 45160 | G46: USM | H46: STOCK | L46: 100% BEFORE PICK UP | M46: FCA | O46: FURNITURE | P46: Cabinet | R46: USMUS00367 | S46: USMUS00367 | T46: Tủ nội thất văn phòng USM HALLER, USMUS00367, Kích thước (dài 1523 x rộng 373 x cao 740 mm), Bằng Kim loại, Màu Olive. Hiệu USM | U46: 1 | V46: EUR | X46: =W46*U46 -> 0 | Z46: 946.75 | AB46: =IF(AA46="F.O.C", 0, Z46*U46) -> 946.75 | AC46: =Z46*U46 -> 946.75 | AE46: 25889.59 | AF46: 0.1 | AG46: =(AC46*AE46+BO46+BP46+BQ46+BS46)*AF46 -> 3171478.8 | AI46: =(AC46*AE46+AG46+BF46+BG46+BH46+BJ46)*AH46 -> 0 | AJ46: 102083254 | AK46: 45244 | AO46: AIR | AQ46: 17/11/2023 | AV46: 105902755340 | AW46: 45252 | AX46: 22/11/2023 | BA46: Xong | BB46: BÌNH PHÚ | BC46: 45253 | BD46: Lô 4 | BE46: {=IF(BD46="","",AC46/SUMPRODUCT(--(BD46=$BD$4:$BD$12824),$AC$4:$AC$12824))} -> 0.36410381 | BO46: =VLOOKUP(BD46,$BD$4:$BN$12824,3,0)*BE46 -> 7203818.6 | BR46: =VLOOKUP(BD46,$BD$4:$BN$12824,6,0)*BE46 -> 657272.91 | BS46: =VLOOKUP(BD46,$BD$4:$BN$12824,7,0)*BE46 -> 0 | BU46: =VLOOKUP(BD46,$BD$4:$BN$12824,9,0)*BE46 -> 0 | BW46: =VLOOKUP(BD46,$BD$4:$BN$12824,11,0)*BE46 -> 218462.28 | BX46: =SUM(BO46:BW46) -> 8079553.8 | BY46: =(AB46*AE46+AG46+BX46)/U46 -> 35762002 | BZ46: =BY46*U46 -> 35762002 | CA46: =_xlfn.MAXIFS($BY$4:$BY$12824,$S$4:$S$12824,$S46) -> 35762002 | CF46: =AC46*AE46 -> 24510969
B47: Done | C47: USM | D47: SC-USM-15-220823-A TAI&CAMPAIGN | E47: =D47 -> SC-USM-15-220823-A TAI&CAMPAIGN | F47: 45160 | G47: USM | H47: STOCK | L47: 100% BEFORE PICK UP | M47: FCA | O47: FURNITURE | P47: Cabinet | R47: USMUS00369 | S47: USMUS00369 | T47: Tủ nội thất văn phòng USM HALLER, USMUS00369, Kích thước (dài 1523 x rộng 373 x cao 610 mm), Bằng Kim loại, Màu Olive. Hiệu USM | U47: 1 | V47: EUR | X47: =W47*U47 -> 0 | Z47: 671.66 | AB47: =IF(AA47="F.O.C", 0, Z47*U47) -> 671.66 | AC47: =Z47*U47 -> 671.66 | AE47: 25889.59 | AF47: 0.1 | AG47: =(AC47*AE47+BO47+BP47+BQ47+BS47)*AF47 -> 2249966.1 | AI47: =(AC47*AE47+AG47+BF47+BG47+BH47+BJ47)*AH47 -> 0 | AJ47: 102083254 | AK47: 45244 | AO47: AIR | AQ47: 17/11/2023 | AV47: 105902755340 | AW47: 45252 | AX47: 22/11/2023 | BA47: Xong | BB47: BÌNH PHÚ | BC47: 45253 | BD47: Lô 4 | BE47: {=IF(BD47="","",AC47/SUMPRODUCT(--(BD47=$BD$4:$BD$12824),$AC$4:$AC$12824))} -> 0.25830891 | BO47: =VLOOKUP(BD47,$BD$4:$BN$12824,3,0)*BE47 -> 5110659.4 | BR47: =VLOOKUP(BD47,$BD$4:$BN$12824,6,0)*BE47 -> 466294.08 | BS47: =VLOOKUP(BD47,$BD$4:$BN$12824,7,0)*BE47 -> 0 | BU47: =VLOOKUP(BD47,$BD$4:$BN$12824,9,0)*BE47 -> 0 | BW47: =VLOOKUP(BD47,$BD$4:$BN$12824,11,0)*BE47 -> 154985.35 | BX47: =SUM(BO47:BW47) -> 5731938.8 | BY47: =(AB47*AE47+AG47+BX47)/U47 -> 25370907 | BZ47: =BY47*U47 -> 25370907 | CA47: =_xlfn.MAXIFS($BY$4:$BY$12824,$S$4:$S$12824,$S47) -> 25370907 | CF47: =AC47*AE47 -> 17389002
B48: Done | C48: USM | D48: SC-USM-15-220823-A TAI&CAMPAIGN | E48: =D48 -> SC-USM-15-220823-A TAI&CAMPAIGN | F48: 45160 | G48: USM | H48: STOCK | L48: 100% BEFORE PICK UP | M48: FCA | O48: FURNITURE | P48: Cabinet | R48: USMUS10171 | S48: USMUS10171 | T48: Kệ văn phòng USM HALLER có bánh xe,USMUS10171,Kích thước (D523xR373xC605 mm), Bằng Kim loại, Màu Trắng (Pure White), Cam (Pure Orange). Hiệu USM | U48: 1 | V48: EUR | X48: =W48*U48 -> 0 | Z48: 235.61 | AB48: =IF(AA48="F.O.C", 0, Z48*U48) -> 235.61 | AC48: =Z48*U48 -> 235.61 | AE48: 25889.59 | AF48: 0.1 | AG48: =(AC48*AE48+BO48+BP48+BQ48+BS48)*AF48 -> 789260.22 | AI48: =(AC48*AE48+AG48+BF48+BG48+BH48+BJ48)*AH48 -> 0 | AJ48: 102083254 | AK48: 45244 | AO48: AIR | AQ48: 17/11/2023 | AV48: 105902755340 | AW48: 45252 | AX48: 22/11/2023 | BA48: Xong | BB48: BÌNH PHÚ | BC48: 45253 | BD48: Lô 4 | BE48: {=IF(BD48="","",AC48/SUMPRODUCT(--(BD48=$BD$4:$BD$12824),$AC$4:$AC$12824))} -> 0.090611564 | BO48: =VLOOKUP(BD48,$BD$4:$BN$12824,3,0)*BE48 -> 1792755.9 | BR48: =VLOOKUP(BD48,$BD$4:$BN$12824,6,0)*BE48 -> 163570.18 | BS48: =VLOOKUP(BD48,$BD$4:$BN$12824,7,0)*BE48 -> 0 | BU48: =VLOOKUP(BD48,$BD$4:$BN$12824,9,0)*BE48 -> 0 | BW48: =VLOOKUP(BD48,$BD$4:$BN$12824,11,0)*BE48 -> 54366.938 | BX48: =SUM(BO48:BW48) -> 2010693.1 | BY48: =(AB48*AE48+AG48+BX48)/U48 -> 8899799.6 | BZ48: =BY48*U48 -> 8899799.6 | CA48: =_xlfn.MAXIFS($BY$4:$BY$12824,$S$4:$S$12824,$S48) -> 8899799.6 | CF48: =AC48*AE48 -> 6099846.3
B49: Done | C49: USM | D49: SC-USM-290623 | E49: SC-USM-290623 | F49: 45106 | G49: USM | H49: STOCK | L49: 100% BEFORE PICK UP | M49: FCA | O49: FURNITURE | P49: Cabinet | R49: USMUS10007 | S49: USMUS10007 | T49: Tủ nội thất văn phòng USM HALLER, USMUS10007, kích thước (dài 4273 x rộng 1123 x cao 990 mm), bằng Kim loại, màu Vàng (Golden Yellow). Hiệu USM | U49: 1 | V49: EUR | X49: =W49*U49 -> 0 | Z49: 2962.41 | AB49: =IF(AA49="F.O.C", 0, Z49*U49) -> 2962.41 | AC49: =Z49*U49 -> 2962.41 | AE49: 25590.88 | AF49: 0.1 | AG49: =(AC49*AE49+BO49+BP49+BQ49+BS49)*AF49 -> 7794876.3 | AI49: =(AC49*AE49+AG49+BF49+BG49+BH49+BJ49)*AH49 -> 0 | AJ49: 102082282 | AK49: 13/07/2023 | AO49: SEA | AQ49: 03/08/2023 | AV49: 105728943720 | AW49: 45189 | AX49: 20/09/2023 | BA49: Xong | BB49: BÌNH PHÚ | BC49: 45195 | BD49: Lô 5 | BE49: {=IF(BD49="","",AC49/SUMPRODUCT(--(BD49=$BD$4:$BD$12824),$AC$4:$AC$12824))} -> 0.034175753 | BF49: 60393000 | BI49: 4104000 | BJ49: 2168428 | BL49: 500000 | BO49: =VLOOKUP(BD49,$BD$4:$BN$12824,3,0)*BE49 -> 2063976.3 | BR49: =VLOOKUP(BD49,$BD$4:$BN$12824,6,0)*BE49 -> 140257.29 | BS49: =VLOOKUP(BD49,$BD$4:$BN$12824,7,0)*BE49 -> 74107.66 | BU49: =VLOOKUP(BD49,$BD$4:$BN$12824,9,0)*BE49 -> 17087.877 | BW49: =VLOOKUP(BD49,$BD$4:$BN$12824,11,0)*BE49 -> 0 | BX49: =SUM(BO49:BW49) -> 2295429.1 | BY49: =(AB49*AE49+AG49+BX49)/U49 -> 85900984 | BZ49: =BY49*U49 -> 85900984 | CA49: =_xlfn.MAXIFS($BY$4:$BY$12824,$S$4:$S$12824,$S49) -> 85900984 | CF49: =AC49*AE49 -> 75810679
B50: Done | C50: USM | D50: SC-USM-290623 | E50: SC-USM-290623 | F50: 45106 | G50: USM | H50: STOCK | L50: 100% BEFORE PICK UP | M50: FCA | O50: FURNITURE | P50: Cabinet | R50: USMUS10008 | S50: USMUS10008 | T50: Tủ nội thất văn phòng USM HALLER, USMUS10008, kích thước (dài 7019 x rộng 1523 x cao 2490 mm), bằng Kim loại, màu Vàng (Golden Yellow). Hiệu USM | U50: 1 | V50: EUR | X50: =W50*U50 -> 0 | Z50: 7665.29 | AB50: =IF(AA50="F.O.C", 0, Z50*U50) -> 7665.29 | AC50: =Z50*U50 -> 7665.29 | AE50: 25590.88 | AF50: 0.1 | AG50: =(AC50*AE50+BO50+BP50+BQ50+BS50)*AF50 -> 20169385 | AI50: =(AC50*AE50+AG50+BF50+BG50+BH50+BJ50)*AH50 -> 0 | AJ50: 102082282 | AK50: 13/07/2023 | AO50: SEA | AQ50: 03/08/2023 | AV50: 105728943720 | AW50: 45189 | AX50: 20/09/2023 | BA50: Xong | BB50: BÌNH PHÚ | BC50: 45195 | BD50: Lô 5 | BE50: {=IF(BD50="","",AC50/SUMPRODUCT(--(BD50=$BD$4:$BD$12824),$AC$4:$AC$12824))} -> 0.088430386 | BO50: =VLOOKUP(BD50,$BD$4:$BN$12824,3,0)*BE50 -> 5340576.3 | BR50: =VLOOKUP(BD50,$BD$4:$BN$12824,6,0)*BE50 -> 362918.3 | BS50: =VLOOKUP(BD50,$BD$4:$BN$12824,7,0)*BE50 -> 191754.93 | BU50: =VLOOKUP(BD50,$BD$4:$BN$12824,9,0)*BE50 -> 44215.193 | BW50: =VLOOKUP(BD50,$BD$4:$BN$12824,11,0)*BE50 -> 0 | BX50: =SUM(BO50:BW50) -> 5939464.7 | BY50: =(AB50*AE50+AG50+BX50)/U50 -> 2.2227037e+08 | BZ50: =BY50*U50 -> 2.2227037e+08 | CA50: =_xlfn.MAXIFS($BY$4:$BY$12824,$S$4:$S$12824,$S50) -> 2.2227037e+08 | CF50: =AC50*AE50 -> 1.9616152e+08
B51: Done | C51: USM | D51: SC-USM-290623 | E51: SC-USM-290623 | F51: 45106 | G51: USM | H51: STOCK | L51: 100% BEFORE PICK UP | M51: FCA | O51: FURNITURE | P51: Cabinet | R51: USMUS10009 | S51: USMUS10009 | T51: Tủ nội thất văn phòng USM HALLER, USMUS10009, kích thước (dài 4373 x rộng 1873 x cao 2140 mm), bằng Kim loại, màu Trắng (Pure White), màu Vàng (Golden Yellow), màu Đen (Graphite Black). Hiệu USM | U51: 1 | V51: EUR | X51: =W51*U51 -> 0 | Z51: 2935.7 | AB51: =IF(AA51="F.O.C", 0, Z51*U51) -> 2935.7 | AC51: =Z51*U51 -> 2935.7 | AE51: 25590.88 | AF51: 0.1 | AG51: =(AC51*AE51+BO51+BP51+BQ51+BS51)*AF51 -> 7724595.3 | AI51: =(AC51*AE51+AG51+BF51+BG51+BH51+BJ51)*AH51 -> 0 | AJ51: 102082282 | AK51: 13/07/2023 | AO51: SEA | AQ51: 03/08/2023 | AV51: 105728943720 | AW51: 45189 | AX51: 20/09/2023 | BA51: Xong | BB51: BÌNH PHÚ | BC51: 45195 | BD51: Lô 5 | BE51: {=IF(BD51="","",AC51/SUMPRODUCT(--(BD51=$BD$4:$BD$12824),$AC$4:$AC$12824))} -> 0.033867614 | BO51: =VLOOKUP(BD51,$BD$4:$BN$12824,3,0)*BE51 -> 2045366.8 | BR51: =VLOOKUP(BD51,$BD$4:$BN$12824,6,0)*BE51 -> 138992.69 | BS51: =VLOOKUP(BD51,$BD$4:$BN$12824,7,0)*BE51 -> 73439.483 | BU51: =VLOOKUP(BD51,$BD$4:$BN$12824,9,0)*BE51 -> 16933.807 | BW51: =VLOOKUP(BD51,$BD$4:$BN$12824,11,0)*BE51 -> 0 | BX51: =SUM(BO51:BW51) -> 2274732.8 | BY51: =(AB51*AE51+AG51+BX51)/U51 -> 85126474 | BZ51: =BY51*U51 -> 85126474 | CA51: =_xlfn.MAXIFS($BY$4:$BY$12824,$S$4:$S$12824,$S51) -> 85126474 | CF51: =AC51*AE51 -> 75127146
B52: Done | C52: USM | D52: SC-USM-290623 | E52: SC-USM-290623 | F52: 45106 | G52: USM | H52: STOCK | L52: 100% BEFORE PICK UP | M52: FCA | O52: FURNITURE | P52: Cabinet | R52: USMUS10010 | S52: USMUS10010 | T52: Tủ nội thất văn phòng USM HALLER, USMUS10010, kích thước (dài 1523 x rộng 373 x cao 1090 mm), bằng Kim loại, màu Trắng (Pure White), màu Vàng (Golden Yellow), màu Đen (Graphite Black). Hiệu USM | U52: 1 | V52: EUR | X52: =W52*U52 -> 0 | Z52: 849.3 | AB52: =IF(AA52="F.O.C", 0, Z52*U52) -> 849.3 | AC52: =Z52*U52 -> 849.3 | AE52: 25590.88 | AF52: 0.1 | AG52: =(AC52*AE52+BO52+BP52+BQ52+BS52)*AF52 -> 2234730.6 | AI52: =(AC52*AE52+AG52+BF52+BG52+BH52+BJ52)*AH52 -> 0 | AJ52: 102082282 | AK52: 13/07/2023 | AO52: SEA | AQ52: 03/08/2023 | AV52: 105728943720 | AW52: 45189 | AX52: 20/09/2023 | BA52: Xong | BB52: BÌNH PHÚ | BC52: 45195 | BD52: Lô 5 | BE52: {=IF(BD52="","",AC52/SUMPRODUCT(--(BD52=$BD$4:$BD$12824),$AC$4:$AC$12824))} -> 0.0097979237 | BO52: =VLOOKUP(BD52,$BD$4:$BN$12824,3,0)*BE52 -> 591726.01 | BR52: =VLOOKUP(BD52,$BD$4:$BN$12824,6,0)*BE52 -> 40210.679 | BS52: =VLOOKUP(BD52,$BD$4:$BN$12824,7,0)*BE52 -> 21246.092 | BU52: =VLOOKUP(BD52,$BD$4:$BN$12824,9,0)*BE52 -> 4898.9619 | BW52: =VLOOKUP(BD52,$BD$4:$BN$12824,11,0)*BE52 -> 0 | BX52: =SUM(BO52:BW52) -> 658081.74 | BY52: =(AB52*AE52+AG52+BX52)/U52 -> 24627147 | BZ52: =BY52*U52 -> 24627147 | CA52: =_xlfn.MAXIFS($BY$4:$BY$12824,$S$4:$S$12824,$S52) -> 24627147 | CF52: =AC52*AE52 -> 21734334
B53: Done | C53: USM | D53: SC-USM-290623 | E53: SC-USM-290623 | F53: 45106 | G53: USM | H53: STOCK | L53: 100% BEFORE PICK UP | M53: FCA | O53: FURNITURE | P53: Cabinet | R53: USMUS10011 | S53: USMUS10011 | T53: Tủ nội thất văn phòng USM HALLER, USMUS10011, kích thước (dài 2273 x rộng 373 x cao 1090 mm), bằng Kim loại, màu Xám (Anthracite). Hiệu USM | U53: 1 | V53: EUR | X53: =W53*U53 -> 0 | Z53: 826.37 | AB53: =IF(AA53="F.O.C", 0, Z53*U53) -> 826.37 | AC53: =Z53*U53 -> 826.37 | AE53: 25590.88 | AF53: 0.1 | AG53: =(AC53*AE53+BO53+BP53+BQ53+BS53)*AF53 -> 2174395.8 | AI53: =(AC53*AE53+AG53+BF53+BG53+BH53+BJ53)*AH53 -> 0 | AJ53: 102082282 | AK53: 13/07/2023 | AO53: SEA | AQ53: 03/08/2023 | AV53: 105728943720 | AW53: 45189 | AX53: 20/09/2023 | BA53: Xong | BB53: BÌNH PHÚ | BC53: 45195 | BD53: Lô 5 | BE53: {=IF(BD53="","",AC53/SUMPRODUCT(--(BD53=$BD$4:$BD$12824),$AC$4:$AC$12824))} -> 0.0095333925 | BO53: =VLOOKUP(BD53,$BD$4:$BN$12824,3,0)*BE53 -> 575750.17 | BR53: =VLOOKUP(BD53,$BD$4:$BN$12824,6,0)*BE53 -> 39125.043 | BS53: =VLOOKUP(BD53,$BD$4:$BN$12824,7,0)*BE53 -> 20672.475 | BU53: =VLOOKUP(BD53,$BD$4:$BN$12824,9,0)*BE53 -> 4766.6962 | BW53: =VLOOKUP(BD53,$BD$4:$BN$12824,11,0)*BE53 -> 0 | BX53: =SUM(BO53:BW53) -> 640314.39 | BY53: =(AB53*AE53+AG53+BX53)/U53 -> 23962246 | BZ53: =BY53*U53 -> 23962246 | CA53: =_xlfn.MAXIFS($BY$4:$BY$12824,$S$4:$S$12824,$S53) -> 23962246 | CF53: =AC53*AE53 -> 21147536
B54: Done | C54: USM | D54: SC-USM-290623 | E54: SC-USM-290623 | F54: 45106 | G54: USM | H54: STOCK | L54: 100% BEFORE PICK UP | M54: FCA | O54: FURNITURE | P54: Cabinet | R54: USMUS00220 | S54: USMUS00220 | T54: Tủ nội thất văn phòng USM HALLER, USMUS00220, kích thước (dài 1523 x rộng 373 x cao 740 mm), bằng Kim loại, màu Be (USM Beige). Hiệu USM | U54: 1 | V54: EUR | X54: =W54*U54 -> 0 | Z54: 767.53 | AB54: =IF(AA54="F.O.C", 0, Z54*U54) -> 767.53 | AC54: =Z54*U54 -> 767.53 | AE54: 25590.88 | AF54: 0.1 | AG54: =(AC54*AE54+BO54+BP54+BQ54+BS54)*AF54 -> 2019572.4 | AI54: =(AC54*AE54+AG54+BF54+BG54+BH54+BJ54)*AH54 -> 0 | AJ54: 102082282 | AK54: 13/07/2023 | AO54: SEA | AQ54: 03/08/2023 | AV54: 105728943720 | AW54: 45189 | AX54: 20/09/2023 | BA54: Xong | BB54: BÌNH PHÚ | BC54: 45195 | BD54: Lô 5 | BE54: {=IF(BD54="","",AC54/SUMPRODUCT(--(BD54=$BD$4:$BD$12824),$AC$4:$AC$12824))} -> 0.0088545866 | BO54: =VLOOKUP(BD54,$BD$4:$BN$12824,3,0)*BE54 -> 534755.05 | BR54: =VLOOKUP(BD54,$BD$4:$BN$12824,6,0)*BE54 -> 36339.223 | BS54: =VLOOKUP(BD54,$BD$4:$BN$12824,7,0)*BE54 -> 19200.534 | BU54: =VLOOKUP(BD54,$BD$4:$BN$12824,9,0)*BE54 -> 4427.2933 | BW54: =VLOOKUP(BD54,$BD$4:$BN$12824,11,0)*BE54 -> 0 | BX54: =SUM(BO54:BW54) -> 594722.1 | BY54: =(AB54*AE54+AG54+BX54)/U54 -> 22256063 | BZ54: =BY54*U54 -> 22256063 | CA54: =_xlfn.MAXIFS($BY$4:$BY$12824,$S$4:$S$12824,$S54) -> 25848825 | CF54: =AC54*AE54 -> 19641768
B55: Done | C55: USM | D55: SC-USM-290623 | E55: SC-USM-290623 | F55: 45106 | G55: USM | H55: STOCK | L55: 100% BEFORE PICK UP | M55: FCA | O55: FURNITURE | P55: Cabinet | R55: USMUS00311 | S55: USMUS00311 | T55: Bàn văn phòng USM HALLER, USMUS00311, kích thước (dài 1750 x rộng 750 x cao 740 mm), Mặt Fenix, khung Kim loại, màu Trắng (Bianco Kos). Hiệu USM | U55: 6 | V55: EUR | X55: =W55*U55 -> 0 | Z55: 605.08 | AB55: =IF(AA55="F.O.C", 0, Z55*U55) -> 3630.48 | AC55: =Z55*U55 -> 3630.48 | AE55: 25590.88 | AF55: 0.1 | AG55: =(AC55*AE55+BO55+BP55+BQ55+BS55)*AF55 -> 9552743.3 | AI55: =(AC55*AE55+AG55+BF55+BG55+BH55+BJ55)*AH55 -> 0 | AJ55: 102082282 | AK55: 13/07/2023 | AO55: SEA | AQ55: 03/08/2023 | AV55: 105728943720 | AW55: 45189 | AX55: 20/09/2023 | BA55: Xong | BB55: BÌNH PHÚ | BC55: 45195 | BD55: Lô 5 | BE55: {=IF(BD55="","",AC55/SUMPRODUCT(--(BD55=$BD$4:$BD$12824),$AC$4:$AC$12824))} -> 0.041882923 | BO55: =VLOOKUP(BD55,$BD$4:$BN$12824,3,0)*BE55 -> 2529435.3 | BR55: =VLOOKUP(BD55,$BD$4:$BN$12824,6,0)*BE55 -> 171887.51 | BS55: =VLOOKUP(BD55,$BD$4:$BN$12824,7,0)*BE55 -> 90820.102 | BU55: =VLOOKUP(BD55,$BD$4:$BN$12824,9,0)*BE55 -> 20941.461 | BW55: =VLOOKUP(BD55,$BD$4:$BN$12824,11,0)*BE55 -> 0 | BX55: =SUM(BO55:BW55) -> 2813084.4 | BY55: =(AB55*AE55+AG55+BX55)/U55 -> 17545501 | BZ55: =BY55*U55 -> 1.0527301e+08 | CA55: =_xlfn.MAXIFS($BY$4:$BY$12824,$S$4:$S$12824,$S55) -> 17545501 | CF55: =AC55*AE55 -> 92907178
B56: Done | C56: USM | D56: SC-USM-290623 | E56: SC-USM-290623 | F56: 45106 | G56: USM | H56: STOCK | L56: 100% BEFORE PICK UP | M56: FCA | O56: FURNITURE | P56: Cabinet | R56: USMUS10013 | S56: USMUS10013 | T56: Tủ nội thất văn phòng USM HALLER, USMUS10013, kích thước (dài 3063 x rộng 373 x cao 2490 mm), bằng Kim loại, màu Xanh Gentian (Gentian Blue). Hiệu USM | U56: 1 | V56: EUR | X56: =W56*U56 -> 0 | Z56: 2234.88 | AB56: =IF(AA56="F.O.C", 0, Z56*U56) -> 2234.88 | AC56: =Z56*U56 -> 2234.88 | AE56: 25590.88 | AF56: 0.1 | AG56: =(AC56*AE56+BO56+BP56+BQ56+BS56)*AF56 -> 5880554.4 | AI56: =(AC56*AE56+AG56+BF56+BG56+BH56+BJ56)*AH56 -> 0 | AJ56: 102082282 | AK56: 13/07/2023 | AO56: SEA | AQ56: 03/08/2023 | AV56: 105728943720 | AW56: 45189 | AX56: 20/09/2023 | BA56: Xong | BB56: BÌNH PHÚ | BC56: 45195 | BD56: Lô 5 | BE56: {=IF(BD56="","",AC56/SUMPRODUCT(--(BD56=$BD$4:$BD$12824),$AC$4:$AC$12824))} -> 0.025782625 | BO56: =VLOOKUP(BD56,$BD$4:$BN$12824,3,0)*BE56 -> 1557090.1 | BR56: =VLOOKUP(BD56,$BD$4:$BN$12824,6,0)*BE56 -> 105811.89 | BS56: =VLOOKUP(BD56,$BD$4:$BN$12824,7,0)*BE56 -> 55907.767 | BU56: =VLOOKUP(BD56,$BD$4:$BN$12824,9,0)*BE56 -> 12891.313 | BW56: =VLOOKUP(BD56,$BD$4:$BN$12824,11,0)*BE56 -> 0 | BX56: =SUM(BO56:BW56) -> 1731701.1 | BY56: =(AB56*AE56+AG56+BX56)/U56 -> 64804801 | BZ56: =BY56*U56 -> 64804801 | CA56: =_xlfn.MAXIFS($BY$4:$BY$12824,$S$4:$S$12824,$S56) -> 64804801 | CF56: =AC56*AE56 -> 57192546
B57: Done | C57: USM | D57: SC-USM-290623 | E57: SC-USM-290623 | F57: 45106 | G57: USM | H57: STOCK | L57: 100% BEFORE PICK UP | M57: FCA | O57: FURNITURE | P57: Cabinet | R57: USMUS10014 | S57: USMUS10014 | T57: Tủ nội thất văn phòng USM HALLER, USMUS10014, kích thước (dài 2523 x rộng 373 x cao 2140 mm), bằng Kim loại, màu Xám (USM Mid-Gray). Hiệu USM | U57: 1 | V57: EUR | X57: =W57*U57 -> 0 | Z57: 1556.33 | AB57: =IF(AA57="F.O.C", 0, Z57*U57) -> 1556.33 | AC57: =Z57*U57 -> 1556.33 | AE57: 25590.88 | AF57: 0.1 | AG57: =(AC57*AE57+BO57+BP57+BQ57+BS57)*AF57 -> 4095111.7 | AI57: =(AC57*AE57+AG57+BF57+BG57+BH57+BJ57)*AH57 -> 0 | AJ57: 102082282 | AK57: 13/07/2023 | AO57: SEA | AQ57: 03/08/2023 | AV57: 105728943720 | AW57: 45189 | AX57: 20/09/2023 | BA57: Xong | BB57: BÌNH PHÚ | BC57: 45195 | BD57: Lô 5 | BE57: {=IF(BD57="","",AC57/SUMPRODUCT(--(BD57=$BD$4:$BD$12824),$AC$4:$AC$12824))} -> 0.017954554 | BO57: =VLOOKUP(BD57,$BD$4:$BN$12824,3,0)*BE57 -> 1084329.4 | BR57: =VLOOKUP(BD57,$BD$4:$BN$12824,6,0)*BE57 -> 73685.489 | BS57: =VLOOKUP(BD57,$BD$4:$BN$12824,7,0)*BE57 -> 38933.157 | BU57: =VLOOKUP(BD57,$BD$4:$BN$12824,9,0)*BE57 -> 8977.277 | BW57: =VLOOKUP(BD57,$BD$4:$BN$12824,11,0)*BE57 -> 0 | BX57: =SUM(BO57:BW57) -> 1205925.3 | BY57: =(AB57*AE57+AG57+BX57)/U57 -> 45128891 | BZ57: =BY57*U57 -> 45128891 | CA57: =_xlfn.MAXIFS($BY$4:$BY$12824,$S$4:$S$12824,$S57) -> 45128891 | CF57: =AC57*AE57 -> 39827854
B58: Done | C58: USM | D58: SC-USM-290623 | E58: SC-USM-290623 | F58: 45106 | G58: USM | H58: STOCK | L58: 100% BEFORE PICK UP | M58: FCA | O58: FURNITURE | P58: Cabinet | R58: USMUS10001 | S58: USMUS10001 | T58: Kệ nội thất văn phòng USM HALLER, USMUS10001, kích thước (dài 5523 x rộng 1073 x cao 2040 mm), bằng Kim loại, màu Cam (Pure Orange). Hiệu USM | U58: 1 | V58: EUR | X58: =W58*U58 -> 0 | Z58: 4889.76 | AB58: =IF(AA58="F.O.C", 0, Z58*U58) -> 4889.76 | AC58: =Z58*U58 -> 4889.76 | AE58: 25590.88 | AF58: 0.1 | AG58: =(AC58*AE58+BO58+BP58+BQ58+BS58)*AF58 -> 12866239 | AI58: =(AC58*AE58+AG58+BF58+BG58+BH58+BJ58)*AH58 -> 0 | AJ58: 102082282 | AK58: 13/07/2023 | AO58: SEA | AQ58: 03/08/2023 | AV58: 105728943720 | AW58: 45189 | AX58: 20/09/2023 | BA58: Xong | BB58: BÌNH PHÚ | BC58: 45195 | BD58: Lô 5 | BE58: {=IF(BD58="","",AC58/SUMPRODUCT(--(BD58=$BD$4:$BD$12824),$AC$4:$AC$12824))} -> 0.056410568 | BO58: =VLOOKUP(BD58,$BD$4:$BN$12824,3,0)*BE58 -> 3406803.4 | BR58: =VLOOKUP(BD58,$BD$4:$BN$12824,6,0)*BE58 -> 231508.97 | BS58: =VLOOKUP(BD58,$BD$4:$BN$12824,7,0)*BE58 -> 122322.26 | BU58: =VLOOKUP(BD58,$BD$4:$BN$12824,9,0)*BE58 -> 28205.284 | BW58: =VLOOKUP(BD58,$BD$4:$BN$12824,11,0)*BE58 -> 0 | BX58: =SUM(BO58:BW58) -> 3788840 | BY58: =(AB58*AE58+AG58+BX58)/U58 -> 1.4178834e+08 | BZ58: =BY58*U58 -> 1.4178834e+08 | CA58: =_xlfn.MAXIFS($BY$4:$BY$12824,$S$4:$S$12824,$S58) -> 1.4178834e+08 | CF58: =AC58*AE58 -> 1.2513326e+08
B59: Done | C59: USM | D59: SC-USM-290623 | E59: SC-USM-290623 | F59: 45106 | G59: USM | H59: STOCK | L59: 100% BEFORE PICK UP | M59: FCA | O59: FURNITURE | P59: Cabinet | R59: USMUS10002 | S59: USMUS10002 | T59: Kệ nội thất văn phòng USM HALLER, USMUS10002,dài 4523xrộng523x cao2335xmm,bằng Kim loại,màu Bạc Silver(USM Matte Silver),Be (USM Beige),Xám (USM Mid-Gray),Trắng (Pure White),Cam(Pure Orange). Hiệu USM | U59: 1 | V59: EUR | X59: =W59*U59 -> 0 | Z59: 3944.7 | AB59: =IF(AA59="F.O.C", 0, Z59*U59) -> 3944.7 | AC59: =Z59*U59 -> 3944.7 | AE59: 25590.88 | AF59: 0.1 | AG59: =(AC59*AE59+BO59+BP59+BQ59+BS59)*AF59 -> 10379538 | AI59: =(AC59*AE59+AG59+BF59+BG59+BH59+BJ59)*AH59 -> 0 | AJ59: 102082282 | AK59: 13/07/2023 | AO59: SEA | AQ59: 03/08/2023 | AV59: 105728943720 | AW59: 45189 | AX59: 20/09/2023 | BA59: Xong | BB59: BÌNH PHÚ | BC59: 45195 | BD59: Lô 5 | BE59: {=IF(BD59="","",AC59/SUMPRODUCT(--(BD59=$BD$4:$BD$12824),$AC$4:$AC$12824))} -> 0.045507912 | BO59: =VLOOKUP(BD59,$BD$4:$BN$12824,3,0)*BE59 -> 2748359.3 | BR59: =VLOOKUP(BD59,$BD$4:$BN$12824,6,0)*BE59 -> 186764.47 | BS59: =VLOOKUP(BD59,$BD$4:$BN$12824,7,0)*BE59 -> 98680.631 | BU59: =VLOOKUP(BD59,$BD$4:$BN$12824,9,0)*BE59 -> 22753.956 | BW59: =VLOOKUP(BD59,$BD$4:$BN$12824,11,0)*BE59 -> 0 | BX59: =SUM(BO59:BW59) -> 3056558.4 | BY59: =(AB59*AE59+AG59+BX59)/U59 -> 1.1438444e+08 | BZ59: =BY59*U59 -> 1.1438444e+08 | CA59: =_xlfn.MAXIFS($BY$4:$BY$12824,$S$4:$S$12824,$S59) -> 1.1438444e+08 | CF59: =AC59*AE59 -> 1.0094834e+08
B60: Done | C60: USM | D60: SC-USM-290623 | E60: SC-USM-290623 | F60: 45106 | G60: USM | H60: STOCK | L60: 100% BEFORE PICK UP | M60: FCA | O60: FURNITURE | P60: Cabinet | R60: USMUS10015 | S60: USMUS10015 | T60: Tủ văn phòng USM HALLER, USMUS10015,(dài 2773xrộng373x cao 990)mm,bằng Kim loại,Thủy tinh,màu Trong suốt (Transparent),Cam(Pure Orange),Xám(USM Mid-Gray),Bạc Silver(USM Matte Silver),Trắng(Pure White) | U60: 1 | V60: EUR | X60: =W60*U60 -> 0 | Z60: 1613.7 | AB60: =IF(AA60="F.O.C", 0, Z60*U60) -> 1613.7 | AC60: =Z60*U60 -> 1613.7 | AE60: 25590.88 | AF60: 0.1 | AG60: =(AC60*AE60+BO60+BP60+BQ60+BS60)*AF60 -> 4246067.2 | AI60: =(AC60*AE60+AG60+BF60+BG60+BH60+BJ60)*AH60 -> 0 | AJ60: 102082282 | AK60: 13/07/2023 | AO60: SEA | AQ60: 03/08/2023 | AV60: 105728943720 | AW60: 45189 | AX60: 20/09/2023 | BA60: Xong | BB60: BÌNH PHÚ | BC60: 45195 | BD60: Lô 5 | BE60: {=IF(BD60="","",AC60/SUMPRODUCT(--(BD60=$BD$4:$BD$12824),$AC$4:$AC$12824))} -> 0.018616401 | BO60: =VLOOKUP(BD60,$BD$4:$BN$12824,3,0)*BE60 -> 1124300.3 | BR60: =VLOOKUP(BD60,$BD$4:$BN$12824,6,0)*BE60 -> 76401.71 | BS60: =VLOOKUP(BD60,$BD$4:$BN$12824,7,0)*BE60 -> 40368.326 | BU60: =VLOOKUP(BD60,$BD$4:$BN$12824,9,0)*BE60 -> 9308.2006 | BW60: =VLOOKUP(BD60,$BD$4:$BN$12824,11,0)*BE60 -> 0 | BX60: =SUM(BO60:BW60) -> 1250378.6 | BY60: =(AB60*AE60+AG60+BX60)/U60 -> 46792449 | BZ60: =BY60*U60 -> 46792449 | CA60: =_xlfn.MAXIFS($BY$4:$BY$12824,$S$4:$S$12824,$S60) -> 46792449 | CF60: =AC60*AE60 -> 41296003
B61: Done | C61: USM | D61: SC-USM-290623 | E61: SC-USM-290623 | F61: 45106 | G61: USM | H61: STOCK | L61: 100% BEFORE PICK UP | M61: FCA | O61: FURNITURE | P61: Cabinet | R61: USMUS00321 | S61: USMUS00321 | T61: Bàn văn phòng USM Kitos M Plus, USMUS00321, kích thước (dài 1800 x rộng 900 x cao 700-1200 mm), Mặt Fenix, khung Kim loại, màu Trắng (Bianco Kos). Hiệu USM | U61: 1 | V61: EUR | X61: =W61*U61 -> 0 | Z61: 1331 | AB61: =IF(AA61="F.O.C", 0, Z61*U61) -> 1331 | AC61: =Z61*U61 -> 1331 | AE61: 25590.88 | AF61: 0.1 | AG61: =(AC61*AE61+BO61+BP61+BQ61+BS61)*AF61 -> 3502209.5 | AI61: =(AC61*AE61+AG61+BF61+BG61+BH61+BJ61)*AH61 -> 0 | AJ61: 102082282 | AK61: 13/07/2023 | AO61: SEA | AQ61: 03/08/2023 | AV61: 105728943720 | AW61: 45189 | AX61: 20/09/2023 | BA61: Xong | BB61: BÌNH PHÚ | BC61: 45195 | BD61: Lô 5 | BE61: {=IF(BD61="","",AC61/SUMPRODUCT(--(BD61=$BD$4:$BD$12824),$AC$4:$AC$12824))} -> 0.015355041 | BO61: =VLOOKUP(BD61,$BD$4:$BN$12824,3,0)*BE61 -> 927337 | BR61: =VLOOKUP(BD61,$BD$4:$BN$12824,6,0)*BE61 -> 63017.089 | BS61: =VLOOKUP(BD61,$BD$4:$BN$12824,7,0)*BE61 -> 33296.301 | BU61: =VLOOKUP(BD61,$BD$4:$BN$12824,9,0)*BE61 -> 7677.5206 | BW61: =VLOOKUP(BD61,$BD$4:$BN$12824,11,0)*BE61 -> 0 | BX61: =SUM(BO61:BW61) -> 1031327.9 | BY61: =(AB61*AE61+AG61+BX61)/U61 -> 38594999 | BZ61: =BY61*U61 -> 38594999 | CA61: =_xlfn.MAXIFS($BY$4:$BY$12824,$S$4:$S$12824,$S61) -> 38594999 | CF61: =AC61*AE61 -> 34061461
... B90: Done | C90: USM | D90: SC-USM-290623 | E90: SC-USM-290623 | F90: 45106 | G90: USM | H90: STOCK | L90: 100% BEFORE PICK UP | M90: FCA | O90: FURNITURE | P90: Cabinet | R90: USMUS10155 | S90: USMUS10155 | T90: Tủ nội thất văn phòng USM HALLER, USMUS10155, kích thước (dài 1273 x rộng 773 x cao 990 mm), bằng Kim loại, Thủy tinh, màu Lục (USM Green), màu Trắng (Pure White). Hiệu USM, hàng F.O.C | U90: 1 | V90: EUR | X90: =W90*U90 -> 0 | Z90: 1186.2 | AB90: =IF(AA90="F.O.C", 0, Z90*U90) -> 1186.2 | AC90: =Z90*U90 -> 1186.2 | AE90: 25590.88 | AF90: 0.1 | AG90: =(AC90*AE90+BO90+BP90+BQ90+BS90)*AF90 -> 3121202.7 | AI90: =(AC90*AE90+AG90+BF90+BG90+BH90+BJ90)*AH90 -> 0 | AJ90: 102082282 | AK90: 13/07/2023 | AO90: SEA | AQ90: 03/08/2023 | AV90: 105728943720 | AW90: 45189 | AX90: 20/09/2023 | BA90: Xong | BB90: BÌNH PHÚ | BC90: 45195 | BD90: Lô 5 | BE90: {=IF(BD90="","",AC90/SUMPRODUCT(--(BD90=$BD$4:$BD$12824),$AC$4:$AC$12824))} -> 0.01368456 | BO90: =VLOOKUP(BD90,$BD$4:$BN$12824,3,0)*BE90 -> 826451.66 | BR90: =VLOOKUP(BD90,$BD$4:$BN$12824,6,0)*BE90 -> 56161.436 | BS90: =VLOOKUP(BD90,$BD$4:$BN$12824,7,0)*BE90 -> 29673.984 | BU90: =VLOOKUP(BD90,$BD$4:$BN$12824,9,0)*BE90 -> 6842.2802 | BW90: =VLOOKUP(BD90,$BD$4:$BN$12824,11,0)*BE90 -> 0 | BX90: =SUM(BO90:BW90) -> 919129.36 | BY90: =(AB90*AE90+AG90+BX90)/U90 -> 34396234 | BZ90: =BY90*U90 -> 34396234 | CA90: =_xlfn.MAXIFS($BY$4:$BY$12824,$S$4:$S$12824,$S90) -> 34396234 | CF90: =AC90*AE90 -> 30355902
B91: Done | C91: FRITZ HANSEN | D91: SC-FH-01-160323-THAO | E91: SC-FH-01-160323-THAO | F91: 45001 | G91: Fritz Hansen | L91: 100% BEFORE PICK UP | M91: EXW | O91: FURNITURE | P91: Sofa | R91: PL120D120 | S91: SFAFH00035 | T91: Ghế Sofa element PL120-120, Kích thước 120(D) x 120(R) x 40(C) cm, Đã nhồi nệm, bọc vải Karakorum, Màu be (Dune 003), Khung kim loại. Hiệu: FRITZ HANSEN. Model: PL120D120. Mới 100% | U91: 1 | V91: EUR | X91: =W91*U91 -> 0 | Z91: 732.5 | AB91: =IF(AA91="F.O.C", 0, Z91*U91) -> 732.5 | AC91: =Z91*U91 -> 732.5 | AE91: 25628.19 | AF91: 0 | AG91: =(AC91*AE91+BO91+BP91+BQ91+BS91)*AF91 -> 0 | AI91: =(AC91*AE91+AG91+BF91+BG91+BH91+BJ91)*AH91 -> 0 | AJ91: 2092724 | AK91: 16/06/2023 | AO91: SEA | AQ91: 04/07/2023 | AV91: 105654702310 | AW91: 45154 | AX91: 16/08/2023 | BA91: Xong | BB91: BÌNH PHÚ | BC91: 45156 | BD91: Lô 6 | BE91: {=IF(BD91="","",AC91/SUMPRODUCT(--(BD91=$BD$4:$BD$12824),$AC$4:$AC$12824))} -> 0.15225525 | BF91: 11991142 | BI91: 906784 | BJ91: 450000 | BL91: 4101 | BN91: 600000 | BO91: =VLOOKUP(BD91,$BD$4:$BN$12824,3,0)*BE91 -> 1825714.3 | BR91: =VLOOKUP(BD91,$BD$4:$BN$12824,6,0)*BE91 -> 138062.62 | BS91: =VLOOKUP(BD91,$BD$4:$BN$12824,7,0)*BE91 -> 68514.862 | BU91: =VLOOKUP(BD91,$BD$4:$BN$12824,9,0)*BE91 -> 624.39877 | BW91: =VLOOKUP(BD91,$BD$4:$BN$12824,11,0)*BE91 -> 91353.149 | BX91: =SUM(BO91:BW91) -> 2124269.3 | BY91: =(AB91*AE91+AG91+BX91)/U91 -> 20896919 | BZ91: =BY91*U91 -> 20896919 | CA91: =_xlfn.MAXIFS($BY$4:$BY$12824,$S$4:$S$12824,$S91) -> 20896919 | CF91: =AC91*AE91 -> 18772649
B92: Done | C92: FRITZ HANSEN | D92: SC-FH-01-160323-THAO | E92: SC-FH-01-160323-THAO | F92: 45001 | G92: Fritz Hansen | L92: 100% BEFORE PICK UP | M92: EXW | O92: FURNITURE | P92: Sofa | R92: PL90105C | S92: SFAFH00036 | T92: Bọc Ghế Sofa Cover PL90-105, Kích thước 90(D) x 105(R) x 40(C) cm, Đã nhồi nệm, bọc vải Karakorum, Màu be (Dune 003). Hiệu: FRITZ HANSEN. Model: PL90105C. Mới 100% | U92: 1 | V92: EUR | X92: =W92*U92 -> 0 | Z92: 203.5 | AB92: =IF(AA92="F.O.C", 0, Z92*U92) -> 203.5 | AC92: =Z92*U92 -> 203.5 | AE92: 25628.19 | AF92: 0 | AG92: =(AC92*AE92+BO92+BP92+BQ92+BS92)*AF92 -> 0 | AI92: =(AC92*AE92+AG92+BF92+BG92+BH92+BJ92)*AH92 -> 0 | AJ92: 2092724 | AK92: 16/06/2023 | AO92: SEA | AQ92: 04/07/2023 | AV92: 105654702310 | AW92: 45154 | AX92: 16/08/2023 | BA92: Xong | BB92: BÌNH PHÚ | BC92: 45156 | BD92: Lô 6 | BE92: {=IF(BD92="","",AC92/SUMPRODUCT(--(BD92=$BD$4:$BD$12824),$AC$4:$AC$12824))} -> 0.042298898 | BO92: =VLOOKUP(BD92,$BD$4:$BN$12824,3,0)*BE92 -> 507212.1 | BR92: =VLOOKUP(BD92,$BD$4:$BN$12824,6,0)*BE92 -> 38355.964 | BS92: =VLOOKUP(BD92,$BD$4:$BN$12824,7,0)*BE92 -> 19034.504 | BU92: =VLOOKUP(BD92,$BD$4:$BN$12824,9,0)*BE92 -> 173.46778 | BW92: =VLOOKUP(BD92,$BD$4:$BN$12824,11,0)*BE92 -> 25379.339 | BX92: =SUM(BO92:BW92) -> 590155.37 | BY92: =(AB92*AE92+AG92+BX92)/U92 -> 5805492 | BZ92: =BY92*U92 -> 5805492 | CA92: =_xlfn.MAXIFS($BY$4:$BY$12824,$S$4:$S$12824,$S92) -> 5805492 | CF92: =AC92*AE92 -> 5215336.7
B93: Done | C93: FRITZ HANSEN | D93: SC-FH-01-160323-THAO | E93: SC-FH-01-160323-THAO | F93: 45001 | G93: Fritz Hansen | L93: 100% BEFORE PICK UP | M93: EXW | O93: FURNITURE | P93: Sofa | R93: PL90D105 | S93: SFAFH00037 | T93: Ghế Sofa element PL90-105, Kích thước 90(D) x 105(R) x 40(C) cm, Khung kim loại, Hiệu: FRITZ HANSEN. Model: PL90D105. Mới 100% | U93: 1 | V93: EUR | X93: =W93*U93 -> 0 | Z93: 377.5 | AB93: =IF(AA93="F.O.C", 0, Z93*U93) -> 377.5 | AC93: =Z93*U93 -> 377.5 | AE93: 25628.19 | AF93: 0 | AG93: =(AC93*AE93+BO93+BP93+BQ93+BS93)*AF93 -> 0 | AI93: =(AC93*AE93+AG93+BF93+BG93+BH93+BJ93)*AH93 -> 0 | AJ93: 2092724 | AK93: 16/06/2023 | AO93: SEA | AQ93: 04/07/2023 | AV93: 105654702310 | AW93: 45154 | AX93: 16/08/2023 | BA93: Xong | BB93: BÌNH PHÚ | BC93: 45156 | BD93: Lô 6 | BE93: {=IF(BD93="","",AC93/SUMPRODUCT(--(BD93=$BD$4:$BD$12824),$AC$4:$AC$12824))} -> 0.078466015 | BO93: =VLOOKUP(BD93,$BD$4:$BN$12824,3,0)*BE93 -> 940897.13 | BR93: =VLOOKUP(BD93,$BD$4:$BN$12824,6,0)*BE93 -> 71151.727 | BS93: =VLOOKUP(BD93,$BD$4:$BN$12824,7,0)*BE93 -> 35309.707 | BU93: =VLOOKUP(BD93,$BD$4:$BN$12824,9,0)*BE93 -> 321.78913 | BW93: =VLOOKUP(BD93,$BD$4:$BN$12824,11,0)*BE93 -> 47079.609 | BX93: =SUM(BO93:BW93) -> 1094760 | BY93: =(AB93*AE93+AG93+BX93)/U93 -> 10769402 | BZ93: =BY93*U93 -> 10769402 | CA93: =_xlfn.MAXIFS($BY$4:$BY$12824,$S$4:$S$12824,$S93) -> 10769402 | CF93: =AC93*AE93 -> 9674641.7
B94: Done | C94: FRITZ HANSEN | D94: SC-FH-01-160323-THAO | E94: SC-FH-01-160323-THAO | F94: 45001 | G94: Fritz Hansen | L94: 100% BEFORE PICK UP | M94: EXW | O94: FURNITURE | P94: Sofa | R94: PL75D105 | S94: SFAFH00038 | T94: Ghế Sofa element PL75-105, Kích thước 75(D) x 105(R) x 40(C) cm, Đã nhồi nệm, bọc vải Karakorum, Màu be (Dune 003), Khung kim loại. Hiệu: FRITZ HANSEN. Model: PL75D105. Mới 100% | U94: 4 | V94: EUR | X94: =W94*U94 -> 0 | Z94: 528 | AB94: =IF(AA94="F.O.C", 0, Z94*U94) -> 2112 | AC94: =Z94*U94 -> 2112 | AE94: 25628.19 | AF94: 0 | AG94: =(AC94*AE94+BO94+BP94+BQ94+BS94)*AF94 -> 0 | AI94: =(AC94*AE94+AG94+BF94+BG94+BH94+BJ94)*AH94 -> 0 | AJ94: 2092724 | AK94: 16/06/2023 | AO94: SEA | AQ94: 04/07/2023 | AV94: 105654702310 | AW94: 45154 | AX94: 16/08/2023 | BA94: Xong | BB94: BÌNH PHÚ | BC94: 45156 | BD94: Lô 6 | BE94: {=IF(BD94="","",AC94/SUMPRODUCT(--(BD94=$BD$4:$BD$12824),$AC$4:$AC$12824))} -> 0.43899397 | BO94: =VLOOKUP(BD94,$BD$4:$BN$12824,3,0)*BE94 -> 5264039.1 | BR94: =VLOOKUP(BD94,$BD$4:$BN$12824,6,0)*BE94 -> 398072.71 | BS94: =VLOOKUP(BD94,$BD$4:$BN$12824,7,0)*BE94 -> 197547.29 | BU94: =VLOOKUP(BD94,$BD$4:$BN$12824,9,0)*BE94 -> 1800.3143 | BW94: =VLOOKUP(BD94,$BD$4:$BN$12824,11,0)*BE94 -> 263396.38 | BX94: =SUM(BO94:BW94) -> 6124855.8 | BY94: =(AB94*AE94+AG94+BX94)/U94 -> 15062898 | BZ94: =BY94*U94 -> 60251593 | CA94: =_xlfn.MAXIFS($BY$4:$BY$12824,$S$4:$S$12824,$S94) -> 15062898 | CF94: =AC94*AE94 -> 54126737
B95: Done | C95: FRITZ HANSEN | D95: SC-FH-01-160323-THAO | E95: SC-FH-01-160323-THAO | F95: 45001 | G95: Fritz Hansen | L95: 100% BEFORE PICK UP | M95: EXW | O95: FURNITURE | P95: Sofa | R95: PL90D30 | S95: SFAFH00039 | T95: Ghế Sofa element PL90-30 có lưng tựa, Kích thước 90(D) x 30(R) x 30(C) cm, Đã nhồi nệm, bọc vải Karakorum, Màu be (Dune 003),Khung kim loại.Hiệu: FRITZ HANSEN.Model:PL90D30. Mới 100% | U95: 1 | V95: EUR | X95: =W95*U95 -> 0 | Z95: 310 | AB95: =IF(AA95="F.O.C", 0, Z95*U95) -> 310 | AC95: =Z95*U95 -> 310 | AE95: 25628.19 | AF95: 0 | AG95: =(AC95*AE95+BO95+BP95+BQ95+BS95)*AF95 -> 0 | AI95: =(AC95*AE95+AG95+BF95+BG95+BH95+BJ95)*AH95 -> 0 | AJ95: 2092724 | AK95: 16/06/2023 | AO95: SEA | AQ95: 04/07/2023 | AV95: 105654702310 | AW95: 45154 | AX95: 16/08/2023 | BA95: Xong | BB95: BÌNH PHÚ | BC95: 45156 | BD95: Lô 6 | BE95: {=IF(BD95="","",AC95/SUMPRODUCT(--(BD95=$BD$4:$BD$12824),$AC$4:$AC$12824))} -> 0.064435668 | BO95: =VLOOKUP(BD95,$BD$4:$BN$12824,3,0)*BE95 -> 772657.25 | BR95: =VLOOKUP(BD95,$BD$4:$BN$12824,6,0)*BE95 -> 58429.233 | BS95: =VLOOKUP(BD95,$BD$4:$BN$12824,7,0)*BE95 -> 28996.051 | BU95: =VLOOKUP(BD95,$BD$4:$BN$12824,9,0)*BE95 -> 264.25068 | BW95: =VLOOKUP(BD95,$BD$4:$BN$12824,11,0)*BE95 -> 38661.401 | BX95: =SUM(BO95:BW95) -> 899008.18 | BY95: =(AB95*AE95+AG95+BX95)/U95 -> 8843747.1 | BZ95: =BY95*U95 -> 8843747.1 | CA95: =_xlfn.MAXIFS($BY$4:$BY$12824,$S$4:$S$12824,$S95) -> 8843747.1 | CF95: =AC95*AE95 -> 7944738.9
B96: Done | C96: FRITZ HANSEN | D96: SC-FH-01-160323-THAO | E96: SC-FH-01-160323-THAO | F96: 45001 | G96: Fritz Hansen | L96: 100% BEFORE PICK UP | M96: EXW | O96: FURNITURE | P96: Sofa | R96: PL90D90D30 | S96: SFAFH00040 | T96: Ghế Sofa corner element PL90-90-30 có góc và lưng tựa,Kích thước 90(D) x 90(R) x 30(C) cm,Đã nhồi nệm,bọc vải Karakorum,Màu be (Dune 003),Khung kim loại.Hiệu:FRITZ HANSEN.Model: PL90D90D30,mới 100% | U96: 1 | V96: EUR | X96: =W96*U96 -> 0 | Z96: 422.5 | AB96: =IF(AA96="F.O.C", 0, Z96*U96) -> 422.5 | AC96: =Z96*U96 -> 422.5 | AE96: 25628.19 | AF96: 0 | AG96: =(AC96*AE96+BO96+BP96+BQ96+BS96)*AF96 -> 0 | AI96: =(AC96*AE96+AG96+BF96+BG96+BH96+BJ96)*AH96 -> 0 | AJ96: 2092724 | AK96: 16/06/2023 | AO96: SEA | AQ96: 04/07/2023 | AV96: 105654702310 | AW96: 45154 | AX96: 16/08/2023 | BA96: Xong | BB96: BÌNH PHÚ | BC96: 45156 | BD96: Lô 6 | BE96: {=IF(BD96="","",AC96/SUMPRODUCT(--(BD96=$BD$4:$BD$12824),$AC$4:$AC$12824))} -> 0.08781958 | BO96: =VLOOKUP(BD96,$BD$4:$BN$12824,3,0)*BE96 -> 1053057.1 | BR96: =VLOOKUP(BD96,$BD$4:$BN$12824,6,0)*BE96 -> 79633.39 | BS96: =VLOOKUP(BD96,$BD$4:$BN$12824,7,0)*BE96 -> 39518.811 | BU96: =VLOOKUP(BD96,$BD$4:$BN$12824,9,0)*BE96 -> 360.1481 | BW96: =VLOOKUP(BD96,$BD$4:$BN$12824,11,0)*BE96 -> 52691.748 | BX96: =SUM(BO96:BW96) -> 1225261.2 | BY96: =(AB96*AE96+AG96+BX96)/U96 -> 12053171 | BZ96: =BY96*U96 -> 12053171 | CA96: =_xlfn.MAXIFS($BY$4:$BY$12824,$S$4:$S$12824,$S96) -> 12053171 | CF96: =AC96*AE96 -> 10827910
B97: Done | C97: FRITZ HANSEN | D97: SC-FH-01-160323-THAO | E97: SC-FH-01-160323-THAO | F97: 45001 | G97: Fritz Hansen | L97: 100% BEFORE PICK UP | M97: EXW | O97: FURNITURE | P97: Sofa | R97: PL150D30 | S97: SFAFH00041 | T97: Ghế Sofa element PL150-30 có lưng tựa, Kích thước 150(D) x 30(R) x 30(C) cm, Đã nhồi nệm, bọc vải Karakorum, Màu be (Dune 003), Khung kim loại. Hiệu: FRITZ HANSEN. Model: PL150D30. Mới 100% | U97: 1 | V97: EUR | X97: =W97*U97 -> 0 | Z97: 416 | AB97: =IF(AA97="F.O.C", 0, Z97*U97) -> 416 | AC97: =Z97*U97 -> 416 | AE97: 25628.19 | AF97: 0 | AG97: =(AC97*AE97+BO97+BP97+BQ97+BS97)*AF97 -> 0 | AI97: =(AC97*AE97+AG97+BF97+BG97+BH97+BJ97)*AH97 -> 0 | AJ97: 2092724 | AK97: 16/06/2023 | AO97: SEA | AQ97: 04/07/2023 | AV97: 105654702310 | AW97: 45154 | AX97: 16/08/2023 | BA97: Xong | BB97: BÌNH PHÚ | BC97: 45156 | BD97: Lô 6 | BE97: {=IF(BD97="","",AC97/SUMPRODUCT(--(BD97=$BD$4:$BD$12824),$AC$4:$AC$12824))} -> 0.08646851 | BO97: =VLOOKUP(BD97,$BD$4:$BN$12824,3,0)*BE97 -> 1036856.2 | BR97: =VLOOKUP(BD97,$BD$4:$BN$12824,6,0)*BE97 -> 78408.261 | BS97: =VLOOKUP(BD97,$BD$4:$BN$12824,7,0)*BE97 -> 38910.829 | BU97: =VLOOKUP(BD97,$BD$4:$BN$12824,9,0)*BE97 -> 354.60736 | BW97: =VLOOKUP(BD97,$BD$4:$BN$12824,11,0)*BE97 -> 51881.106 | BX97: =SUM(BO97:BW97) -> 1206411 | BY97: =(AB97*AE97+AG97+BX97)/U97 -> 11867738 | BZ97: =BY97*U97 -> 11867738 | CA97: =_xlfn.MAXIFS($BY$4:$BY$12824,$S$4:$S$12824,$S97) -> 11867738 | CF97: =AC97*AE97 -> 10661327
B98: Done | C98: FRITZ HANSEN | D98: SC-FH-01-160323-THAO | E98: SC-FH-01-160323-THAO | F98: 45001 | G98: Fritz Hansen | L98: 100% BEFORE PICK UP | M98: EXW | O98: ACCESSORIES | P98: Cushion | R98: PL001 | S98: SFAFH00042 | T98: Gối Sofa Cushion, AlphabetTM Sofa Series, PL001, Đã nhồi nệm, bọc vải Karakorum, Màu be (Dune 003). Hiệu: FRITZ HANSEN. Model: PL001. Mới 100% | U98: 3 | V98: EUR | X98: =W98*U98 -> 0 | Z98: 79 | AB98: =IF(AA98="F.O.C", 0, Z98*U98) -> 237 | AC98: =Z98*U98 -> 237 | AE98: 25628.19 | AF98: 0 | AG98: =(AC98*AE98+BO98+BP98+BQ98+BS98)*AF98 -> 0 | AI98: =(AC98*AE98+AG98+BF98+BG98+BH98+BJ98)*AH98 -> 0 | AJ98: 2092724 | AK98: 16/06/2023 | AO98: SEA | AQ98: 04/07/2023 | AV98: 105654702310 | AW98: 45154 | AX98: 16/08/2023 | BA98: Xong | BB98: BÌNH PHÚ | BC98: 45156 | BD98: Lô 6 | BE98: {=IF(BD98="","",AC98/SUMPRODUCT(--(BD98=$BD$4:$BD$12824),$AC$4:$AC$12824))} -> 0.049262108 | BO98: =VLOOKUP(BD98,$BD$4:$BN$12824,3,0)*BE98 -> 590708.93 | BR98: =VLOOKUP(BD98,$BD$4:$BN$12824,6,0)*BE98 -> 44670.091 | BS98: =VLOOKUP(BD98,$BD$4:$BN$12824,7,0)*BE98 -> 22167.948 | BU98: =VLOOKUP(BD98,$BD$4:$BN$12824,9,0)*BE98 -> 202.0239 | BW98: =VLOOKUP(BD98,$BD$4:$BN$12824,11,0)*BE98 -> 29557.265 | BX98: =SUM(BO98:BW98) -> 687306.26 | BY98: =(AB98*AE98+AG98+BX98)/U98 -> 2253729.1 | BZ98: =BY98*U98 -> 6761187.3 | CA98: =_xlfn.MAXIFS($BY$4:$BY$12824,$S$4:$S$12824,$S98) -> 2647339.5 | CF98: =AC98*AE98 -> 6073881
B99: Done | C99: NINE UNITED | D99: SC-HAY-02-040423-PALISSADE | E99: PO-HAY-02-040423-PALISSADE | F99: 45020 | G99: HAY | H99: STOCK | L99: 100% BEFORE PICK UP | M99: CFR | O99: FURNITURE | P99: Chairs | R99: AA606-A221 | S99: OUTHA00060 | T99: Ghế PALISSADE CHAIR, Kích thước (Dài 47 x Rộng 56 x Cao 45/80) cm, Bằng Thép, Màu xám (SKY GREY). Hiệu: HAY. Model: AA606-A221. Mới 100% | U99: 10 | V99: USD | X99: =W99*U99 -> 0 | Z99: 109.782 | AB99: =IF(AA99="F.O.C", 0, Z99*U99) -> 1097.82 | AC99: =Z99*U99 -> 1097.82 | AE99: 23310 | AF99: 0 | AG99: =(AC99*AE99+BO99+BP99+BQ99+BS99)*AF99 -> 0 | AI99: =(AC99*AE99+AG99+BF99+BG99+BH99+BJ99)*AH99 -> 0 | AJ99: IN230523091020 | AK99: 23/05/2023 | AO99: SEA | AQ99: 01/06/2023 | AV99: 105502791661 | AW99: 45086 | AX99: 09/06/2023 | BA99: Xong | BB99: BÌNH PHÚ | BC99: 45086 | BD99: Lô 7 | BE99: {=IF(BD99="","",AC99/SUMPRODUCT(--(BD99=$BD$4:$BD$12824),$AC$4:$AC$12824))} -> 0.025832026 | BI99: =(14088500+1064000+7400000+1318182+1065000+210000) -> 25145682 | BJ99: 1324291 | BK99: 36450000 | BL99: 500000 | BN99: =1000000 -> 1000000 | BO99: =VLOOKUP(BD99,$BD$4:$BN$12824,3,0)*BE99 -> 0 | BR99: =VLOOKUP(BD99,$BD$4:$BN$12824,6,0)*BE99 -> 649563.9 | BS99: =VLOOKUP(BD99,$BD$4:$BN$12824,7,0)*BE99 -> 34209.119 | BU99: =VLOOKUP(BD99,$BD$4:$BN$12824,9,0)*BE99 -> 12916.013 | BW99: =VLOOKUP(BD99,$BD$4:$BN$12824,11,0)*BE99 -> 25832.026 | BX99: =SUM(BO99:BW99) -> 722521.06 | BY99: =(AB99*AE99+AG99+BX99)/U99 -> 2631270.5 | BZ99: =BY99*U99 -> 26312705 | CA99: =_xlfn.MAXIFS($BY$4:$BY$12824,$S$4:$S$12824,$S99) -> 4043720.1 | CF99: =AC99*AE99 -> 25590184
B100: Done | C100: NINE UNITED | D100: SC-HAY-02-040423-PALISSADE | E100: PO-HAY-02-040423-PALISSADE | F100: 45020 | G100: HAY | H100: STOCK | L100: 100% BEFORE PICK UP | M100: CFR | O100: FURNITURE | P100: Chairs | R100: AA606-A237 | S100: OUTHA00015 | T100: Ghế PALISSADE CHAIR, Kích thước (Dài 47 x Rộng 56 x Cao 45/80) cm, Bằng Thép, Màu lục (OLIVE). Hiệu: HAY. Model: AA606-A237. Mới 100% | U100: 26 | V100: USD | X100: =W100*U100 -> 0 | Z100: 109.78192 | AB100: =IF(AA100="F.O.C", 0, Z100*U100) -> 2854.3299 | AC100: =Z100*U100 -> 2854.3299 | AE100: 23310 | AF100: 0 | AG100: =(AC100*AE100+BO100+BP100+BQ100+BS100)*AF100 -> 0 | AI100: =(AC100*AE100+AG100+BF100+BG100+BH100+BJ100)*AH100 -> 0 | AJ100: IN230523091020 | AK100: 23/05/2023 | AO100: SEA | AQ100: 01/06/2023 | AV100: 105502791661 | AW100: 45086 | AX100: 09/06/2023 | BA100: Xong | BB100: BÌNH PHÚ | BC100: 45086 | BD100: Lô 7 | BE100: {=IF(BD100="","",AC100/SUMPRODUCT(--(BD100=$BD$4:$BD$12824),$AC$4:$AC$12824))} -> 0.067163218 | BO100: =VLOOKUP(BD100,$BD$4:$BN$12824,3,0)*BE100 -> 0 | BR100: =VLOOKUP(BD100,$BD$4:$BN$12824,6,0)*BE100 -> 1688864.9 | BS100: =VLOOKUP(BD100,$BD$4:$BN$12824,7,0)*BE100 -> 88943.645 | BU100: =VLOOKUP(BD100,$BD$4:$BN$12824,9,0)*BE100 -> 33581.609 | BW100: =VLOOKUP(BD100,$BD$4:$BN$12824,11,0)*BE100 -> 67163.218 | BX100: =SUM(BO100:BW100) -> 1878553.4 | BY100: =(AB100*AE100+AG100+BX100)/U100 -> 2631268.6 | BZ100: =BY100*U100 -> 68412984 | CA100: =_xlfn.MAXIFS($BY$4:$BY$12824,$S$4:$S$12824,$S100) -> 2631268.6 | CF100: =AC100*AE100 -> 66534430
B101: Done | C101: NINE UNITED | D101: SC-HAY-02-040423-PALISSADE | E101: PO-HAY-02-040423-PALISSADE | F101: 45020 | G101: HAY | H101: STOCK | L101: 100% BEFORE PICK UP | M101: CFR | O101: FURNITURE | P101: Chairs | R101: AA607-A221 | S101: OUTHA00061 | T101: Ghế PALISSADE ARMCHAIR, Kích thước (Dài 51 x Rộng 56 x Cao 45/80) cm, Bằng Thép, Màu xám (SKY GREY). Hiệu: HAY. Model: AA607-A221. Mới 100% | U101: 4 | V101: USD | X101: =W101*U101 -> 0 | Z101: 125.1725 | AB101: =IF(AA101="F.O.C", 0, Z101*U101) -> 500.69 | AC101: =Z101*U101 -> 500.69 | AE101: 23310 | AF101: 0 | AG101: =(AC101*AE101+BO101+BP101+BQ101+BS101)*AF101 -> 0 | AI101: =(AC101*AE101+AG101+BF101+BG101+BH101+BJ101)*AH101 -> 0 | AJ101: IN230523091020 | AK101: 23/05/2023 | AO101: SEA | AQ101: 01/06/2023 | AV101: 105502791661 | AW101: 45086 | AX101: 09/06/2023 | BA101: Xong | BB101: BÌNH PHÚ | BC101: 45086 | BD101: Lô 7 | BE101: {=IF(BD101="","",AC101/SUMPRODUCT(--(BD101=$BD$4:$BD$12824),$AC$4:$AC$12824))} -> 0.011781382 | BO101: =VLOOKUP(BD101,$BD$4:$BN$12824,3,0)*BE101 -> 0 | BR101: =VLOOKUP(BD101,$BD$4:$BN$12824,6,0)*BE101 -> 296250.89 | BS101: =VLOOKUP(BD101,$BD$4:$BN$12824,7,0)*BE101 -> 15601.978 | BU101: =VLOOKUP(BD101,$BD$4:$BN$12824,9,0)*BE101 -> 5890.691 | BW101: =VLOOKUP(BD101,$BD$4:$BN$12824,11,0)*BE101 -> 11781.382 | BX101: =SUM(BO101:BW101) -> 329524.94 | BY101: =(AB101*AE101+AG101+BX101)/U101 -> 3000152.2 | BZ101: =BY101*U101 -> 12000609 | CA101: =_xlfn.MAXIFS($BY$4:$BY$12824,$S$4:$S$12824,$S101) -> 3000152.2 | CF101: =AC101*AE101 -> 11671084
B102: Done | C102: NINE UNITED | D102: SC-HAY-02-040423-PALISSADE | E102: PO-HAY-02-040423-PALISSADE | F102: 45020 | G102: HAY | H102: STOCK | L102: 100% BEFORE PICK UP | M102: CFR | O102: FURNITURE | P102: Chairs | R102: AA607-A237 | S102: OUTHA00010 | T102: Ghế PALISSADE ARMCHAIR, Kích thước (Dài 51 x Rộng 56 x Cao 45/80) cm, Bằng Thép, Màu lục (OLIVE). Hiệu: HAY. Model: AA607-A237. Mới 100% | U102: 24 | V102: USD | X102: =W102*U102 -> 0 | Z102: 125.17208 | AB102: =IF(AA102="F.O.C", 0, Z102*U102) -> 3004.1299 | AC102: =Z102*U102 -> 3004.1299 | AE102: 23310 | AF102: 0 | AG102: =(AC102*AE102+BO102+BP102+BQ102+BS102)*AF102 -> 0 | AI102: =(AC102*AE102+AG102+BF102+BG102+BH102+BJ102)*AH102 -> 0 | AJ102: IN230523091020 | AK102: 23/05/2023 | AO102: SEA | AQ102: 01/06/2023 | AV102: 105502791661 | AW102: 45086 | AX102: 09/06/2023 | BA102: Xong | BB102: BÌNH PHÚ | BC102: 45086 | BD102: Lô 7 | BE102: {=IF(BD102="","",AC102/SUMPRODUCT(--(BD102=$BD$4:$BD$12824),$AC$4:$AC$12824))} -> 0.070688055 | BO102: =VLOOKUP(BD102,$BD$4:$BN$12824,3,0)*BE102 -> 0 | BR102: =VLOOKUP(BD102,$BD$4:$BN$12824,6,0)*BE102 -> 1777499.4 | BS102: =VLOOKUP(BD102,$BD$4:$BN$12824,7,0)*BE102 -> 93611.556 | BU102: =VLOOKUP(BD102,$BD$4:$BN$12824,9,0)*BE102 -> 35344.028 | BW102: =VLOOKUP(BD102,$BD$4:$BN$12824,11,0)*BE102 -> 70688.055 | BX102: =SUM(BO102:BW102) -> 1977143 | BY102: =(AB102*AE102+AG102+BX102)/U102 -> 3000142.1 | BZ102: =BY102*U102 -> 72003411 | CA102: =_xlfn.MAXIFS($BY$4:$BY$12824,$S$4:$S$12824,$S102) -> 3000142.1 | CF102: =AC102*AE102 -> 70026268
B103: Done | C103: NINE UNITED | D103: SC-HAY-02-040423-PALISSADE | E103: PO-HAY-02-040423-PALISSADE | F103: 45020 | G103: HAY | H103: STOCK | L103: 100% BEFORE PICK UP | M103: CFR | O103: FURNITURE | P103: Chairs | R103: AA608-A221 | S103: OUTHA00062 | T103: Ghế PALISSADE DINING ARM CHAIR, Kích thước (Dài 63 x Rộng 66 x Cao 80) cm, Bằng Thép, Màu xám (SKY GREY). Hiệu: HAY. Model: AA608-A221. Mới 100% | U103: 2 | V103: USD | X103: =W103*U103 -> 0 | Z103: 132.865 | AB103: =IF(AA103="F.O.C", 0, Z103*U103) -> 265.73 | AC103: =Z103*U103 -> 265.73 | AE103: 23310 | AF103: 0 | AG103: =(AC103*AE103+BO103+BP103+BQ103+BS103)*AF103 -> 0 | AI103: =(AC103*AE103+AG103+BF103+BG103+BH103+BJ103)*AH103 -> 0 | AJ103: IN230523091020 | AK103: 23/05/2023 | AO103: SEA | AQ103: 01/06/2023 | AV103: 105502791661 | AW103: 45086 | AX103: 09/06/2023 | BA103: Xong | BB103: BÌNH PHÚ | BC103: 45086 | BD103: Lô 7 | BE103: {=IF(BD103="","",AC103/SUMPRODUCT(--(BD103=$BD$4:$BD$12824),$AC$4:$AC$12824))} -> 0.0062527046 | BO103: =VLOOKUP(BD103,$BD$4:$BN$12824,3,0)*BE103 -> 0 | BR103: =VLOOKUP(BD103,$BD$4:$BN$12824,6,0)*BE103 -> 157228.52 | BS103: =VLOOKUP(BD103,$BD$4:$BN$12824,7,0)*BE103 -> 8280.4004 | BU103: =VLOOKUP(BD103,$BD$4:$BN$12824,9,0)*BE103 -> 3126.3523 | BW103: =VLOOKUP(BD103,$BD$4:$BN$12824,11,0)*BE103 -> 6252.7046 | BX103: =SUM(BO103:BW103) -> 174887.98 | BY103: =(AB103*AE103+AG103+BX103)/U103 -> 3184527.1 | BZ103: =BY103*U103 -> 6369054.3 | CA103: =_xlfn.MAXIFS($BY$4:$BY$12824,$S$4:$S$12824,$S103) -> 3548804.2 | CF103: =AC103*AE103 -> 6194166.3
B104: Done | C104: NINE UNITED | D104: SC-HAY-02-040423-PALISSADE | E104: PO-HAY-02-040423-PALISSADE | F104: 45020 | G104: HAY | H104: STOCK | L104: 100% BEFORE PICK UP | M104: CFR | O104: FURNITURE | P104: Chairs | R104: AA608-A237 | S104: OUTHA00016 | T104: Ghế PALISSADE DINING ARM CHAIR, Kích thước (Dài 63 x Rộng 66 x Cao 80) cm, Bằng Thép, Màu lục (OLIVE). Hiệu: HAY. Model: AA608-A237. Mới 100% | U104: 6 | V104: USD | X104: =W104*U104 -> 0 | Z104: 132.86666 | AB104: =IF(AA104="F.O.C", 0, Z104*U104) -> 797.19996 | AC104: =Z104*U104 -> 797.19996 | AE104: 23310 | AF104: 0 | AG104: =(AC104*AE104+BO104+BP104+BQ104+BS104)*AF104 -> 0 | AI104: =(AC104*AE104+AG104+BF104+BG104+BH104+BJ104)*AH104 -> 0 | AJ104: IN230523091020 | AK104: 23/05/2023 | AO104: SEA | AQ104: 01/06/2023 | AV104: 105502791661 | AW104: 45086 | AX104: 09/06/2023 | BA104: Xong | BB104: BÌNH PHÚ | BC104: 45086 | BD104: Lô 7 | BE104: {=IF(BD104="","",AC104/SUMPRODUCT(--(BD104=$BD$4:$BD$12824),$AC$4:$AC$12824))} -> 0.018758348 | BO104: =VLOOKUP(BD104,$BD$4:$BN$12824,3,0)*BE104 -> 0 | BR104: =VLOOKUP(BD104,$BD$4:$BN$12824,6,0)*BE104 -> 471691.46 | BS104: =VLOOKUP(BD104,$BD$4:$BN$12824,7,0)*BE104 -> 24841.512 | BU104: =VLOOKUP(BD104,$BD$4:$BN$12824,9,0)*BE104 -> 9379.1741 | BW104: =VLOOKUP(BD104,$BD$4:$BN$12824,11,0)*BE104 -> 18758.348 | BX104: =SUM(BO104:BW104) -> 524670.49 | BY104: =(AB104*AE104+AG104+BX104)/U104 -> 3184566.9 | BZ104: =BY104*U104 -> 19107402 | CA104: =_xlfn.MAXIFS($BY$4:$BY$12824,$S$4:$S$12824,$S104) -> 3184566.9 | CF104: =AC104*AE104 -> 18582731
B105: Done | C105: NINE UNITED | D105: SC-HAY-02-040423-PALISSADE | E105: PO-HAY-02-040423-PALISSADE | F105: 45020 | G105: HAY | H105: STOCK | L105: 100% BEFORE PICK UP | M105: CFR | O105: FURNITURE | P105: Chairs | R105: AA610-A221 | S105: OUTHA00063 | T105: Ghế PALISSADE BENCH, Kích thước (Dài 120 x Rộng 42 x Cao 45) cm, Bằng Thép, Màu xám (SKY GREY). Hiệu: HAY. Model: AA610-A221. Mới 100% | U105: 2 | V105: USD | X105: =W105*U105 -> 0 | Z105: 148.77 | AB105: =IF(AA105="F.O.C", 0, Z105*U105) -> 297.54 | AC105: =Z105*U105 -> 297.54 | AE105: 23310 | AF105: 0 | AG105: =(AC105*AE105+BO105+BP105+BQ105+BS105)*AF105 -> 0 | AI105: =(AC105*AE105+AG105+BF105+BG105+BH105+BJ105)*AH105 -> 0 | AJ105: IN230523091020 | AK105: 23/05/2023 | AO105: SEA | AQ105: 01/06/2023 | AV105: 105502791661 | AW105: 45086 | AX105: 09/06/2023 | BA105: Xong | BB105: BÌNH PHÚ | BC105: 45086 | BD105: Lô 7 | BE105: {=IF(BD105="","",AC105/SUMPRODUCT(--(BD105=$BD$4:$BD$12824),$AC$4:$AC$12824))} -> 0.0070012032 | BO105: =VLOOKUP(BD105,$BD$4:$BN$12824,3,0)*BE105 -> 0 | BR105: =VLOOKUP(BD105,$BD$4:$BN$12824,6,0)*BE105 -> 176050.03 | BS105: =VLOOKUP(BD105,$BD$4:$BN$12824,7,0)*BE105 -> 9271.6304 | BU105: =VLOOKUP(BD105,$BD$4:$BN$12824,9,0)*BE105 -> 3500.6016 | BW105: =VLOOKUP(BD105,$BD$4:$BN$12824,11,0)*BE105 -> 7001.2032 | BX105: =SUM(BO105:BW105) -> 195823.46 | BY105: =(AB105*AE105+AG105+BX105)/U105 -> 3565740.4 | BZ105: =BY105*U105 -> 7131480.9 | CA105: =_xlfn.MAXIFS($BY$4:$BY$12824,$S$4:$S$12824,$S105) -> 3565740.4 | CF105: =AC105*AE105 -> 6935657.4
B106: Done | C106: NINE UNITED | D106: SC-HAY-02-040423-PALISSADE | E106: PO-HAY-02-040423-PALISSADE | F106: 45020 | G106: HAY | H106: STOCK | L106: 100% BEFORE PICK UP | M106: CFR | O106: FURNITURE | P106: Chairs | R106: AA610-A237 | S106: OUTHA00013 | T106: Ghế PALISSADE BENCH, Kích thước (Dài 120 x Rộng 42 x Cao 45) cm, Bằng Thép, Màu lục (OLIVE). Hiệu: HAY. Model: AA610-A237. Mới 100% | U106: 17 | V106: USD | X106: =W106*U106 -> 0 | Z106: 148.77 | AB106: =IF(AA106="F.O.C", 0, Z106*U106) -> 2529.09 | AC106: =Z106*U106 -> 2529.09 | AE106: 23310 | AF106: 0 | AG106: =(AC106*AE106+BO106+BP106+BQ106+BS106)*AF106 -> 0 | AI106: =(AC106*AE106+AG106+BF106+BG106+BH106+BJ106)*AH106 -> 0 | AJ106: IN230523091020 | AK106: 23/05/2023 | AO106: SEA | AQ106: 01/06/2023 | AV106: 105502791661 | AW106: 45086 | AX106: 09/06/2023 | BA106: Xong | BB106: BÌNH PHÚ | BC106: 45086 | BD106: Lô 7 | BE106: {=IF(BD106="","",AC106/SUMPRODUCT(--(BD106=$BD$4:$BD$12824),$AC$4:$AC$12824))} -> 0.059510227 | BO106: =VLOOKUP(BD106,$BD$4:$BN$12824,3,0)*BE106 -> 0 | BR106: =VLOOKUP(BD106,$BD$4:$BN$12824,6,0)*BE106 -> 1496425.2 | BS106: =VLOOKUP(BD106,$BD$4:$BN$12824,7,0)*BE106 -> 78808.858 | BU106: =VLOOKUP(BD106,$BD$4:$BN$12824,9,0)*BE106 -> 29755.114 | BW106: =VLOOKUP(BD106,$BD$4:$BN$12824,11,0)*BE106 -> 59510.227 | BX106: =SUM(BO106:BW106) -> 1664499.4 | BY106: =(AB106*AE106+AG106+BX106)/U106 -> 3565740.4 | BZ106: =BY106*U106 -> 60617587 | CA106: =_xlfn.MAXIFS($BY$4:$BY$12824,$S$4:$S$12824,$S106) -> 4159383.2 | CF106: =AC106*AE106 -> 58953088
B107: Done | C107: NINE UNITED | D107: SC-HAY-02-040423-PALISSADE | E107: PO-HAY-02-040423-PALISSADE | F107: 45020 | G107: HAY | H107: STOCK | M107: CFR | O107: FURNITURE | P107: Chairs | R107: AA611-A221 | S107: OUTHA00064 | T107: Ghế PALISSADE DINING BENCH ARMREST, Kích thước (Dài 128 x Rộng 70 x Cao 45/80) cm, Bằng Thép, Màu xám (SKY GREY). Hiệu: HAY. Model: AA611-A221. Mới 100% | U107: 5 | V107: USD | X107: =W107*U107 -> 0 | Z107: 215.46 | AB107: =IF(AA107="F.O.C", 0, Z107*U107) -> 1077.3 | AC107: =Z107*U107 -> 1077.3 | AE107: 23310 | AF107: 0 | AG107: =(AC107*AE107+BO107+BP107+BQ107+BS107)*AF107 -> 0 | AI107: =(AC107*AE107+AG107+BF107+BG107+BH107+BJ107)*AH107 -> 0 | AJ107: IN230523091020 | AK107: 23/05/2023 | AO107: SEA | AQ107: 01/06/2023 | AV107: 105502791661 | AW107: 45086 | AX107: 09/06/2023 | BA107: Xong | BB107: BÌNH PHÚ | BC107: 45086 | BD107: Lô 7 | BE107: {=IF(BD107="","",AC107/SUMPRODUCT(--(BD107=$BD$4:$BD$12824),$AC$4:$AC$12824))} -> 0.025349184 | BO107: =VLOOKUP(BD107,$BD$4:$BN$12824,3,0)*BE107 -> 0 | BR107: =VLOOKUP(BD107,$BD$4:$BN$12824,6,0)*BE107 -> 637422.52 | BS107: =VLOOKUP(BD107,$BD$4:$BN$12824,7,0)*BE107 -> 33569.696 | BU107: =VLOOKUP(BD107,$BD$4:$BN$12824,9,0)*BE107 -> 12674.592 | BW107: =VLOOKUP(BD107,$BD$4:$BN$12824,11,0)*BE107 -> 25349.184 | BX107: =SUM(BO107:BW107) -> 709015.99 | BY107: =(AB107*AE107+AG107+BX107)/U107 -> 5164175.8 | BZ107: =BY107*U107 -> 25820879 | CA107: =_xlfn.MAXIFS($BY$4:$BY$12824,$S$4:$S$12824,$S107) -> 5164175.8 | CF107: =AC107*AE107 -> 25111863
B108: Done | C108: NINE UNITED | D108: SC-HAY-02-040423-PALISSADE | E108: PO-HAY-02-040423-PALISSADE | F108: 45020 | G108: HAY | H108: STOCK | M108: CFR | O108: FURNITURE | P108: Chairs | R108: AA611-A237 | S108: OUTHA00072 | T108: Ghế PALISSADE DINING BENCH ARMREST, Kích thước (Dài 128 x Rộng 70 x Cao 45/80) cm, Bằng Thép, Màu lục (OLIVE). Hiệu: HAY. Model: AA611-A237. Mới 100% | U108: 5 | V108: USD | X108: =W108*U108 -> 0 | Z108: 215.46 | AB108: =IF(AA108="F.O.C", 0, Z108*U108) -> 1077.3 | AC108: =Z108*U108 -> 1077.3 | AE108: 23310 | AF108: 0 | AG108: =(AC108*AE108+BO108+BP108+BQ108+BS108)*AF108 -> 0 | AI108: =(AC108*AE108+AG108+BF108+BG108+BH108+BJ108)*AH108 -> 0 | AJ108: IN230523091020 | AK108: 23/05/2023 | AO108: SEA | AQ108: 01/06/2023 | AV108: 105502791661 | AW108: 45086 | AX108: 09/06/2023 | BA108: Xong | BB108: BÌNH PHÚ | BC108: 45086 | BD108: Lô 7 | BE108: {=IF(BD108="","",AC108/SUMPRODUCT(--(BD108=$BD$4:$BD$12824),$AC$4:$AC$12824))} -> 0.025349184 | BO108: =VLOOKUP(BD108,$BD$4:$BN$12824,3,0)*BE108 -> 0 | BR108: =VLOOKUP(BD108,$BD$4:$BN$12824,6,0)*BE108 -> 637422.52 | BS108: =VLOOKUP(BD108,$BD$4:$BN$12824,7,0)*BE108 -> 33569.696 | BU108: =VLOOKUP(BD108,$BD$4:$BN$12824,9,0)*BE108 -> 12674.592 | BW108: =VLOOKUP(BD108,$BD$4:$BN$12824,11,0)*BE108 -> 25349.184 | BX108: =SUM(BO108:BW108) -> 709015.99 | BY108: =(AB108*AE108+AG108+BX108)/U108 -> 5164175.8 | BZ108: =BY108*U108 -> 25820879 | CA108: =_xlfn.MAXIFS($BY$4:$BY$12824,$S$4:$S$12824,$S108) -> 5164175.8 | CF108: =AC108*AE108 -> 25111863
B109: Done | C109: NINE UNITED | D109: SC-HAY-02-040423-PALISSADE | E109: PO-HAY-02-040423-PALISSADE | F109: 45020 | G109: HAY | H109: STOCK | M109: CFR | O109: FURNITURE | P109: Chairs | R109: AA612-A237 | S109: OUTHA00023 | T109: Ghế PALISSADE STOOL, Kích thước (Dài 37 x Rộng 42 x Cao 45) cm, Bằng Thép, Màu lục (OLIVE). Hiệu: HAY. Model: AA612-A237. Mới 100% | U109: 31 | V109: USD | X109: =W109*U109 -> 0 | Z109: 78.489032 | AB109: =IF(AA109="F.O.C", 0, Z109*U109) -> 2433.16 | AC109: =Z109*U109 -> 2433.16 | AE109: 23310 | AF109: 0 | AG109: =(AC109*AE109+BO109+BP109+BQ109+BS109)*AF109 -> 0 | AI109: =(AC109*AE109+AG109+BF109+BG109+BH109+BJ109)*AH109 -> 0 | AJ109: IN230523091020 | AK109: 23/05/2023 | AO109: SEA | AQ109: 01/06/2023 | AV109: 105502791661 | AW109: 45086 | AX109: 09/06/2023 | BA109: Xong | BB109: BÌNH PHÚ | BC109: 45086 | BD109: Lô 7 | BE109: {=IF(BD109="","",AC109/SUMPRODUCT(--(BD109=$BD$4:$BD$12824),$AC$4:$AC$12824))} -> 0.057252966 | BO109: =VLOOKUP(BD109,$BD$4:$BN$12824,3,0)*BE109 -> 0 | BR109: =VLOOKUP(BD109,$BD$4:$BN$12824,6,0)*BE109 -> 1439664.9 | BS109: =VLOOKUP(BD109,$BD$4:$BN$12824,7,0)*BE109 -> 75819.588 | BU109: =VLOOKUP(BD109,$BD$4:$BN$12824,9,0)*BE109 -> 28626.483 | BW109: =VLOOKUP(BD109,$BD$4:$BN$12824,11,0)*BE109 -> 57252.966 | BX109: =SUM(BO109:BW109) -> 1601363.9 | BY109: =(AB109*AE109+AG109+BX109)/U109 -> 1881236.2 | BZ109: =BY109*U109 -> 58318323 | CA109: =_xlfn.MAXIFS($BY$4:$BY$12824,$S$4:$S$12824,$S109) -> 1881236.2 | CF109: =AC109*AE109 -> 56716959
B110: Done | C110: NINE UNITED | D110: SC-HAY-02-040423-PALISSADE | E110: PO-HAY-02-040423-PALISSADE | F110: 45020 | G110: HAY | H110: STOCK | M110: CFR | O110: FURNITURE | P110: Chairs | R110: AA614-A221 | S110: OUTHA00065 | T110: Ghế PALISSADE CHAISE LOUNGE, Kích thước (Dài 164.5 x Rộng 65.5 x Cao 70) cm, Bằng Thép, Màu xám (SKY GREY ). Hiệu: HAY. Model: AA614-A221. Mới 100% | U110: 4 | V110: USD | X110: =W110*U110 -> 0 | Z110: 321.1375 | AB110: =IF(AA110="F.O.C", 0, Z110*U110) -> 1284.55 | AC110: =Z110*U110 -> 1284.55 | AE110: 23310 | AF110: 0 | AG110: =(AC110*AE110+BO110+BP110+BQ110+BS110)*AF110 -> 0 | AI110: =(AC110*AE110+AG110+BF110+BG110+BH110+BJ110)*AH110 -> 0 | AJ110: IN230523091020 | AK110: 23/05/2023 | AO110: SEA | AQ110: 01/06/2023 | AV110: 105502791661 | AW110: 45086 | AX110: 09/06/2023 | BA110: Xong | BB110: BÌNH PHÚ | BC110: 45086 | BD110: Lô 7 | BE110: {=IF(BD110="","",AC110/SUMPRODUCT(--(BD110=$BD$4:$BD$12824),$AC$4:$AC$12824))} -> 0.030225837 | BO110: =VLOOKUP(BD110,$BD$4:$BN$12824,3,0)*BE110 -> 0 | BR110: =VLOOKUP(BD110,$BD$4:$BN$12824,6,0)*BE110 -> 760049.29 | BS110: =VLOOKUP(BD110,$BD$4:$BN$12824,7,0)*BE110 -> 40027.804 | BU110: =VLOOKUP(BD110,$BD$4:$BN$12824,9,0)*BE110 -> 15112.919 | BW110: =VLOOKUP(BD110,$BD$4:$BN$12824,11,0)*BE110 -> 30225.837 | BX110: =SUM(BO110:BW110) -> 845415.85 | BY110: =(AB110*AE110+AG110+BX110)/U110 -> 7697069.1 | BZ110: =BY110*U110 -> 30788276 | CA110: =_xlfn.MAXIFS($BY$4:$BY$12824,$S$4:$S$12824,$S110) -> 7697069.1 | CF110: =AC110*AE110 -> 29942860
B111: Done | C111: NINE UNITED | D111: SC-HAY-02-040423-PALISSADE | E111: PO-HAY-02-040423-PALISSADE | F111: 45020 | G111: HAY | H111: STOCK | M111: CFR | O111: FURNITURE | P111: Chairs | R111: AA614-A237 | S111: OUTHA00025 | T111: Ghế PALISSADE CHAISE LOUNGE, Kích thước (Dài 164.5 x Rộng 65.5 x Cao 70) cm, Bằng Thép, Màu lục (OLIVE). Hiệu: HAY. Model: AA614-A237. Mới 100% | U111: 8 | V111: USD | X111: =W111*U111 -> 0 | Z111: 321.1375 | AB111: =IF(AA111="F.O.C", 0, Z111*U111) -> 2569.1 | AC111: =Z111*U111 -> 2569.1 | AE111: 23310 | AF111: 0 | AG111: =(AC111*AE111+BO111+BP111+BQ111+BS111)*AF111 -> 0 | AI111: =(AC111*AE111+AG111+BF111+BG111+BH111+BJ111)*AH111 -> 0 | AJ111: IN230523091020 | AK111: 23/05/2023 | AO111: SEA | AQ111: 01/06/2023 | AV111: 105502791661 | AW111: 45086 | AX111: 09/06/2023 | BA111: Xong | BB111: BÌNH PHÚ | BC111: 45086 | BD111: Lô 7 | BE111: {=IF(BD111="","",AC111/SUMPRODUCT(--(BD111=$BD$4:$BD$12824),$AC$4:$AC$12824))} -> 0.060451674 | BO111: =VLOOKUP(BD111,$BD$4:$BN$12824,3,0)*BE111 -> 0 | BR111: =VLOOKUP(BD111,$BD$4:$BN$12824,6,0)*BE111 -> 1520098.6 | BS111: =VLOOKUP(BD111,$BD$4:$BN$12824,7,0)*BE111 -> 80055.608 | BU111: =VLOOKUP(BD111,$BD$4:$BN$12824,9,0)*BE111 -> 30225.837 | BW111: =VLOOKUP(BD111,$BD$4:$BN$12824,11,0)*BE111 -> 60451.674 | BX111: =SUM(BO111:BW111) -> 1690831.7 | BY111: =(AB111*AE111+AG111+BX111)/U111 -> 7697069.1 | BZ111: =BY111*U111 -> 61576553 | CA111: =_xlfn.MAXIFS($BY$4:$BY$12824,$S$4:$S$12824,$S111) -> 7697069.1 | CF111: =AC111*AE111 -> 59885721
B112: Done | C112: NINE UNITED | D112: SC-HAY-02-040423-PALISSADE | E112: PO-HAY-02-040423-PALISSADE | F112: 45020 | G112: HAY | H112: STOCK | M112: CFR | O112: FURNITURE | P112: Table | R112: AA695-A379-AB03 | S112: OUTHA00001 | T112: Bàn PALISSADE CONE TABLE- phi 70(BOM), Kích thước (Đường kính 70 x Cao 74) cm, Bằng Thép, Màu lục (OLIVE). Hiệu: HAY. Model: AA695-A379-AB03. Mới 100% | U112: 6 | V112: USD | X112: =W112*U112 -> 0 | Z112: 207.25166 | AB112: =IF(AA112="F.O.C", 0, Z112*U112) -> 1243.51 | AC112: =Z112*U112 -> 1243.51 | AE112: 23310 | AF112: 0 | AG112: =(AC112*AE112+BO112+BP112+BQ112+BS112)*AF112 -> 0 | AI112: =(AC112*AE112+AG112+BF112+BG112+BH112+BJ112)*AH112 -> 0 | AJ112: IN230523091020 | AK112: 23/05/2023 | AO112: SEA | AQ112: 01/06/2023 | AV112: 105502791661 | AW112: 45086 | AX112: 09/06/2023 | BA112: Xong | BB112: BÌNH PHÚ | BC112: 45086 | BD112: Lô 7 | BE112: {=IF(BD112="","",AC112/SUMPRODUCT(--(BD112=$BD$4:$BD$12824),$AC$4:$AC$12824))} -> 0.029260153 | BO112: =VLOOKUP(BD112,$BD$4:$BN$12824,3,0)*BE112 -> 0 | BR112: =VLOOKUP(BD112,$BD$4:$BN$12824,6,0)*BE112 -> 735766.5 | BS112: =VLOOKUP(BD112,$BD$4:$BN$12824,7,0)*BE112 -> 38748.957 | BU112: =VLOOKUP(BD112,$BD$4:$BN$12824,9,0)*BE112 -> 14630.076 | BW112: =VLOOKUP(BD112,$BD$4:$BN$12824,11,0)*BE112 -> 29260.153 | BX112: =SUM(BO112:BW112) -> 818405.69 | BY112: =(AB112*AE112+AG112+BX112)/U112 -> 4967437.1 | BZ112: =BY112*U112 -> 29804623 | CA112: =_xlfn.MAXIFS($BY$4:$BY$12824,$S$4:$S$12824,$S112) -> 4967437.1 | CF112: =AC112*AE112 -> 28986217
B113: Done | C113: NINE UNITED | D113: SC-HAY-01-230323-TOTEBAG | E113: PO-HAY-01-230323-TOTEBAG | F113: 45008 | G113: HAY | H113: STOCK | M113: CFR | O113: ACCESSORIES | P113: Others | R113: 010376 | S113: ACCHA00221 | T113: Túi GREEN TOTE BAG, Kích thước (Rộng 42 X Cao 44.5) cm, Bằng Cotton, Màu Lục có White Logo. Hiệu: HAY. Model: 010376. Mới 100% | U113: 60 | V113: USD | X113: =W113*U113 -> 0 | Z113: 3.04 | AB113: =IF(AA113="F.O.C", 0, Z113*U113) -> 182.4 | AC113: =Z113*U113 -> 182.4 | AE113: 23310 | AF113: 0 | AG113: =(AC113*AE113+BO113+BP113+BQ113+BS113)*AF113 -> 0 | AI113: =(AC113*AE113+AG113+BF113+BG113+BH113+BJ113)*AH113 -> 0 | AJ113: IN230523091020 | AK113: 23/05/2023 | AO113: SEA | AQ113: 01/06/2023 | AV113: 105502791661 | AW113: 45086 | AX113: 09/06/2023 | BA113: Xong | BB113: BÌNH PHÚ | BC113: 45086 | BD113: Lô 7 | BE113: {=IF(BD113="","",AC113/SUMPRODUCT(--(BD113=$BD$4:$BD$12824),$AC$4:$AC$12824))} -> 0.0042919253 | BO113: =VLOOKUP(BD113,$BD$4:$BN$12824,3,0)*BE113 -> 0 | BR113: =VLOOKUP(BD113,$BD$4:$BN$12824,6,0)*BE113 -> 107923.39 | BS113: =VLOOKUP(BD113,$BD$4:$BN$12824,7,0)*BE113 -> 5683.7581 | BU113: =VLOOKUP(BD113,$BD$4:$BN$12824,9,0)*BE113 -> 2145.9627 | BW113: =VLOOKUP(BD113,$BD$4:$BN$12824,11,0)*BE113 -> 4291.9253 | BX113: =SUM(BO113:BW113) -> 120045.04 | BY113: =(AB113*AE113+AG113+BX113)/U113 -> 72863.151 | BZ113: =BY113*U113 -> 4371789 | CA113: =_xlfn.MAXIFS($BY$4:$BY$12824,$S$4:$S$12824,$S113) -> 72863.151 | CF113: =AC113*AE113 -> 4251744
B114: Done | C114: NINE UNITED | D114: SC-&TRADITION-01-100423-FLOWERPOT VP9 | E114: PO-&TRADITION-01-100423-FLOWERPOT VP9 | F114: 45026 | G114: HAY | H114: STOCK | M114: CFR | O114: DECOR LIGHTING | P114: Table lamp | R114: 410431 2009000 | S114: LTLHA00010 | T114: Đèn trang trí PC DECORATIVE LIGHT dùng công nghệ LED, Kích thước (Dài 14 x Rộng 14 x Cao 22) cm, Bằng nhựa ABS, Màu Lục (Olive). Hiệu: HAY. Model: 410431 2009000. Mới 100% (Hàng FOC) | U114: 2 | V114: USD | X114: =W114*U114 -> 0 | Z114: 43.32 | AB114: =IF(AA114="F.O.C", 0, Z114*U114) -> 86.64 | AC114: =Z114*U114 -> 86.64 | AE114: 23310 | AF114: 0 | AG114: =(AC114*AE114+BO114+BP114+BQ114+BS114)*AF114 -> 0 | AI114: =(AC114*AE114+AG114+BF114+BG114+BH114+BJ114)*AH114 -> 0 | AJ114: IN230523091020 | AK114: 23/05/2023 | AO114: SEA | AQ114: 01/06/2023 | AV114: 105502791661 | AW114: 45086 | AX114: 09/06/2023 | BA114: Xong | BB114: BÌNH PHÚ | BC114: 45086 | BD114: Lô 7 | BE114: {=IF(BD114="","",AC114/SUMPRODUCT(--(BD114=$BD$4:$BD$12824),$AC$4:$AC$12824))} -> 0.0020386645 | BO114: =VLOOKUP(BD114,$BD$4:$BN$12824,3,0)*BE114 -> 0 | BR114: =VLOOKUP(BD114,$BD$4:$BN$12824,6,0)*BE114 -> 51263.61 | BS114: =VLOOKUP(BD114,$BD$4:$BN$12824,7,0)*BE114 -> 2699.7851 | BT114: 1323765.5 | BU114: =VLOOKUP(BD114,$BD$4:$BN$12824,9,0)*BE114 -> 1019.3323 | BW114: =VLOOKUP(BD114,$BD$4:$BN$12824,11,0)*BE114 -> 2038.6645 | BX114: =SUM(BO114:BW114) -> 1380786.9 | BY114: =(AB114*AE114+AG114+BX114)/U114 -> 1700182.7 | BZ114: =BY114*U114 -> 3400365.3 | CA114: =_xlfn.MAXIFS($BY$4:$BY$12824,$S$4:$S$12824,$S114) -> 1700182.7 | CF114: =AC114*AE114 -> 2019578.4
B115: Done | C115: NINE UNITED | D115: SC-&TRADITION-01-100423-FLOWERPOT VP9 | E115: PO-&TRADITION-01-100423-FLOWERPOT VP9 | F115: 45026 | G115: &Tradition | H115: STOCK | M115: CFR | O115: DECOR LIGHTING | P115: Table lamp | R115: 20712201 | S115: LTLAT00009 | T115: Đèn trang trí FLOWERPOT VP9 DECORATIVE LIGHT dùng công nghệ LED, Kích thước (Đường kính 16 x cao 29.5) cm, 3W 2700K, Bằng PC và Thép. Màu vàng (Mustard). Hiệu: &TRADITION. Model: 20712201. Mới 100% | U115: 5 | V115: USD | X115: =W115*U115 -> 0 | Z115: 104.5 | AB115: =IF(AA115="F.O.C", 0, Z115*U115) -> 522.5 | AC115: =Z115*U115 -> 522.5 | AE115: 23310 | AF115: 0 | AG115: =(AC115*AE115+BO115+BP115+BQ115+BS115)*AF115 -> 0 | AI115: =(AC115*AE115+AG115+BF115+BG115+BH115+BJ115)*AH115 -> 0 | AJ115: IN230523091020 | AK115: 23/05/2023 | AO115: SEA | AQ115: 01/06/2023 | AV115: 105502791661 | AW115: 45086 | AX115: 09/06/2023 | BA115: Xong | BB115: BÌNH PHÚ | BC115: 45086 | BD115: Lô 7 | BE115: {=IF(BD115="","",AC115/SUMPRODUCT(--(BD115=$BD$4:$BD$12824),$AC$4:$AC$12824))} -> 0.012294578 | BO115: =VLOOKUP(BD115,$BD$4:$BN$12824,3,0)*BE115 -> 0 | BR115: =VLOOKUP(BD115,$BD$4:$BN$12824,6,0)*BE115 -> 309155.54 | BS115: =VLOOKUP(BD115,$BD$4:$BN$12824,7,0)*BE115 -> 16281.599 | BT115: 7983235.1 | BU115: =VLOOKUP(BD115,$BD$4:$BN$12824,9,0)*BE115 -> 6147.2889 | BW115: =VLOOKUP(BD115,$BD$4:$BN$12824,11,0)*BE115 -> 12294.578 | BX115: =SUM(BO115:BW115) -> 8327114.1 | BY115: =(AB115*AE115+AG115+BX115)/U115 -> 4101317.8 | BZ115: =BY115*U115 -> 20506589 | CA115: =_xlfn.MAXIFS($BY$4:$BY$12824,$S$4:$S$12824,$S115) -> 4101317.8 | CF115: =AC115*AE115 -> 12179475
B116: Done | C116: NINE UNITED | D116: SC-&TRADITION-01-100423-FLOWERPOT VP9 | E116: PO-&TRADITION-01-100423-FLOWERPOT VP9 | F116: 45026 | G116: &Tradition | H116: STOCK | M116: CFR | O116: DECOR LIGHTING | P116: Table lamp | R116: 20713701 | S116: LTLAT00012 | T116: Đèn trang trí FLOWERPOT VP9 DECORATIVE LIGHT dùng công nghệ LED, Kích thước (Đường kính 16 x cao 29.5) cm, 3W 2700K, Bằng PC và Thép. Màu xanh (Swim Blue). Hiệu: &TRADITION. Model: 20713701. Mới 100% | U116: 5 | V116: USD | X116: =W116*U116 -> 0 | Z116: 104.5 | AB116: =IF(AA116="F.O.C", 0, Z116*U116) -> 522.5 | AC116: =Z116*U116 -> 522.5 | AE116: 23310 | AF116: 0 | AG116: =(AC116*AE116+BO116+BP116+BQ116+BS116)*AF116 -> 0 | AI116: =(AC116*AE116+AG116+BF116+BG116+BH116+BJ116)*AH116 -> 0 | AJ116: IN230523091020 | AK116: 23/05/2023 | AO116: SEA | AQ116: 01/06/2023 | AV116: 105502791661 | AW116: 45086 | AX116: 09/06/2023 | BA116: Xong | BB116: BÌNH PHÚ | BC116: 45086 | BD116: Lô 7 | BE116: {=IF(BD116="","",AC116/SUMPRODUCT(--(BD116=$BD$4:$BD$12824),$AC$4:$AC$12824))} -> 0.012294578 | BO116: =VLOOKUP(BD116,$BD$4:$BN$12824,3,0)*BE116 -> 0 | BR116: =VLOOKUP(BD116,$BD$4:$BN$12824,6,0)*BE116 -> 309155.54 | BS116: =VLOOKUP(BD116,$BD$4:$BN$12824,7,0)*BE116 -> 16281.599 | BT116: 7983235.1 | BU116: =VLOOKUP(BD116,$BD$4:$BN$12824,9,0)*BE116 -> 6147.2889 | BW116: =VLOOKUP(BD116,$BD$4:$BN$12824,11,0)*BE116 -> 12294.578 | BX116: =SUM(BO116:BW116) -> 8327114.1 | BY116: =(AB116*AE116+AG116+BX116)/U116 -> 4101317.8 | BZ116: =BY116*U116 -> 20506589 | CA116: =_xlfn.MAXIFS($BY$4:$BY$12824,$S$4:$S$12824,$S116) -> 4101317.8 | CF116: =AC116*AE116 -> 12179475
B117: Done | C117: NINE UNITED | D117: SC-&TRADITION-01-100423-FLOWERPOT VP9 | E117: PO-&TRADITION-01-100423-FLOWERPOT VP9 | F117: 45026 | G117: &Tradition | H117: STOCK | M117: CFR | O117: DECOR LIGHTING | P117: Table lamp | R117: 20715002 | S117: LTLAT00013 | T117: Đèn trang trí FLOWERPOT VP9 DECORATIVE LIGHT dùng công nghệ LED, Kích thước (Đường kính 16 x cao 29.5) cm, 3W 2700K, Bằng PC và Thép. Màu xanh (Cobalt Blue).Hiệu: &TRADITION. Model: 20715002. Mới 100% | U117: 5 | V117: USD | X117: =W117*U117 -> 0 | Z117: 104.5 | AB117: =IF(AA117="F.O.C", 0, Z117*U117) -> 522.5 | AC117: =Z117*U117 -> 522.5 | AE117: 23310 | AF117: 0 | AG117: =(AC117*AE117+BO117+BP117+BQ117+BS117)*AF117 -> 0 | AI117: =(AC117*AE117+AG117+BF117+BG117+BH117+BJ117)*AH117 -> 0 | AJ117: IN230523091020 | AK117: 23/05/2023 | AO117: SEA | AQ117: 01/06/2023 | AV117: 105502791661 | AW117: 45086 | AX117: 09/06/2023 | BA117: Xong | BB117: BÌNH PHÚ | BC117: 45086 | BD117: Lô 7 | BE117: {=IF(BD117="","",AC117/SUMPRODUCT(--(BD117=$BD$4:$BD$12824),$AC$4:$AC$12824))} -> 0.012294578 | BO117: =VLOOKUP(BD117,$BD$4:$BN$12824,3,0)*BE117 -> 0 | BR117: =VLOOKUP(BD117,$BD$4:$BN$12824,6,0)*BE117 -> 309155.54 | BS117: =VLOOKUP(BD117,$BD$4:$BN$12824,7,0)*BE117 -> 16281.599 | BT117: 7983235.1 | BU117: =VLOOKUP(BD117,$BD$4:$BN$12824,9,0)*BE117 -> 6147.2889 | BW117: =VLOOKUP(BD117,$BD$4:$BN$12824,11,0)*BE117 -> 12294.578 | BX117: =SUM(BO117:BW117) -> 8327114.1 | BY117: =(AB117*AE117+AG117+BX117)/U117 -> 4101317.8 | BZ117: =BY117*U117 -> 20506589 | CA117: =_xlfn.MAXIFS($BY$4:$BY$12824,$S$4:$S$12824,$S117) -> 4101317.8 | CF117: =AC117*AE117 -> 12179475
B118: Done | C118: NINE UNITED | D118: SC-&TRADITION-01-100423-FLOWERPOT VP9 | E118: PO-&TRADITION-01-100423-FLOWERPOT VP9 | F118: 45026 | G118: &Tradition | H118: STOCK | M118: CFR | O118: DECOR LIGHTING | P118: Table lamp | R118: 20718901 | S118: LTLAT00002 | T118: Đèn trang trí FLOWERPOT VP9 DECORATIVE LIGHT dùng công nghệ LED, Kích thước (Đường kính 16 x cao 29.5) cm, 3W 2700K, Bằng PC và Thép. Màu be (Grey Beige). Hiệu: &TRADITION. Model: 20718901. Mới 100% | U118: 2 | V118: USD | X118: =W118*U118 -> 0 | Z118: 104.5 | AB118: =IF(AA118="F.O.C", 0, Z118*U118) -> 209 | AC118: =Z118*U118 -> 209 | AE118: 23310 | AF118: 0 | AG118: =(AC118*AE118+BO118+BP118+BQ118+BS118)*AF118 -> 0 | AI118: =(AC118*AE118+AG118+BF118+BG118+BH118+BJ118)*AH118 -> 0 | AJ118: IN230523091020 | AK118: 23/05/2023 | AO118: SEA | AQ118: 01/06/2023 | AV118: 105502791661 | AW118: 45086 | AX118: 09/06/2023 | BA118: Xong | BB118: BÌNH PHÚ | BC118: 45086 | BD118: Lô 7 | BE118: {=IF(BD118="","",AC118/SUMPRODUCT(--(BD118=$BD$4:$BD$12824),$AC$4:$AC$12824))} -> 0.0049178311 | BO118: =VLOOKUP(BD118,$BD$4:$BN$12824,3,0)*BE118 -> 0 | BR118: =VLOOKUP(BD118,$BD$4:$BN$12824,6,0)*BE118 -> 123662.22 | BS118: =VLOOKUP(BD118,$BD$4:$BN$12824,7,0)*BE118 -> 6512.6395 | BT118: 3193294 | BU118: =VLOOKUP(BD118,$BD$4:$BN$12824,9,0)*BE118 -> 2458.9156 | BW118: =VLOOKUP(BD118,$BD$4:$BN$12824,11,0)*BE118 -> 4917.8311 | BX118: =SUM(BO118:BW118) -> 3330845.6 | BY118: =(AB118*AE118+AG118+BX118)/U118 -> 4101317.8 | BZ118: =BY118*U118 -> 8202635.6 | CA118: =_xlfn.MAXIFS($BY$4:$BY$12824,$S$4:$S$12824,$S118) -> 4101317.8 | CF118: =AC118*AE118 -> 4871790
B119: Done | C119: NINE UNITED | D119: SC-&TRADITION-01-100423-FLOWERPOT VP9 | E119: PO-&TRADITION-01-100423-FLOWERPOT VP9 | F119: 45026 | G119: &Tradition | H119: STOCK | M119: CFR | O119: DECOR LIGHTING | P119: Table lamp | R119: 20719201 | S119: LTLAT00001 | T119: Đèn trang trí FLOWERPOT VP9 DECORATIVE LIGHT dùng công nghệ LED, Kích thước (Đường kính 16 x cao 29.5) cm, 3W 2700K, Bằng PC và Thép. Màu Lục (Signal Green).Hiệu: &TRADITION. Model: 20719201. Mới 100% | U119: 5 | V119: USD | X119: =W119*U119 -> 0 | Z119: 104.5 | AB119: =IF(AA119="F.O.C", 0, Z119*U119) -> 522.5 | AC119: =Z119*U119 -> 522.5 | AE119: 23310 | AF119: 0 | AG119: =(AC119*AE119+BO119+BP119+BQ119+BS119)*AF119 -> 0 | AI119: =(AC119*AE119+AG119+BF119+BG119+BH119+BJ119)*AH119 -> 0 | AJ119: IN230523091020 | AK119: 23/05/2023 | AO119: SEA | AQ119: 01/06/2023 | AV119: 105502791661 | AW119: 45086 | AX119: 09/06/2023 | BA119: Xong | BB119: BÌNH PHÚ | BC119: 45086 | BD119: Lô 7 | BE119: {=IF(BD119="","",AC119/SUMPRODUCT(--(BD119=$BD$4:$BD$12824),$AC$4:$AC$12824))} -> 0.012294578 | BO119: =VLOOKUP(BD119,$BD$4:$BN$12824,3,0)*BE119 -> 0 | BR119: =VLOOKUP(BD119,$BD$4:$BN$12824,6,0)*BE119 -> 309155.54 | BS119: =VLOOKUP(BD119,$BD$4:$BN$12824,7,0)*BE119 -> 16281.599 | BT119: 7983235.1 | BU119: =VLOOKUP(BD119,$BD$4:$BN$12824,9,0)*BE119 -> 6147.2889 | BW119: =VLOOKUP(BD119,$BD$4:$BN$12824,11,0)*BE119 -> 12294.578 | BX119: =SUM(BO119:BW119) -> 8327114.1 | BY119: =(AB119*AE119+AG119+BX119)/U119 -> 4101317.8 | BZ119: =BY119*U119 -> 20506589 | CA119: =_xlfn.MAXIFS($BY$4:$BY$12824,$S$4:$S$12824,$S119) -> 4101317.8 | CF119: =AC119*AE119 -> 12179475
B120: Done | C120: NINE UNITED | D120: SC-HAY-02-040423-PALISSADE | E120: PO-HAY-02-040423-PALISSADE | F120: 45020 | G120: HAY | H120: STOCK | M120: CFR | O120: FURNITURE | P120: Chairs | R120: AA615-A221 | S120: OUTHA00066 | T120: Ghế PALISSADE LOUNGE CHAIR LOW, Kích thước (Dài 73 x Rộng 81 x Cao 38/70) cm, Bằng Thép, Màu xám (SKY GREY). Hiệu: HAY. Model: AA615-A221. Mới 100% | U120: 4 | V120: USD | X120: =W120*U120 -> 0 | Z120: 156.465 | AB120: =IF(AA120="F.O.C", 0, Z120*U120) -> 625.86 | AC120: =Z120*U120 -> 625.86 | AE120: 23310 | AF120: 0 | AG120: =(AC120*AE120+BO120+BP120+BQ120+BS120)*AF120 -> 0 | AI120: =(AC120*AE120+AG120+BF120+BG120+BH120+BJ120)*AH120 -> 0 | AJ120: IN230523091020 | AK120: 23/05/2023 | AO120: SEA | AQ120: 01/06/2023 | AV120: 105502791661 | AW120: 45086 | AX120: 09/06/2023 | BA120: Xong | BB120: BÌNH PHÚ | BC120: 45086 | BD120: Lô 7 | BE120: {=IF(BD120="","",AC120/SUMPRODUCT(--(BD120=$BD$4:$BD$12824),$AC$4:$AC$12824))} -> 0.014726669 | BO120: =VLOOKUP(BD120,$BD$4:$BN$12824,3,0)*BE120 -> 0 | BR120: =VLOOKUP(BD120,$BD$4:$BN$12824,6,0)*BE120 -> 370312.13 | BS120: =VLOOKUP(BD120,$BD$4:$BN$12824,7,0)*BE120 -> 19502.395 | BU120: =VLOOKUP(BD120,$BD$4:$BN$12824,9,0)*BE120 -> 7363.3344 | BW120: =VLOOKUP(BD120,$BD$4:$BN$12824,11,0)*BE120 -> 14726.669 | BX120: =SUM(BO120:BW120) -> 411904.53 | BY120: =(AB120*AE120+AG120+BX120)/U120 -> 3750175.3 | BZ120: =BY120*U120 -> 15000701 | CA120: =_xlfn.MAXIFS($BY$4:$BY$12824,$S$4:$S$12824,$S120) -> 3750175.3 | CF120: =AC120*AE120 -> 14588797
B121: Done | C121: NINE UNITED | D121: SC-HAY-02-040423-PALISSADE | E121: PO-HAY-02-040423-PALISSADE | F121: 45020 | G121: HAY | H121: STOCK | M121: CFR | O121: FURNITURE | P121: Chairs | R121: AA615-A237 | S121: OUTHA00019 | T121: Ghế PALISSADE LOUNGE CHAIR LOW, Kích thước (Dài 73 x Rộng 81 x Cao 38/70) cm, Bằng Thép, Màu lục (OLIVE). Hiệu: HAY. Model: AA615-A237. Mới 100% | U121: 12 | V121: USD | X121: =W121*U121 -> 0 | Z121: 156.465 | AB121: =IF(AA121="F.O.C", 0, Z121*U121) -> 1877.58 | AC121: =Z121*U121 -> 1877.58 | AE121: 23310 | AF121: 0 | AG121: =(AC121*AE121+BO121+BP121+BQ121+BS121)*AF121 -> 0 | AI121: =(AC121*AE121+AG121+BF121+BG121+BH121+BJ121)*AH121 -> 0 | AJ121: IN230523091020 | AK121: 23/05/2023 | AO121: SEA | AQ121: 01/06/2023 | AV121: 105502791661 | AW121: 45086 | AX121: 09/06/2023 | BA121: Xong | BB121: BÌNH PHÚ | BC121: 45086 | BD121: Lô 7 | BE121: {=IF(BD121="","",AC121/SUMPRODUCT(--(BD121=$BD$4:$BD$12824),$AC$4:$AC$12824))} -> 0.044180006 | BO121: =VLOOKUP(BD121,$BD$4:$BN$12824,3,0)*BE121 -> 0 | BR121: =VLOOKUP(BD121,$BD$4:$BN$12824,6,0)*BE121 -> 1110936.4 | BS121: =VLOOKUP(BD121,$BD$4:$BN$12824,7,0)*BE121 -> 58507.185 | BU121: =VLOOKUP(BD121,$BD$4:$BN$12824,9,0)*BE121 -> 22090.003 | BW121: =VLOOKUP(BD121,$BD$4:$BN$12824,11,0)*BE121 -> 44180.006 | BX121: =SUM(BO121:BW121) -> 1235713.6 | BY121: =(AB121*AE121+AG121+BX121)/U121 -> 3750175.3 | BZ121: =BY121*U121 -> 45002103 | CA121: =_xlfn.MAXIFS($BY$4:$BY$12824,$S$4:$S$12824,$S121) -> 3750175.3 | CF121: =AC121*AE121 -> 43766390
B122: Done | C122: NINE UNITED | D122: SC-HAY-02-040423-PALISSADE | E122: PO-HAY-02-040423-PALISSADE | F122: 45020 | G122: HAY | H122: STOCK | M122: CFR | O122: FURNITURE | P122: Chairs | R122: AA616-A221 | S122: OUTHA00067 | T122: Ghế PALISSADE LOUNGE CHAIR HIGH, Kích thước (Dài 92 x Rộng 73 x Cao 38/88) cm, Bằng Thép, Màu xám (SKY GREY). Hiệu: HAY. Model: AA616-A221. Mới 100% | U122: 4 | V122: USD | X122: =W122*U122 -> 0 | Z122: 184.1675 | AB122: =IF(AA122="F.O.C", 0, Z122*U122) -> 736.67 | AC122: =Z122*U122 -> 736.67 | AE122: 23310 | AF122: 0 | AG122: =(AC122*AE122+BO122+BP122+BQ122+BS122)*AF122 -> 0 | AI122: =(AC122*AE122+AG122+BF122+BG122+BH122+BJ122)*AH122 -> 0 | AJ122: IN230523091020 | AK122: 23/05/2023 | AO122: SEA | AQ122: 01/06/2023 | AV122: 105502791661 | AW122: 45086 | AX122: 09/06/2023 | BA122: Xong | BB122: BÌNH PHÚ | BC122: 45086 | BD122: Lô 7 | BE122: {=IF(BD122="","",AC122/SUMPRODUCT(--(BD122=$BD$4:$BD$12824),$AC$4:$AC$12824))} -> 0.01733406 | BO122: =VLOOKUP(BD122,$BD$4:$BN$12824,3,0)*BE122 -> 0 | BR122: =VLOOKUP(BD122,$BD$4:$BN$12824,6,0)*BE122 -> 435876.77 | BS122: =VLOOKUP(BD122,$BD$4:$BN$12824,7,0)*BE122 -> 22955.34 | BU122: =VLOOKUP(BD122,$BD$4:$BN$12824,9,0)*BE122 -> 8667.0302 | BW122: =VLOOKUP(BD122,$BD$4:$BN$12824,11,0)*BE122 -> 17334.06 | BX122: =SUM(BO122:BW122) -> 484833.2 | BY122: =(AB122*AE122+AG122+BX122)/U122 -> 4414152.7 | BZ122: =BY122*U122 -> 17656611 | CA122: =_xlfn.MAXIFS($BY$4:$BY$12824,$S$4:$S$12824,$S122) -> 4414152.7 | CF122: =AC122*AE122 -> 17171778
B123: Done | C123: NINE UNITED | D123: SC-HAY-02-040423-PALISSADE | E123: PO-HAY-02-040423-PALISSADE | F123: 45020 | G123: HAY | H123: STOCK | M123: CFR | O123: FURNITURE | P123: Chairs | R123: AA616-A237 | S123: OUTHA00018 | T123: Ghế PALISSADE LOUNGE CHAIR HIGH, Kích thước (Dài 92 x Rộng 73 x Cao 38/88) cm, Bằng Thép, Màu lục (OLIVE). Hiệu: HAY. Model: AA616-A237. Mới 100% | U123: 10 | V123: USD | X123: =W123*U123 -> 0 | Z123: 184.167 | AB123: =IF(AA123="F.O.C", 0, Z123*U123) -> 1841.67 | AC123: =Z123*U123 -> 1841.67 | AE123: 23310 | AF123: 0 | AG123: =(AC123*AE123+BO123+BP123+BQ123+BS123)*AF123 -> 0 | AI123: =(AC123*AE123+AG123+BF123+BG123+BH123+BJ123)*AH123 -> 0 | AJ123: IN230523091020 | AK123: 23/05/2023 | AO123: SEA | AQ123: 01/06/2023 | AV123: 105502791661 | AW123: 45086 | AX123: 09/06/2023 | BA123: Xong | BB123: BÌNH PHÚ | BC123: 45086 | BD123: Lô 7 | BE123: {=IF(BD123="","",AC123/SUMPRODUCT(--(BD123=$BD$4:$BD$12824),$AC$4:$AC$12824))} -> 0.043335034 | BO123: =VLOOKUP(BD123,$BD$4:$BN$12824,3,0)*BE123 -> 0 | BR123: =VLOOKUP(BD123,$BD$4:$BN$12824,6,0)*BE123 -> 1089689 | BS123: =VLOOKUP(BD123,$BD$4:$BN$12824,7,0)*BE123 -> 57388.195 | BU123: =VLOOKUP(BD123,$BD$4:$BN$12824,9,0)*BE123 -> 21667.517 | BW123: =VLOOKUP(BD123,$BD$4:$BN$12824,11,0)*BE123 -> 43335.034 | BX123: =SUM(BO123:BW123) -> 1212079.7 | BY123: =(AB123*AE123+AG123+BX123)/U123 -> 4414140.7 | BZ123: =BY123*U123 -> 44141407 | CA123: =_xlfn.MAXIFS($BY$4:$BY$12824,$S$4:$S$12824,$S123) -> 4414140.7 | CF123: =AC123*AE123 -> 42929328
B124: Done | C124: NINE UNITED | D124: SC-HAY-02-040423-PALISSADE | E124: PO-HAY-02-040423-PALISSADE | F124: 45020 | G124: HAY | H124: STOCK | M124: CFR | O124: FURNITURE | P124: Chairs | R124: AA617-A221 | S124: OUTHA00068 | T124: Ghế PALISSADE LOUNGE SOFA, Kích thước (Dài 139 x Rộng 88 x Cao 38/70) cm, Bằng Thép, Màu xám (SKY GREY). Hiệu: HAY. Model: AA617-A221. Mới 100% | U124: 2 | V124: USD | X124: =W124*U124 -> 0 | Z124: 281.635 | AB124: =IF(AA124="F.O.C", 0, Z124*U124) -> 563.27 | AC124: =Z124*U124 -> 563.27 | AE124: 23310 | AF124: 0 | AG124: =(AC124*AE124+BO124+BP124+BQ124+BS124)*AF124 -> 0 | AI124: =(AC124*AE124+AG124+BF124+BG124+BH124+BJ124)*AH124 -> 0 | AJ124: IN230523091020 | AK124: 23/05/2023 | AO124: SEA | AQ124: 01/06/2023 | AV124: 105502791661 | AW124: 45086 | AX124: 09/06/2023 | BA124: Xong | BB124: BÌNH PHÚ | BC124: 45086 | BD124: Lô 7 | BE124: {=IF(BD124="","",AC124/SUMPRODUCT(--(BD124=$BD$4:$BD$12824),$AC$4:$AC$12824))} -> 0.013253908 | BO124: =VLOOKUP(BD124,$BD$4:$BN$12824,3,0)*BE124 -> 0 | BR124: =VLOOKUP(BD124,$BD$4:$BN$12824,6,0)*BE124 -> 333278.55 | BS124: =VLOOKUP(BD124,$BD$4:$BN$12824,7,0)*BE124 -> 17552.031 | BU124: =VLOOKUP(BD124,$BD$4:$BN$12824,9,0)*BE124 -> 6626.9539 | BW124: =VLOOKUP(BD124,$BD$4:$BN$12824,11,0)*BE124 -> 13253.908 | BX124: =SUM(BO124:BW124) -> 370711.44 | BY124: =(AB124*AE124+AG124+BX124)/U124 -> 6750267.6 | BZ124: =BY124*U124 -> 13500535 | CA124: =_xlfn.MAXIFS($BY$4:$BY$12824,$S$4:$S$12824,$S124) -> 6750267.6 | CF124: =AC124*AE124 -> 13129824
B125: Done | C125: NINE UNITED | D125: SC-HAY-02-040423-PALISSADE | E125: PO-HAY-02-040423-PALISSADE | F125: 45020 | G125: HAY | H125: STOCK | M125: CFR | O125: FURNITURE | P125: Chairs | R125: AA617-A237 | S125: OUTHA00021 | T125: Ghế PALISSADE LOUNGE SOFA, Kích thước (Dài 139 x Rộng 88 x Cao 38/70) cm, Bằng Thép, Màu lục (OLIVE). Hiệu: HAY. Model: AA617-A237. Mới 100% | U125: 6 | V125: USD | X125: =W125*U125 -> 0 | Z125: 281.63666 | AB125: =IF(AA125="F.O.C", 0, Z125*U125) -> 1689.82 | AC125: =Z125*U125 -> 1689.82 | AE125: 23310 | AF125: 0 | AG125: =(AC125*AE125+BO125+BP125+BQ125+BS125)*AF125 -> 0 | AI125: =(AC125*AE125+AG125+BF125+BG125+BH125+BJ125)*AH125 -> 0 | AJ125: IN230523091020 | AK125: 23/05/2023 | AO125: SEA | AQ125: 01/06/2023 | AV125: 105502791661 | AW125: 45086 | AX125: 09/06/2023 | BA125: Xong | BB125: BÌNH PHÚ | BC125: 45086 | BD125: Lô 7 | BE125: {=IF(BD125="","",AC125/SUMPRODUCT(--(BD125=$BD$4:$BD$12824),$AC$4:$AC$12824))} -> 0.039761958 | BO125: =VLOOKUP(BD125,$BD$4:$BN$12824,3,0)*BE125 -> 0 | BR125: =VLOOKUP(BD125,$BD$4:$BN$12824,6,0)*BE125 -> 999841.54 | BS125: =VLOOKUP(BD125,$BD$4:$BN$12824,7,0)*BE125 -> 52656.403 | BU125: =VLOOKUP(BD125,$BD$4:$BN$12824,9,0)*BE125 -> 19880.979 | BW125: =VLOOKUP(BD125,$BD$4:$BN$12824,11,0)*BE125 -> 39761.958 | BX125: =SUM(BO125:BW125) -> 1112140.9 | BY125: =(AB125*AE125+AG125+BX125)/U125 -> 6750307.4 | BZ125: =BY125*U125 -> 40501844 | CA125: =_xlfn.MAXIFS($BY$4:$BY$12824,$S$4:$S$12824,$S125) -> 6750307.4 | CF125: =AC125*AE125 -> 39389703
B126: Done | C126: NINE UNITED | D126: SC-HAY-02-040423-PALISSADE | E126: PO-HAY-02-040423-PALISSADE | F126: 45020 | G126: HAY | H126: STOCK | M126: CFR | O126: FURNITURE | P126: Chairs | R126: AA618-A221 | S126: OUTHA00069 | T126: Ghế PALISSADE OTTOMAN, Kích thước (Dài 65 x Rộng 60 x Cao 37) cm, Bằng Thép, Màu xám (SKY GREY). Hiệu: HAY. Model: AA618-A221. Mới 100% | U126: 6 | V126: USD | X126: =W126*U126 -> 0 | Z126: 101.57333 | AB126: =IF(AA126="F.O.C", 0, Z126*U126) -> 609.43998 | AC126: =Z126*U126 -> 609.43998 | AE126: 23310 | AF126: 0 | AG126: =(AC126*AE126+BO126+BP126+BQ126+BS126)*AF126 -> 0 | AI126: =(AC126*AE126+AG126+BF126+BG126+BH126+BJ126)*AH126 -> 0 | AJ126: IN230523091020 | AK126: 23/05/2023 | AO126: SEA | AQ126: 01/06/2023 | AV126: 105502791661 | AW126: 45086 | AX126: 09/06/2023 | BA126: Xong | BB126: BÌNH PHÚ | BC126: 45086 | BD126: Lô 7 | BE126: {=IF(BD126="","",AC126/SUMPRODUCT(--(BD126=$BD$4:$BD$12824),$AC$4:$AC$12824))} -> 0.014340301 | BO126: =VLOOKUP(BD126,$BD$4:$BN$12824,3,0)*BE126 -> 0 | BR126: =VLOOKUP(BD126,$BD$4:$BN$12824,6,0)*BE126 -> 360596.65 | BS126: =VLOOKUP(BD126,$BD$4:$BN$12824,7,0)*BE126 -> 18990.731 | BU126: =VLOOKUP(BD126,$BD$4:$BN$12824,9,0)*BE126 -> 7170.1505 | BW126: =VLOOKUP(BD126,$BD$4:$BN$12824,11,0)*BE126 -> 14340.301 | BX126: =SUM(BO126:BW126) -> 401097.83 | BY126: =(AB126*AE126+AG126+BX126)/U126 -> 2434524 | BZ126: =BY126*U126 -> 14607144 | CA126: =_xlfn.MAXIFS($BY$4:$BY$12824,$S$4:$S$12824,$S126) -> 2434524 | CF126: =AC126*AE126 -> 14206046
B127: Done | C127: NINE UNITED | D127: SC-HAY-02-040423-PALISSADE | E127: PO-HAY-02-040423-PALISSADE | F127: 45020 | G127: HAY | H127: STOCK | M127: CFR | O127: FURNITURE | P127: Chairs | R127: AA618-A237 | S127: OUTHA00022 | T127: Ghế PALISSADE OTTOMAN, Kích thước (Dài 65 x Rộng 60 x Cao 37) cm, Bằng Thép, Màu lục (OLIVE). Hiệu: HAY. Model: AA618-A237. Mới 100% | U127: 18 | V127: USD | X127: =W127*U127 -> 0 | Z127: 101.57388 | AB127: =IF(AA127="F.O.C", 0, Z127*U127) -> 1828.3298 | AC127: =Z127*U127 -> 1828.3298 | AE127: 23310 | AF127: 0 | AG127: =(AC127*AE127+BO127+BP127+BQ127+BS127)*AF127 -> 0 | AI127: =(AC127*AE127+AG127+BF127+BG127+BH127+BJ127)*AH127 -> 0 | AJ127: IN230523091020 | AK127: 23/05/2023 | AO127: SEA | AQ127: 01/06/2023 | AV127: 105502791661 | AW127: 45086 | AX127: 09/06/2023 | BA127: Xong | BB127: BÌNH PHÚ | BC127: 45086 | BD127: Lô 7 | BE127: {=IF(BD127="","",AC127/SUMPRODUCT(--(BD127=$BD$4:$BD$12824),$AC$4:$AC$12824))} -> 0.043021136 | BO127: =VLOOKUP(BD127,$BD$4:$BN$12824,3,0)*BE127 -> 0 | BR127: =VLOOKUP(BD127,$BD$4:$BN$12824,6,0)*BE127 -> 1081795.8 | BS127: =VLOOKUP(BD127,$BD$4:$BN$12824,7,0)*BE127 -> 56972.503 | BU127: =VLOOKUP(BD127,$BD$4:$BN$12824,9,0)*BE127 -> 21510.568 | BW127: =VLOOKUP(BD127,$BD$4:$BN$12824,11,0)*BE127 -> 43021.136 | BX127: =SUM(BO127:BW127) -> 1203300 | BY127: =(AB127*AE127+AG127+BX127)/U127 -> 2434537.1 | BZ127: =BY127*U127 -> 43821669 | CA127: =_xlfn.MAXIFS($BY$4:$BY$12824,$S$4:$S$12824,$S127) -> 2434537.1 | CF127: =AC127*AE127 -> 42618369
B128: Done | C128: NINE UNITED | D128: SC-HAY-02-040423-PALISSADE | E128: PO-HAY-02-040423-PALISSADE | F128: 45020 | G128: HAY | H128: STOCK | M128: CFR | O128: FURNITURE | P128: Table | R128: AA693-A376-AA79 | S128: OUTHA00070 | T128: Bàn PALISSADE TABLE L82.5xW90, Kích thước (Dài 82.5 x Rộng 90 x Cao 75) cm, Bằng Thép, Màu xám (SKY GREY). Hiệu: HAY. Model: AA693-A376-AA79. Mới 100% | U128: 2 | V128: USD | X128: =W128*U128 -> 0 | Z128: 215.46 | AB128: =IF(AA128="F.O.C", 0, Z128*U128) -> 430.92 | AC128: =Z128*U128 -> 430.92 | AE128: 23310 | AF128: 0.05 | AG128: =(AC128*AE128+BO128+BP128+BQ128+BS128)*AF128 -> 502908.65 | AI128: =(AC128*AE128+AG128+BF128+BG128+BH128+BJ128)*AH128 -> 0 | AJ128: IN230523091020 | AK128: 23/05/2023 | AO128: SEA | AQ128: 01/06/2023 | AV128: 105502791661 | AW128: 45086 | AX128: 09/06/2023 | BA128: Xong | BB128: BÌNH PHÚ | BC128: 45086 | BD128: Lô 7 | BE128: {=IF(BD128="","",AC128/SUMPRODUCT(--(BD128=$BD$4:$BD$12824),$AC$4:$AC$12824))} -> 0.010139674 | BO128: =VLOOKUP(BD128,$BD$4:$BN$12824,3,0)*BE128 -> 0 | BR128: =VLOOKUP(BD128,$BD$4:$BN$12824,6,0)*BE128 -> 254969.01 | BS128: =VLOOKUP(BD128,$BD$4:$BN$12824,7,0)*BE128 -> 13427.878 | BU128: =VLOOKUP(BD128,$BD$4:$BN$12824,9,0)*BE128 -> 5069.8368 | BW128: =VLOOKUP(BD128,$BD$4:$BN$12824,11,0)*BE128 -> 10139.674 | BX128: =SUM(BO128:BW128) -> 283606.4 | BY128: =(AB128*AE128+AG128+BX128)/U128 -> 5415630.1 | BZ128: =BY128*U128 -> 10831260 | CA128: =_xlfn.MAXIFS($BY$4:$BY$12824,$S$4:$S$12824,$S128) -> 5415630.1 | CF128: =AC128*AE128 -> 10044745
B129: Done | C129: NINE UNITED | D129: SC-HAY-02-040423-PALISSADE | E129: PO-HAY-02-040423-PALISSADE | F129: 45020 | G129: HAY | H129: STOCK | M129: CFR | O129: FURNITURE | P129: Table | R129: AA693-A376-AB03 | S129: OUTHA00005 | T129: Bàn PALISSADE TABLE L82.5xW90, Kích thước (Dài 82.5 x Rộng 90 x Cao 75) cm, Bằng Thép, Màu lục (OLIVE). Hiệu: HAY. Model: AA693-A376-AB03. Mới 100% | U129: 6 | V129: USD | X129: =W129*U129 -> 0 | Z129: 215.46 | AB129: =IF(AA129="F.O.C", 0, Z129*U129) -> 1292.76 | AC129: =Z129*U129 -> 1292.76 | AE129: 23310 | AF129: 0.05 | AG129: =(AC129*AE129+BO129+BP129+BQ129+BS129)*AF129 -> 1508726 | AI129: =(AC129*AE129+AG129+BF129+BG129+BH129+BJ129)*AH129 -> 0 | AJ129: IN230523091020 | AK129: 23/05/2023 | AO129: SEA | AQ129: 01/06/2023 | AV129: 105502791661 | AW129: 45086 | AX129: 09/06/2023 | BA129: Xong | BB129: BÌNH PHÚ | BC129: 45086 | BD129: Lô 7 | BE129: {=IF(BD129="","",AC129/SUMPRODUCT(--(BD129=$BD$4:$BD$12824),$AC$4:$AC$12824))} -> 0.030419021 | BO129: =VLOOKUP(BD129,$BD$4:$BN$12824,3,0)*BE129 -> 0 | BR129: =VLOOKUP(BD129,$BD$4:$BN$12824,6,0)*BE129 -> 764907.02 | BS129: =VLOOKUP(BD129,$BD$4:$BN$12824,7,0)*BE129 -> 40283.635 | BU129: =VLOOKUP(BD129,$BD$4:$BN$12824,9,0)*BE129 -> 15209.51 | BW129: =VLOOKUP(BD129,$BD$4:$BN$12824,11,0)*BE129 -> 30419.021 | BX129: =SUM(BO129:BW129) -> 850819.19 | BY129: =(AB129*AE129+AG129+BX129)/U129 -> 5415630.1 | BZ129: =BY129*U129 -> 32493781 | CA129: =_xlfn.MAXIFS($BY$4:$BY$12824,$S$4:$S$12824,$S129) -> 5415630.1 | CF129: =AC129*AE129 -> 30134236
B130: Done | C130: NINE UNITED | D130: SC-HAY-02-040423-PALISSADE | E130: PO-HAY-02-040423-PALISSADE | F130: 45020 | G130: HAY | H130: STOCK | M130: CFR | O130: FURNITURE | P130: Table | R130: AA693-A377-AA79 | S130: OUTHA00071 | T130: Bàn PALISSADE TABLE L170xW90, Kích thước (Dài 170 x Rộng 90 x Cao 75) cm, Bằng Thép, Màu xám (SKY GREY). Hiệu: HAY. Model: AA693-A377-AA79. Mới 100% | U130: 2 | V130: USD | X130: =W130*U130 -> 0 | Z130: 399.115 | AB130: =IF(AA130="F.O.C", 0, Z130*U130) -> 798.23 | AC130: =Z130*U130 -> 798.23 | AE130: 23310 | AF130: 0.05 | AG130: =(AC130*AE130+BO130+BP130+BQ130+BS130)*AF130 -> 931580.75 | AI130: =(AC130*AE130+AG130+BF130+BG130+BH130+BJ130)*AH130 -> 0 | AJ130: IN230523091020 | AK130: 23/05/2023 | AO130: SEA | AQ130: 01/06/2023 | AV130: 105502791661 | AW130: 45086 | AX130: 09/06/2023 | BA130: Xong | BB130: BÌNH PHÚ | BC130: 45086 | BD130: Lô 7 | BE130: {=IF(BD130="","",AC130/SUMPRODUCT(--(BD130=$BD$4:$BD$12824),$AC$4:$AC$12824))} -> 0.018782585 | BO130: =VLOOKUP(BD130,$BD$4:$BN$12824,3,0)*BE130 -> 0 | BR130: =VLOOKUP(BD130,$BD$4:$BN$12824,6,0)*BE130 -> 472300.92 | BS130: =VLOOKUP(BD130,$BD$4:$BN$12824,7,0)*BE130 -> 24873.609 | BU130: =VLOOKUP(BD130,$BD$4:$BN$12824,9,0)*BE130 -> 9391.2926 | BW130: =VLOOKUP(BD130,$BD$4:$BN$12824,11,0)*BE130 -> 18782.585 | BX130: =SUM(BO130:BW130) -> 525348.4 | BY130: =(AB130*AE130+AG130+BX130)/U130 -> 10031835 | BZ130: =BY130*U130 -> 20063670 | CA130: =_xlfn.MAXIFS($BY$4:$BY$12824,$S$4:$S$12824,$S130) -> 10031835 | CF130: =AC130*AE130 -> 18606741
B131: Done | C131: NINE UNITED | D131: SC-HAY-02-040423-PALISSADE | E131: PO-HAY-02-040423-PALISSADE | F131: 45020 | G131: HAY | H131: STOCK | M131: CFR | O131: FURNITURE | P131: Table | R131: AA693-A377-AB03 | S131: OUTHA00003 | T131: Bàn PALISSADE TABLE L170xW90, Kích thước (Dài 170 x Rộng 90 x Cao 75) cm, Bằng Thép, Màu lục (OLIVE). Hiệu: HAY. Model: AA693-A377-AB03. Mới 100% | U131: 13 | V131: USD | X131: =W131*U131 -> 0 | Z131: 399.11384 | AB131: =IF(AA131="F.O.C", 0, Z131*U131) -> 5188.4799 | AC131: =Z131*U131 -> 5188.4799 | AE131: 23310 | AF131: 0.05 | AG131: =(AC131*AE131+BO131+BP131+BQ131+BS131)*AF131 -> 6055257.2 | AI131: =(AC131*AE131+AG131+BF131+BG131+BH131+BJ131)*AH131 -> 0 | AJ131: IN230523091020 | AK131: 23/05/2023 | AO131: SEA | AQ131: 01/06/2023 | AV131: 105502791661 | AW131: 45086 | AX131: 09/06/2023 | BA131: Xong | BB131: BÌNH PHÚ | BC131: 45086 | BD131: Lô 7 | BE131: {=IF(BD131="","",AC131/SUMPRODUCT(--(BD131=$BD$4:$BD$12824),$AC$4:$AC$12824))} -> 0.12208645 | BO131: =VLOOKUP(BD131,$BD$4:$BN$12824,3,0)*BE131 -> 0 | BR131: =VLOOKUP(BD131,$BD$4:$BN$12824,6,0)*BE131 -> 3069947 | BS131: =VLOOKUP(BD131,$BD$4:$BN$12824,7,0)*BE131 -> 161677.99 | BU131: =VLOOKUP(BD131,$BD$4:$BN$12824,9,0)*BE131 -> 61043.225 | BW131: =VLOOKUP(BD131,$BD$4:$BN$12824,11,0)*BE131 -> 122086.45 | BX131: =SUM(BO131:BW131) -> 3414754.7 | BY131: =(AB131*AE131+AG131+BX131)/U131 -> 10031806 | BZ131: =BY131*U131 -> 1.3041348e+08 | CA131: =_xlfn.MAXIFS($BY$4:$BY$12824,$S$4:$S$12824,$S131) -> 10031806 | CF131: =AC131*AE131 -> 1.2094347e+08
... B135: Done | C135: NINE UNITED | D135: SC-HAY-02-040423-PALISSADE | E135: PO-HAY-02-040423-PALISSADE | F135: 45020 | G135: HAY | H135: STOCK | M135: CFR | O135: ACCESSORIES | P135: Cushion | R135: AB562-B293-AB70 | S135: SPAHA00010 | T135: Đệm PALISSADE-LOUNGE CHAIR LOW QUILTED CUSHION, Kích thước (Dài 117 x Rộng 49.5 x Cao 1) cm, Bằng Mút xốp. Bọc vải Olefin. Màu lục (OLIVE). Hiệu: HAY. Model: AB562-B293-AB70. Mới 100% | U135: 5 | V135: USD | X135: =W135*U135 -> 0 | Z135: 46.684 | AB135: =IF(AA135="F.O.C", 0, Z135*U135) -> 233.42 | AC135: =Z135*U135 -> 233.42 | AE135: 23310 | AF135: 0 | AG135: =(AC135*AE135+BO135+BP135+BQ135+BS135)*AF135 -> 0 | AI135: =(AC135*AE135+AG135+BF135+BG135+BH135+BJ135)*AH135 -> 0 | AJ135: IN230523091020 | AK135: 23/05/2023 | AO135: SEA | AQ135: 01/06/2023 | AV135: 105502791661 | AW135: 45086 | AX135: 09/06/2023 | BA135: Xong | BB135: BÌNH PHÚ | BC135: 45086 | BD135: Lô 7 | BE135: {=IF(BD135="","",AC135/SUMPRODUCT(--(BD135=$BD$4:$BD$12824),$AC$4:$AC$12824))} -> 0.0054924408 | BO135: =VLOOKUP(BD135,$BD$4:$BN$12824,3,0)*BE135 -> 0 | BR135: =VLOOKUP(BD135,$BD$4:$BN$12824,6,0)*BE135 -> 138111.17 | BS135: =VLOOKUP(BD135,$BD$4:$BN$12824,7,0)*BE135 -> 7273.59 | BU135: =VLOOKUP(BD135,$BD$4:$BN$12824,9,0)*BE135 -> 2746.2204 | BW135: =VLOOKUP(BD135,$BD$4:$BN$12824,11,0)*BE135 -> 5492.4408 | BX135: =SUM(BO135:BW135) -> 153623.42 | BY135: =(AB135*AE135+AG135+BX135)/U135 -> 1118928.7 | BZ135: =BY135*U135 -> 5594643.6 | CA135: =_xlfn.MAXIFS($BY$4:$BY$12824,$S$4:$S$12824,$S135) -> 1118928.7 | CF135: =AC135*AE135 -> 5441020.2
B136: Done | C136: MUUTO | D136: SC-MUUTO-02-070323-APPLE HCM-03 | E136: =D136 -> SC-MUUTO-02-070323-APPLE HCM-03 | F136: 44992 | G136: Muuto | H136: PRE-ORDER | M136: DAP | O136: FURNITURE | P136: Chairs | R136: 32069 | S136: MTO-STL-00006 | T136: Ghế NERD BAR STOOL, Dài 45cm Rộng 44cm, Cao 75cm (tính từ mặt ghế). Bằng Gỗ sồi (Oak), Màu Nâu (Dark Brown). Hiệu MUUTO. MODEL:32069. Mới 100% | U136: 16 | V136: EUR | X136: =W136*U136 -> 0 | Z136: 242 | AB136: =IF(AA136="F.O.C", 0, Z136*U136) -> 3872 | AC136: =Z136*U136 -> 3872 | AE136: 25481.03 | AF136: 0 | AG136: =(AC136*AE136+BO136+BP136+BQ136+BS136)*AF136 -> 0 | AI136: =(AC136*AE136+AG136+BF136+BG136+BH136+BJ136)*AH136 -> 0 | AJ136: 10453063 | AK136: 08/03/2023 | AO136: SEA | AQ136: 21/03/2023 | AV136: 105449483310 | AW136: 45057 | AX136: 11/05/2023 | BA136: Xong | BB136: BÌNH PHÚ | BC136: 45061 | BD136: Lô 8 | BE136: {=IF(BD136="","",AC136/SUMPRODUCT(--(BD136=$BD$4:$BD$12824),$AC$4:$AC$12824))} -> 1 | BN136: =600000 -> 600000 | BO136: =VLOOKUP(BD136,$BD$4:$BN$12824,3,0)*BE136 -> 0 | BR136: =VLOOKUP(BD136,$BD$4:$BN$12824,6,0)*BE136 -> 0 | BS136: =VLOOKUP(BD136,$BD$4:$BN$12824,7,0)*BE136 -> 0 | BU136: =VLOOKUP(BD136,$BD$4:$BN$12824,9,0)*BE136 -> 0 | BW136: =VLOOKUP(BD136,$BD$4:$BN$12824,11,0)*BE136 -> 600000 | BX136: =SUM(BO136:BW136) -> 600000 | BY136: =(AB136*AE136+AG136+BX136)/U136 -> 6203909.3 | BZ136: =BY136*U136 -> 99262548 | CA136: =_xlfn.MAXIFS($BY$4:$BY$12824,$S$4:$S$12824,$S136) -> 6203909.3 | CF136: =AC136*AE136 -> 98662548
B137: Done | C137: USM | D137: SC-USM-01-180123-STK | E137: SC-USM-01-180123-STK | F137: 44944 | G137: USM | H137: STOCK | M137: FCA | O137: FURNITURE | P137: Table | R137: USMUS00178 | S137: USMUS00178 | T137: Bàn văn phòng USM HALLER, USMUS00178, Kích thước (dài 723 x rộng 723 x cao 390 mm), Bằng Kim loại, Thủy tinh, Màu Trong suốt (Transparent), Màu Be (USM Beige). Hiệu USM. Mới 100% | U137: 1 | V137: EUR | X137: =W137*U137 -> 0 | Z137: 601.56 | AB137: =IF(AA137="F.O.C", 0, Z137*U137) -> 601.56 | AC137: =Z137*U137 -> 601.56 | AE137: 25481.03 | AF137: 0.1 | AG137: =(AC137*AE137+BO137+BP137+BQ137+BS137)*AF137 -> 1634467.9 | AI137: =(AC137*AE137+AG137+BF137+BG137+BH137+BJ137)*AH137 -> 0 | AJ137: 102081208 | AK137: 14/03/2023 | AO137: SEA | AQ137: 30/03/2023 | AV137: 105448332950 | AW137: 45058 | AX137: 12/05/2023 | BA137: Xong | BB137: BÌNH PHÚ | BC137: 45058 | BD137: Lô 9.1 | BE137: {=IF(BD137="","",AC137/SUMPRODUCT(--(BD137=$BD$4:$BD$12824),$AC$4:$AC$12824))} -> 0.01283592 | BF137: 79177049 | BI137: 18950800 | BO137: =VLOOKUP(BD137,$BD$4:$BN$12824,3,0)*BE137 -> 1016310.2 | BR137: =VLOOKUP(BD137,$BD$4:$BN$12824,6,0)*BE137 -> 243250.95 | BS137: =VLOOKUP(BD137,$BD$4:$BN$12824,7,0)*BE137 -> 0 | BU137: =VLOOKUP(BD137,$BD$4:$BN$12824,9,0)*BE137 -> 0 | BW137: =VLOOKUP(BD137,$BD$4:$BN$12824,11,0)*BE137 -> 0 | BX137: =SUM(BO137:BW137) -> 1259561.2 | BY137: =(AB137*AE137+AG137+BX137)/U137 -> 18222397 | BZ137: =BY137*U137 -> 18222397 | CA137: =_xlfn.MAXIFS($BY$4:$BY$12824,$S$4:$S$12824,$S137) -> 18222397 | CF137: =AC137*AE137 -> 15328368
B138: Done | C138: USM | D138: SC-USM-01-180123-STK | E138: SC-USM-01-180123-STK | F138: 44944 | G138: USM | H138: STOCK | M138: FCA | O138: FURNITURE | P138: Table | R138: USMUS00173 | S138: USMUS00173 | T138: Bàn văn phòng USM HALLER, USMUS00173, Kích thước (dài 723 x rộng 723 x cao 390 mm), Bằng Kim loại, Thủy tinh, Màu Trong suốt (Transparent), Màu Cam (Pure Orange). Hiệu USM. Mới 100% | U138: 1 | V138: EUR | X138: =W138*U138 -> 0 | Z138: 601.56 | AB138: =IF(AA138="F.O.C", 0, Z138*U138) -> 601.56 | AC138: =Z138*U138 -> 601.56 | AE138: 25481.03 | AF138: 0.1 | AG138: =(AC138*AE138+BO138+BP138+BQ138+BS138)*AF138 -> 1634467.9 | AI138: =(AC138*AE138+AG138+BF138+BG138+BH138+BJ138)*AH138 -> 0 | AJ138: 102081208 | AK138: 14/03/2023 | AO138: SEA | AQ138: 30/03/2023 | AV138: 105448332950 | AW138: 45058 | AX138: 12/05/2023 | BA138: Xong | BB138: BÌNH PHÚ | BC138: 45058 | BD138: Lô 9.1 | BE138: {=IF(BD138="","",AC138/SUMPRODUCT(--(BD138=$BD$4:$BD$12824),$AC$4:$AC$12824))} -> 0.01283592 | BO138: =VLOOKUP(BD138,$BD$4:$BN$12824,3,0)*BE138 -> 1016310.2 | BR138: =VLOOKUP(BD138,$BD$4:$BN$12824,6,0)*BE138 -> 243250.95 | BS138: =VLOOKUP(BD138,$BD$4:$BN$12824,7,0)*BE138 -> 0 | BU138: =VLOOKUP(BD138,$BD$4:$BN$12824,9,0)*BE138 -> 0 | BW138: =VLOOKUP(BD138,$BD$4:$BN$12824,11,0)*BE138 -> 0 | BX138: =SUM(BO138:BW138) -> 1259561.2 | BY138: =(AB138*AE138+AG138+BX138)/U138 -> 18222397 | BZ138: =BY138*U138 -> 18222397 | CA138: =_xlfn.MAXIFS($BY$4:$BY$12824,$S$4:$S$12824,$S138) -> 18222397 | CF138: =AC138*AE138 -> 15328368
B139: Done | C139: USM | D139: SC-USM-01-180123-STK | E139: SC-USM-01-180123-STK | F139: 44944 | G139: USM | H139: STOCK | M139: FCA | O139: FURNITURE | P139: Table | R139: USMUS00143 | S139: USMUS00143 | T139: Bàn văn phòng USM HALLER, USMUS00143, Kích thước (dài 723 x rộng 723 x cao 390 mm), Bằng Kim loại, Thủy tinh, Màu Trong suốt (Transparent), Màu Trắng (Pure White). Hiệu USM. Mới 100% | U139: 2 | V139: EUR | X139: =W139*U139 -> 0 | Z139: 581.155 | AB139: =IF(AA139="F.O.C", 0, Z139*U139) -> 1162.31 | AC139: =Z139*U139 -> 1162.31 | AE139: 25481.03 | AF139: 0.1 | AG139: =(AC139*AE139+BO139+BP139+BQ139+BS139)*AF139 -> 3158053 | AI139: =(AC139*AE139+AG139+BF139+BG139+BH139+BJ139)*AH139 -> 0 | AJ139: 102081208 | AK139: 14/03/2023 | AO139: SEA | AQ139: 30/03/2023 | AV139: 105448332950 | AW139: 45058 | AX139: 12/05/2023 | BA139: Xong | BB139: BÌNH PHÚ | BC139: 45058 | BD139: Lô 9.1 | BE139: {=IF(BD139="","",AC139/SUMPRODUCT(--(BD139=$BD$4:$BD$12824),$AC$4:$AC$12824))} -> 0.024801047 | BO139: =VLOOKUP(BD139,$BD$4:$BN$12824,3,0)*BE139 -> 1963673.7 | BR139: =VLOOKUP(BD139,$BD$4:$BN$12824,6,0)*BE139 -> 469999.68 | BS139: =VLOOKUP(BD139,$BD$4:$BN$12824,7,0)*BE139 -> 0 | BU139: =VLOOKUP(BD139,$BD$4:$BN$12824,9,0)*BE139 -> 0 | BW139: =VLOOKUP(BD139,$BD$4:$BN$12824,11,0)*BE139 -> 0 | BX139: =SUM(BO139:BW139) -> 2433673.4 | BY139: =(AB139*AE139+AG139+BX139)/U139 -> 17604291 | BZ139: =BY139*U139 -> 35208582 | CA139: =_xlfn.MAXIFS($BY$4:$BY$12824,$S$4:$S$12824,$S139) -> 17604291 | CF139: =AC139*AE139 -> 29616856
B140: Done | C140: USM | D140: SC-USM-01-180123-STK | E140: SC-USM-01-180123-STK | F140: 44944 | G140: USM | H140: STOCK | M140: FCA | O140: FURNITURE | P140: Table | R140: USMUS00144 | S140: USMUS00144 | T140: Bàn văn phòng USM HALLER, USMUS00144, Kích thước (dài 723 x rộng 723 x cao 390 mm), Bằng Kim loại, Thủy tinh, Màu Trong suốt (Transparent), Màu Vàng (Golden Yellow). Hiệu USM. Mới 100% | U140: 1 | V140: EUR | X140: =W140*U140 -> 0 | Z140: 581.16 | AB140: =IF(AA140="F.O.C", 0, Z140*U140) -> 581.16 | AC140: =Z140*U140 -> 581.16 | AE140: 25481.03 | AF140: 0.1 | AG140: =(AC140*AE140+BO140+BP140+BQ140+BS140)*AF140 -> 1579040.1 | AI140: =(AC140*AE140+AG140+BF140+BG140+BH140+BJ140)*AH140 -> 0 | AJ140: 102081208 | AK140: 14/03/2023 | AO140: SEA | AQ140: 30/03/2023 | AV140: 105448332950 | AW140: 45058 | AX140: 12/05/2023 | BA140: Xong | BB140: BÌNH PHÚ | BC140: 45058 | BD140: Lô 9.1 | BE140: {=IF(BD140="","",AC140/SUMPRODUCT(--(BD140=$BD$4:$BD$12824),$AC$4:$AC$12824))} -> 0.01240063 | BO140: =VLOOKUP(BD140,$BD$4:$BN$12824,3,0)*BE140 -> 981845.31 | BR140: =VLOOKUP(BD140,$BD$4:$BN$12824,6,0)*BE140 -> 235001.86 | BS140: =VLOOKUP(BD140,$BD$4:$BN$12824,7,0)*BE140 -> 0 | BU140: =VLOOKUP(BD140,$BD$4:$BN$12824,9,0)*BE140 -> 0 | BW140: =VLOOKUP(BD140,$BD$4:$BN$12824,11,0)*BE140 -> 0 | BX140: =SUM(BO140:BW140) -> 1216847.2 | BY140: =(AB140*AE140+AG140+BX140)/U140 -> 17604443 | BZ140: =BY140*U140 -> 17604443 | CA140: =_xlfn.MAXIFS($BY$4:$BY$12824,$S$4:$S$12824,$S140) -> 17604443 | CF140: =AC140*AE140 -> 14808555
B141: Done | C141: USM | D141: SC-USM-01-180123-STK | E141: SC-USM-01-180123-STK | F141: 44944 | G141: USM | H141: STOCK | M141: FCA | O141: FURNITURE | P141: Table | R141: USMUS00199 | S141: USMUS00199 | T141: Bàn văn phòng USM HALLER, USMUS00199, Kích thước (dài 1023 x rộng 1023 x cao 390 mm), Bằng Kim loại, Thủy tinh, Màu Trong suốt (Transparent), Màu Trắng (Pure White). Hiệu USM. Mới 100% | U141: 1 | V141: EUR | X141: =W141*U141 -> 0 | Z141: 693.64 | AB141: =IF(AA141="F.O.C", 0, Z141*U141) -> 693.64 | AC141: =Z141*U141 -> 693.64 | AE141: 25481.03 | AF141: 0.1 | AG141: =(AC141*AE141+BO141+BP141+BQ141+BS141)*AF141 -> 1884653.7 | AI141: =(AC141*AE141+AG141+BF141+BG141+BH141+BJ141)*AH141 -> 0 | AJ141: 102081208 | AK141: 14/03/2023 | AO141: SEA | AQ141: 30/03/2023 | AV141: 105448332950 | AW141: 45058 | AX141: 12/05/2023 | BA141: Xong | BB141: BÌNH PHÚ | BC141: 45058 | BD141: Lô 9.1 | BE141: {=IF(BD141="","",AC141/SUMPRODUCT(--(BD141=$BD$4:$BD$12824),$AC$4:$AC$12824))} -> 0.014800697 | BO141: =VLOOKUP(BD141,$BD$4:$BN$12824,3,0)*BE141 -> 1171875.5 | BR141: =VLOOKUP(BD141,$BD$4:$BN$12824,6,0)*BE141 -> 280485.05 | BS141: =VLOOKUP(BD141,$BD$4:$BN$12824,7,0)*BE141 -> 0 | BU141: =VLOOKUP(BD141,$BD$4:$BN$12824,9,0)*BE141 -> 0 | BW141: =VLOOKUP(BD141,$BD$4:$BN$12824,11,0)*BE141 -> 0 | BX141: =SUM(BO141:BW141) -> 1452360.6 | BY141: =(AB141*AE141+AG141+BX141)/U141 -> 21011676 | BZ141: =BY141*U141 -> 21011676 | CA141: =_xlfn.MAXIFS($BY$4:$BY$12824,$S$4:$S$12824,$S141) -> 21011676 | CF141: =AC141*AE141 -> 17674662
B142: Done | C142: USM | D142: SC-USM-01-180123-STK | E142: SC-USM-01-180123-STK | F142: 44944 | G142: USM | H142: STOCK | M142: FCA | O142: FURNITURE | P142: Table | R142: USMUS00205 | S142: USMUS00205 | T142: Bàn văn phòng USM HALLER, USMUS00205, Kích thước (dài 1023 x rộng 1023 x cao 390 mm), Bằng Kim loại, Thủy tinh, Màu Trong suốt (Transparent), Màu Đen (Graphite Black). Hiệu USM. Mới 100% | U142: 1 | V142: EUR | X142: =W142*U142 -> 0 | Z142: 693.58 | AB142: =IF(AA142="F.O.C", 0, Z142*U142) -> 693.58 | AC142: =Z142*U142 -> 693.58 | AE142: 25481.03 | AF142: 0.1 | AG142: =(AC142*AE142+BO142+BP142+BQ142+BS142)*AF142 -> 1884490.7 | AI142: =(AC142*AE142+AG142+BF142+BG142+BH142+BJ142)*AH142 -> 0 | AJ142: 102081208 | AK142: 14/03/2023 | AO142: SEA | AQ142: 30/03/2023 | AV142: 105448332950 | AW142: 45058 | AX142: 12/05/2023 | BA142: Xong | BB142: BÌNH PHÚ | BC142: 45058 | BD142: Lô 9.1 | BE142: {=IF(BD142="","",AC142/SUMPRODUCT(--(BD142=$BD$4:$BD$12824),$AC$4:$AC$12824))} -> 0.014799417 | BO142: =VLOOKUP(BD142,$BD$4:$BN$12824,3,0)*BE142 -> 1171774.2 | BR142: =VLOOKUP(BD142,$BD$4:$BN$12824,6,0)*BE142 -> 280460.79 | BS142: =VLOOKUP(BD142,$BD$4:$BN$12824,7,0)*BE142 -> 0 | BU142: =VLOOKUP(BD142,$BD$4:$BN$12824,9,0)*BE142 -> 0 | BW142: =VLOOKUP(BD142,$BD$4:$BN$12824,11,0)*BE142 -> 0 | BX142: =SUM(BO142:BW142) -> 1452234.9 | BY142: =(AB142*AE142+AG142+BX142)/U142 -> 21009858 | BZ142: =BY142*U142 -> 21009858 | CA142: =_xlfn.MAXIFS($BY$4:$BY$12824,$S$4:$S$12824,$S142) -> 21009858 | CF142: =AC142*AE142 -> 17673133
B143: Done | C143: USM | D143: SC-USM-01-180123-STK | E143: SC-USM-01-180123-STK | F143: 44944 | G143: USM | H143: STOCK | M143: FCA | O143: FURNITURE | P143: Cabinet | R143: USMUS00018 | S143: USMUS00018 | T143: Kệ nội thất văn phòng USM HALLER có tay cầm, USMUS00018, Kích thước (dài 523 x rộng 373 x cao 63 mm), Bằng Kim loại, Màu Vàng (Golden Yellow). Hiệu USM. Mới 100% | U143: 2 | V143: EUR | X143: =W143*U143 -> 0 | Z143: 149.235 | AB143: =IF(AA143="F.O.C", 0, Z143*U143) -> 298.47 | AC143: =Z143*U143 -> 298.47 | AE143: 25481.03 | AF143: 0.1 | AG143: =(AC143*AE143+BO143+BP143+BQ143+BS143)*AF143 -> 810957.55 | AI143: =(AC143*AE143+AG143+BF143+BG143+BH143+BJ143)*AH143 -> 0 | AJ143: 102081208 | AK143: 14/03/2023 | AO143: SEA | AQ143: 30/03/2023 | AV143: 105448332950 | AW143: 45058 | AX143: 12/05/2023 | BA143: Xong | BB143: BÌNH PHÚ | BC143: 45058 | BD143: Lô 9.1 | BE143: {=IF(BD143="","",AC143/SUMPRODUCT(--(BD143=$BD$4:$BD$12824),$AC$4:$AC$12824))} -> 0.0063686697 | BO143: =VLOOKUP(BD143,$BD$4:$BN$12824,3,0)*BE143 -> 504252.48 | BR143: =VLOOKUP(BD143,$BD$4:$BN$12824,6,0)*BE143 -> 120691.39 | BS143: =VLOOKUP(BD143,$BD$4:$BN$12824,7,0)*BE143 -> 0 | BU143: =VLOOKUP(BD143,$BD$4:$BN$12824,9,0)*BE143 -> 0 | BW143: =VLOOKUP(BD143,$BD$4:$BN$12824,11,0)*BE143 -> 0 | BX143: =SUM(BO143:BW143) -> 624943.86 | BY143: =(AB143*AE143+AG143+BX143)/U143 -> 4520612.2 | BZ143: =BY143*U143 -> 9041224.4 | CA143: =_xlfn.MAXIFS($BY$4:$BY$12824,$S$4:$S$12824,$S143) -> 4520612.2 | CF143: =AC143*AE143 -> 7605323
B144: Done | C144: USM | D144: SC-USM-01-180123-STK | E144: SC-USM-01-180123-STK | F144: 44944 | G144: USM | H144: STOCK | M144: FCA | O144: FURNITURE | P144: Cabinet | R144: USMUS00019 | S144: USMUS00019 | T144: Kệ nội thất văn phòng USM HALLER có tay cầm, USMUS00019, Kích thước (dài 523 x rộng 373 x cao 63 mm), Bằng Kim loại, Màu Cam (Pure Orange). Hiệu USM. Mới 100% | U144: 2 | V144: EUR | X144: =W144*U144 -> 0 | Z144: 149.235 | AB144: =IF(AA144="F.O.C", 0, Z144*U144) -> 298.47 | AC144: =Z144*U144 -> 298.47 | AE144: 25481.03 | AF144: 0.1 | AG144: =(AC144*AE144+BO144+BP144+BQ144+BS144)*AF144 -> 810957.55 | AI144: =(AC144*AE144+AG144+BF144+BG144+BH144+BJ144)*AH144 -> 0 | AJ144: 102081208 | AK144: 14/03/2023 | AO144: SEA | AQ144: 30/03/2023 | AV144: 105448332950 | AW144: 45058 | AX144: 12/05/2023 | BA144: Xong | BB144: BÌNH PHÚ | BC144: 45058 | BD144: Lô 9.1 | BE144: {=IF(BD144="","",AC144/SUMPRODUCT(--(BD144=$BD$4:$BD$12824),$AC$4:$AC$12824))} -> 0.0063686697 | BO144: =VLOOKUP(BD144,$BD$4:$BN$12824,3,0)*BE144 -> 504252.48 | BR144: =VLOOKUP(BD144,$BD$4:$BN$12824,6,0)*BE144 -> 120691.39 | BS144: =VLOOKUP(BD144,$BD$4:$BN$12824,7,0)*BE144 -> 0 | BU144: =VLOOKUP(BD144,$BD$4:$BN$12824,9,0)*BE144 -> 0 | BW144: =VLOOKUP(BD144,$BD$4:$BN$12824,11,0)*BE144 -> 0 | BX144: =SUM(BO144:BW144) -> 624943.86 | BY144: =(AB144*AE144+AG144+BX144)/U144 -> 4520612.2 | BZ144: =BY144*U144 -> 9041224.4 | CA144: =_xlfn.MAXIFS($BY$4:$BY$12824,$S$4:$S$12824,$S144) -> 4520612.2 | CF144: =AC144*AE144 -> 7605323
B145: Done | C145: USM | D145: SC-USM-01-180123-STK | E145: SC-USM-01-180123-STK | F145: 44944 | G145: USM | H145: STOCK | M145: FCA | O145: FURNITURE | P145: Cabinet | R145: USMUS00021 | S145: USMUS00021 | T145: Kệ nội thất văn phòng USM HALLER có tay cầm, USMUS00021, Kích thước (dài 523 x rộng 373 x cao 63 mm), Bằng Kim loại, Màu Lục (USM Green). Hiệu USM. Mới 100% | U145: 2 | V145: EUR | X145: =W145*U145 -> 0 | Z145: 149.235 | AB145: =IF(AA145="F.O.C", 0, Z145*U145) -> 298.47 | AC145: =Z145*U145 -> 298.47 | AE145: 25481.03 | AF145: 0.1 | AG145: =(AC145*AE145+BO145+BP145+BQ145+BS145)*AF145 -> 810957.55 | AI145: =(AC145*AE145+AG145+BF145+BG145+BH145+BJ145)*AH145 -> 0 | AJ145: 102081208 | AK145: 14/03/2023 | AO145: SEA | AQ145: 30/03/2023 | AV145: 105448332950 | AW145: 45058 | AX145: 12/05/2023 | BA145: Xong | BB145: BÌNH PHÚ | BC145: 45058 | BD145: Lô 9.1 | BE145: {=IF(BD145="","",AC145/SUMPRODUCT(--(BD145=$BD$4:$BD$12824),$AC$4:$AC$12824))} -> 0.0063686697 | BO145: =VLOOKUP(BD145,$BD$4:$BN$12824,3,0)*BE145 -> 504252.48 | BR145: =VLOOKUP(BD145,$BD$4:$BN$12824,6,0)*BE145 -> 120691.39 | BS145: =VLOOKUP(BD145,$BD$4:$BN$12824,7,0)*BE145 -> 0 | BU145: =VLOOKUP(BD145,$BD$4:$BN$12824,9,0)*BE145 -> 0 | BW145: =VLOOKUP(BD145,$BD$4:$BN$12824,11,0)*BE145 -> 0 | BX145: =SUM(BO145:BW145) -> 624943.86 | BY145: =(AB145*AE145+AG145+BX145)/U145 -> 4520612.2 | BZ145: =BY145*U145 -> 9041224.4 | CA145: =_xlfn.MAXIFS($BY$4:$BY$12824,$S$4:$S$12824,$S145) -> 4520612.2 | CF145: =AC145*AE145 -> 7605323
B146: Done | C146: USM | D146: SC-USM-01-180123-STK | E146: SC-USM-01-180123-STK | F146: 44944 | G146: USM | H146: STOCK | M146: FCA | O146: FURNITURE | P146: Cabinet | R146: USMUS00023 | S146: USMUS00023 | T146: Kệ nội thất văn phòng USM HALLER có tay cầm, USMUS00023, Kích thước (dài 523 x rộng 373 x cao 63 mm), Bằng Kim loại, Màu Đen (Graphite Black). Hiệu USM. Mới 100% | U146: 2 | V146: EUR | X146: =W146*U146 -> 0 | Z146: 149.225 | AB146: =IF(AA146="F.O.C", 0, Z146*U146) -> 298.45 | AC146: =Z146*U146 -> 298.45 | AE146: 25481.03 | AF146: 0.1 | AG146: =(AC146*AE146+BO146+BP146+BQ146+BS146)*AF146 -> 810903.21 | AI146: =(AC146*AE146+AG146+BF146+BG146+BH146+BJ146)*AH146 -> 0 | AJ146: 102081208 | AK146: 14/03/2023 | AO146: SEA | AQ146: 30/03/2023 | AV146: 105448332950 | AW146: 45058 | AX146: 12/05/2023 | BA146: Xong | BB146: BÌNH PHÚ | BC146: 45058 | BD146: Lô 9.1 | BE146: {=IF(BD146="","",AC146/SUMPRODUCT(--(BD146=$BD$4:$BD$12824),$AC$4:$AC$12824))} -> 0.006368243 | BO146: =VLOOKUP(BD146,$BD$4:$BN$12824,3,0)*BE146 -> 504218.69 | BR146: =VLOOKUP(BD146,$BD$4:$BN$12824,6,0)*BE146 -> 120683.3 | BS146: =VLOOKUP(BD146,$BD$4:$BN$12824,7,0)*BE146 -> 0 | BU146: =VLOOKUP(BD146,$BD$4:$BN$12824,9,0)*BE146 -> 0 | BW146: =VLOOKUP(BD146,$BD$4:$BN$12824,11,0)*BE146 -> 0 | BX146: =SUM(BO146:BW146) -> 624901.99 | BY146: =(AB146*AE146+AG146+BX146)/U146 -> 4520309.3 | BZ146: =BY146*U146 -> 9040618.6 | CA146: =_xlfn.MAXIFS($BY$4:$BY$12824,$S$4:$S$12824,$S146) -> 4520309.3 | CF146: =AC146*AE146 -> 7604813.4
B147: Done | C147: USM | D147: SC-USM-01-180123-STK | E147: SC-USM-01-180123-STK | F147: 44944 | G147: USM | H147: STOCK | M147: FCA | O147: FURNITURE | P147: Cabinet | R147: USMUS00101 | S147: USMUS00101 | T147: Tủ nội thất văn phòng USM HALLER, USMUS00101, Kích thước (dài 1523 x rộng 373 x cao 390 mm), Bằng Kim loại, Màu Trắng (Pure White). Hiệu USM. Mới 100% | U147: 1 | V147: EUR | X147: =W147*U147 -> 0 | Z147: 1900.09 | AB147: =IF(AA147="F.O.C", 0, Z147*U147) -> 1900.09 | AC147: =Z147*U147 -> 1900.09 | AE147: 25481.03 | AF147: 0.1 | AG147: =(AC147*AE147+BO147+BP147+BQ147+BS147)*AF147 -> 5162637.2 | AI147: =(AC147*AE147+AG147+BF147+BG147+BH147+BJ147)*AH147 -> 0 | AJ147: 102081208 | AK147: 14/03/2023 | AO147: SEA | AQ147: 30/03/2023 | AV147: 105448332950 | AW147: 45058 | AX147: 12/05/2023 | BA147: Xong | BB147: BÌNH PHÚ | BC147: 45058 | BD147: Lô 9.1 | BE147: {=IF(BD147="","",AC147/SUMPRODUCT(--(BD147=$BD$4:$BD$12824),$AC$4:$AC$12824))} -> 0.040543591 | BO147: =VLOOKUP(BD147,$BD$4:$BN$12824,3,0)*BE147 -> 3210121.9 | BR147: =VLOOKUP(BD147,$BD$4:$BN$12824,6,0)*BE147 -> 768333.49 | BS147: =VLOOKUP(BD147,$BD$4:$BN$12824,7,0)*BE147 -> 0 | BU147: =VLOOKUP(BD147,$BD$4:$BN$12824,9,0)*BE147 -> 0 | BW147: =VLOOKUP(BD147,$BD$4:$BN$12824,11,0)*BE147 -> 0 | BX147: =SUM(BO147:BW147) -> 3978455.4 | BY147: =(AB147*AE147+AG147+BX147)/U147 -> 57557343 | BZ147: =BY147*U147 -> 57557343 | CA147: =_xlfn.MAXIFS($BY$4:$BY$12824,$S$4:$S$12824,$S147) -> 57557343 | CF147: =AC147*AE147 -> 48416250
B148: Done | C148: USM | D148: SC-USM-01-180123-STK | E148: SC-USM-01-180123-STK | F148: 44944 | G148: USM | H148: STOCK | M148: FCA | O148: FURNITURE | P148: Cabinet | R148: USMUS00102 | S148: USMUS00102 | T148: Tủ nội thất văn phòng USM HALLER, USMUS00102, Kích thước (dài 1523 x rộng 373 x cao 390 mm), Bằng Kim loại, Màu Vàng (Golden Yellow). Hiệu USM. Mới 100% | U148: 1 | V148: EUR | X148: =W148*U148 -> 0 | Z148: 452.96 | AB148: =IF(AA148="F.O.C", 0, Z148*U148) -> 452.96 | AC148: =Z148*U148 -> 452.96 | AE148: 25481.03 | AF148: 0.1 | AG148: =(AC148*AE148+BO148+BP148+BQ148+BS148)*AF148 -> 1230714.4 | AI148: =(AC148*AE148+AG148+BF148+BG148+BH148+BJ148)*AH148 -> 0 | AJ148: 102081208 | AK148: 14/03/2023 | AO148: SEA | AQ148: 30/03/2023 | AV148: 105448332950 | AW148: 45058 | AX148: 12/05/2023 | BA148: Xong | BB148: BÌNH PHÚ | BC148: 45058 | BD148: Lô 9.1 | BE148: {=IF(BD148="","",AC148/SUMPRODUCT(--(BD148=$BD$4:$BD$12824),$AC$4:$AC$12824))} -> 0.0096651344 | BO148: =VLOOKUP(BD148,$BD$4:$BN$12824,3,0)*BE148 -> 765256.82 | BR148: =VLOOKUP(BD148,$BD$4:$BN$12824,6,0)*BE148 -> 183162.03 | BS148: =VLOOKUP(BD148,$BD$4:$BN$12824,7,0)*BE148 -> 0 | BU148: =VLOOKUP(BD148,$BD$4:$BN$12824,9,0)*BE148 -> 0 | BW148: =VLOOKUP(BD148,$BD$4:$BN$12824,11,0)*BE148 -> 0 | BX148: =SUM(BO148:BW148) -> 948418.84 | BY148: =(AB148*AE148+AG148+BX148)/U148 -> 13721021 | BZ148: =BY148*U148 -> 13721021 | CA148: =_xlfn.MAXIFS($BY$4:$BY$12824,$S$4:$S$12824,$S148) -> 13721021 | CF148: =AC148*AE148 -> 11541887
B149: Done | C149: USM | D149: SC-USM-01-180123-STK | E149: SC-USM-01-180123-STK | F149: 44944 | G149: USM | H149: STOCK | M149: FCA | O149: FURNITURE | P149: Cabinet | R149: USMUS00103 | S149: USMUS00103 | T149: Tủ nội thất văn phòng USM HALLER, USMUS00103, Kích thước (dài 1523 x rộng 373 x cao 390 mm), Bằng Kim loại, Màu Cam (Pure Orange). Hiệu USM. Mới 100% | U149: 1 | V149: EUR | X149: =W149*U149 -> 0 | Z149: 452.96 | AB149: =IF(AA149="F.O.C", 0, Z149*U149) -> 452.96 | AC149: =Z149*U149 -> 452.96 | AE149: 25481.03 | AF149: 0.1 | AG149: =(AC149*AE149+BO149+BP149+BQ149+BS149)*AF149 -> 1230714.4 | AI149: =(AC149*AE149+AG149+BF149+BG149+BH149+BJ149)*AH149 -> 0 | AJ149: 102081208 | AK149: 14/03/2023 | AO149: SEA | AQ149: 30/03/2023 | AV149: 105448332950 | AW149: 45058 | AX149: 12/05/2023 | BA149: Xong | BB149: BÌNH PHÚ | BC149: 45058 | BD149: Lô 9.1 | BE149: {=IF(BD149="","",AC149/SUMPRODUCT(--(BD149=$BD$4:$BD$12824),$AC$4:$AC$12824))} -> 0.0096651344 | BO149: =VLOOKUP(BD149,$BD$4:$BN$12824,3,0)*BE149 -> 765256.82 | BR149: =VLOOKUP(BD149,$BD$4:$BN$12824,6,0)*BE149 -> 183162.03 | BS149: =VLOOKUP(BD149,$BD$4:$BN$12824,7,0)*BE149 -> 0 | BU149: =VLOOKUP(BD149,$BD$4:$BN$12824,9,0)*BE149 -> 0 | BW149: =VLOOKUP(BD149,$BD$4:$BN$12824,11,0)*BE149 -> 0 | BX149: =SUM(BO149:BW149) -> 948418.84 | BY149: =(AB149*AE149+AG149+BX149)/U149 -> 13721021 | BZ149: =BY149*U149 -> 13721021 | CA149: =_xlfn.MAXIFS($BY$4:$BY$12824,$S$4:$S$12824,$S149) -> 13721021 | CF149: =AC149*AE149 -> 11541887
...

Sheet Cost
B1: THÔNG TIN CHUNG | H1: BẢO HIỂM | L1: THUẾ | O1: VẬN CHUYỂN | Z1: KHAI HẢI QUAN VÀ CÁC PHI PHÍ LIÊN QUAN
B2: Hãng | C2: Số Bill | D2: SC | E2: Invoice | F2: Số lô | H2: Bảo hiểm (chưa VAT) =Total/1.1 (10%) | J2: Thanh toán | L2: Thuế NK | M2: Thuế VAT | O2: FWD | P2: EXW+OF | R2: Local charge (include VAT) | T2: Lưu kho (include VAT) | V2: Trucking nội địa (include VAT) | X2: Thanh toán | Z2: Phí Dịch vụ khai Hải quan (+VAT) | AB2: Lệ phí hải quan | AC2: Phí sử dụng cơ sở hạ tầng (SEA) | AE2: Phí dịch vụ chi ngoài (+VAT) | AG2: Phí dịch vụ bốc dỡ (AIR) (+VAT) | AI2: Chuyển bãi nội bộ (SEA) (+VAT) | AK2: Phí rút đóng kiểm hóa (SEA) (+VAT) | AM2: Phí nâng cont | AO2: Phí hạ rỗng | AQ2: Thanh toán | AS2: THỬ NGHIỆM | AV2: Thông báo nhập kho
I3: Cost 3 | Q3: Cost 1 | S3: Cost 2 | U3: Cost 2 | W3: Cost 2 | AA3: Cost 5 | AB3: Cost 4 | AD3: Cost 4 | AF3: Cost 5 | AH3: Cost 5 | AJ3: Cost 5 | AL3: Cost 5 | AN3: Cost 5 | AP3: Cost 5 | AT3: Cost 6
H4: HĐ | I4: Số tiền | P4: HĐ | Q4: Số tiền | R4: HĐ | S4: Số tiền | T4: HĐ | U4: Số tiền | V4: HĐ | W4: Số tiền | Z4: HĐ | AA4: Số tiền | AC4: HĐ | AD4: Số tiền | AE4: HĐ | AF4: Số tiền | AG4: HĐ | AH4: Số tiền | AI4: HĐ | AJ4: Số tiền | AK4: HĐ | AL4: Số tiền | AM4: HĐ | AN4: Số tiền | AO4: HĐ | AP4: Số tiền | AS4: HĐ | AT4: Số tiền
B5: Santa&Cole | C5: 250401582/0111 | D5: SC-S&C-01-281224-DH-SHOWROOM | E5: SC-S&C-01-281224-DH-SHOWROOM | F5: Lô 68 | H5: 4963 | I5: 546197 | J5: Đã TT | L5: 47492627 | M5: 47492627 | O5: Bách Việt | P5: 17199 | Q5: 11967068 | R5: 18465 | S5: =7161281-W5 -> 4461281 | T5: no | U5: 0 | V5: 18465 | W5: 2700000 | X5: Đã TT | Z5: 1853 | AA5: 648000 | AB5: 20000 | AC5: 1350202 | AD5: 3585 | AE5: no | AF5: 0 | AG5: no | AH5: 0 | AI5: no | AJ5: 0 | AK5: no | AL5: 0 | AM5: no | AN5: 0 | AO5: no | AP5: 0 | AQ5: Đã TT | AV5: Rồi
B6: Vitra | C6: FRA-00011902 | D6: NNH-VT-2025-002-1906-RIMOWA | E6: 5085293 | F6: Lô 69 | H6: no | I6: 0 | J6: / | L6: 0 | M6: 10584585 | O6: Bách Việt | P6: 18908 | Q6: 16471563 | R6: 19546 | S6: =1774947-W6 -> 1133427 | T6: 234093 bach viet+'231456 dynamic (lưu kho +phục vụ hàng nhập) | U6: =656003+1245548 -> 1901551 | V6: 19546 | W6: =594000*1.08 -> 641520 | X6: Đã TT | Z6: 1995 | AA6: 1188000 | AB6: 20000 | AC6: no | AD6: 0 | AE6: no | AF6: 0 | AG6: no | AH6: 0 | AI6: no | AJ6: 0 | AK6: no | AL6: 0 | AM6: no | AN6: 0 | AO6: no | AP6: 0 | AQ6: Đã TT | AV6: Rồi
B7: Vitra | C7: SDBJOS016565 | D7: NNH-VT-03-231224-DH-0002612; SC-VT-2025-180125-STOCK | E7: 5084714 / 1 | F7: Lô 70 | H7: 5991 | I7: 1350952 | J7: Đã TT | L7: =4507715+1139719 -> 5647434 | M7: =102642190+18228001 -> 120870191 | O7: SAVINO | P7: 6496 | Q7: 35874160 | R7: 6497 | S7: 7817040 | T7: 6846 | U7: 3797963 | V7: 7186 | W7: 5702400 | X7: Đã TT | Z7: 2130 | AA7: 1188000 | AB7: 40000 | AC7: 1515372 | AD7: 500000 | AE7: 2130 | AF7: 2592000 | AG7: no | AH7: 0 | AI7: 3679 | AJ7: 559000 | AK7: 1022138 | AL7: 1745000 | AM7: 1025647 savino chi ho | AN7: 2068000 | AO7: 277585 savino chi hộ | AP7: 1500000 | AQ7: Đã TT | AV7: Rồi
B8: USM | C8: 618-25519572 | D8: NNH-USM-2025-007-2406 (AIR) | E8: 102088938 | F8: Lô 71 | H8: no | I8: 0 | J8: / | L8: 12567148 | M8: 11059090 | O8: POCO | P8: 1767 | Q8: 18953694 | R8: 245701 | S8: =244200*1.08 -> 263736 | T8: 245701 | U8: =246050*1.08 -> 265734 | V8: 1785 | W8: 323568 | X8: Đã TT | Z8: no | AA8: 0 | AB8: 20000 | AC8: no | AD8: 0 | AE8: no | AF8: 0 | AG8: no | AH8: 0 | AI8: no | AJ8: 0 | AK8: no | AL8: 0 | AM8: no | AN8: 0 | AO8: no | AP8: 0 | AQ8: Đã TT | AV8: Rồi
B9: VIABIZZUNO 1st | C9: SMIL00439401 | D9: NNH-VB-2025-001-1503 (đợt 1) | E9: NNNH-VB-2025-001-2.377/03 | F9: Lô 72 | H9: no | I9: 0 | J9: / | L9: 0 | M9: 63355129 | O9: D.B | P9: 2773 | Q9: 23221422 | R9: 2774 | S9: 370235 | T9: 3216 30/08/2025 | U9: =690814*1.08 -> 746079.12 | V9: 3216 30/08/2025 | W9: 1127792 | X9: Đã TT | Z9: 2148 | AA9: =1100000*1.08 -> 1188000 | AB9: 20000 | AC9: no | AD9: 0 | AE9: 2148 | AF9: 5184000 | AG9: 229273 | AH9: 176796 | AI9: no | AJ9: 0 | AK9: no | AL9: 0 | AM9: no | AN9: 0 | AO9: no | AP9: 0 | AQ9: Đã TT | AV9: Rồi
B10: USM | C10: 01/25/300247 | D10: NNH-USM-2025-004-1503 | E10: 102087998 | F10: Lô 73 | H10: 6685 | I10: 337385 | J10: Đã TT | L10: 36246334 | M10: 31896774 | O10: Bách Việt | P10: 21694 13/ 08/ 2025 | Q10: 13757654 | R10: 22430 20/ 08/ 2025 | S10: =4447749-W10 -> 3691749 | T10: no | U10: 0 | V10: 22430 20/ 08/ 2025 | W10: =756000 -> 756000 | X10: Đã TT | Z10: no | AA10: 0 | AB10: 20000 | AC10: 1630441 | AD10: 12195 | AE10: no | AF10: 0 | AG10: no | AH10: 0 | AI10: no | AJ10: 0 | AK10: no | AL10: 0 | AM10: no | AN10: 0 | AO10: no | AP10: 0 | AQ10: Đã TT | AV10: Rồi
B11: Fritz Hansen | C11: SDK0111260 | D11: NNH-FH-2025-001-2103-DH-0002924 | E11: 100150372 | F11: Lô 74 | H11: 6415 | I11: 250000 | J11: Đã TT | L11: 0 | M11: 20681841 | O11: Macnel | P11: 14190 13/08/2025 | Q11: 8061150 | R11: 14189 13/08/2025 | S11: 2919521 | T11: no | U11: 0 | V11: 14450 18/08/2025 | W11: 941965 | X11: Đã TT | Z11: 2181 | AA11: 648000 | AB11: 20000 | AC11: 1630440 | AD11: 3675 | AE11: no | AF11: 0 | AG11: no | AH11: 0 | AI11: no | AJ11: 0 | AK11: no | AL11: 0 | AM11: no | AN11: 0 | AO11: no | AP11: 0 | AQ11: Đã TT | AV11: Rồi
B12: Knoll | C12: SOTA00433847 | D12: NNH-KN-2025-003-2503-SR Date 25/03/2025; NNH-KN-2025-002-1103-DH-0002924 Date 11/03/2025 | E12: 053617 - 053920 | F12: Lô 75 | H12: 6917 | I12: 250000 | J12: Đã TT | L12: 31796442 | M12: 14826155 | O12: D.B | P12: 3022 19/08/2025 | Q12: 6163875 | R12: 3023 19/08/2025 | S12: 5441070 | T12: no | U12: 0 | V12: 3217 30/08/2025 | W12: =996773 -> 996773 | X12: Đã TT | Z12: 2362 | AA12: 648000 | AB12: 20000 | AD12: 1350 | AE12: no | AF12: 0 | AG12: no | AH12: 0 | AI12: no | AJ12: 0 | AK12: no | AL12: 0 | AM12: no | AN12: 0 | AO12: no | AP12: 0 | AQ12: Đã TT | AV12: Rồi
B13: Louis Poulsen | C13: 618-37227794 | D13: NNH-LPS-2025-004-0108-DH-0003788 | E13: 053617 - 053920 | F13: Lô 77 | H13: no | I13: 0 | J13: / | L13: 0 | M13: 3967869 | O13: POCO | P13: 1977 25/08/2025 | Q13: 11386400 | R13: no | S13: 0 | T13: 281857 | U13: 486000 | V13: 2140 09/09/2025 | W13: 571968 | X13: Đã TT | Z13: 2411 | AA13: 648000 | AB13: 20000 | AC13: no | AD13: 0 | AE13: no | AF13: 0 | AG13: no | AH13: 0 | AI13: no | AJ13: 0 | AK13: no | AL13: 0 | AM13: no | AN13: 0 | AO13: no | AP13: 0 | AQ13: Đã TT | AV13: Rồi
B14: Santa&Cole 2 &BD | C14: 250402065/0413 | D14: SC-S&C-01-281224-DH-SHOWROOM | E14: SCN-FV25-03354 | F14: Lô 76 | H14: no | I14: 0 | J14: / | L14: 0 | M14: 7063086 | O14: CP | P14: no | Q14: 0 | R14: no | S14: 0 | T14: no | U14: 0 | V14: no | W14: 0 | X14: / | Z14: no | AA14: 0 | AB14: - | AC14: no | AD14: 0 | AE14: no | AF14: 0 | AG14: no | AH14: 0 | AI14: no | AJ14: 0 | AK14: no | AL14: 0 | AM14: no | AN14: 0 | AO14: no | AP14: 0 | AQ14: Đã TT | AV14: Rồi
B15: FONTANA ARTE | D15: NNH-FA-2025-001 | F15: Lô 78 | H15: no | I15: 0 | J15: / | L15: 0 | M15: 254015 | O15: Fedex | P15: no | Q15: 0 | R15: no | S15: 0 | T15: no | U15: 0 | V15: no | W15: 0 | X15: / | Z15: no | AA15: 0 | AB15: - | AC15: no | AD15: 0 | AE15: no | AF15: 0 | AG15: no | AH15: 0 | AI15: no | AJ15: 0 | AK15: no | AL15: 0 | AM15: no | AN15: 0 | AO15: no | AP15: 0 | AQ15: Đã TT | AV15: Rồi
B16: VIABIZZUNO 2rd | C16: 73482058 | D16: NNH-VB-2025-001-1503-DH-0003027 | E16: NNNH-VB-2025-001-2.377/03-2 | F16: Lô 80 | H16: no | I16: 0 | J16: / | L16: 0 | M16: 7082444.6 | O16: D.B | P16: 3299 08/09/2025 | Q16: 13476109 | R16: no | S16: 0 | T16: no | U16: 0 | V16: no | W16: 0 | X16: Đã TT | Z16: no | AA16: 0 | AB16: 20000 | AC16: no | AD16: 0 | AE16: no | AF16: 0 | AG16: no | AH16: 0 | AI16: no | AJ16: 0 | AK16: no | AL16: 0 | AM16: no | AN16: 0 | AO16: no | AP16: 0 | AQ16: Đã TT | AV16: Rồi
B17: Flos mini button | C17: IT72505803 | D17: NNH-FLOS-2025-006-1408-DH-0003915 | E17: 2503005586 | F17: Lô 79 | H17: no | I17: 0 | J17: / | L17: 0 | M17: 2471859 | O17: Long Hoàng | P17: 5623 08/09/2025 | Q17: 8479040 | R17: 263092 10/09/2025 | S17: 162000 | T17: 263092 10/09/2025 | U17: 287280 | V17: 5728 10/09/2025 | W17: 572335 | X17: Đã TT | Z17: 2454 | AA17: 648000 | AB17: 20000 | AC17: no | AD17: 0 | AE17: no | AF17: 0 | AG17: no | AH17: 0 | AI17: no | AJ17: 0 | AK17: no | AL17: 0 | AM17: no | AN17: 0 | AO17: no | AP17: 0 | AQ17: Đã TT | AV17: Rồi
B18: Stoff | C18: SPRJ051413 | D18: NNH-ST-2025-001-1706 | E18: 289375 | F18: Lô 82 | H18: 8037 | I18: =250000/1.1 -> 227272.73 | J18: Đã TT | L18: 62262732 | M18: 25432665 | O18: Long Hoàng | P18: 6017 22/09/2025 | Q18: 16131450 | R18: no | S18: 0 | T18: no | U18: 0 | V18: 6171 29/09/2025 | W18: 428409 | X18: Đã TT | Z18: no | AA18: 0 | AB18: 20000 | AC18: 1931672 | AD18: 2625 | AE18: no | AF18: 0 | AG18: no | AH18: 0 | AI18: no | AJ18: 0 | AK18: no | AL18: 0 | AM18: no | AN18: 0 | AO18: no | AP18: 0 | AQ18: Đã TT | AV18: Rồi
B19: Louis Poulsen | C19: SPRJ051412 | D19: NNH-LPS-2025-002-2702-PANTHELLA | E19: NNH-LPS-2025-001 | F19: Lô 81 | H19: 8038 | I19: =797715/1.1 -> 725195.45 | J19: Đã TT | L19: 109593283 | M19: 76322736 | P19: 6016 22/09/2025 | Q19: 22478250 | R19: no | T19: 116945 25/09/2025 | U19: 277757 | V19: 6172 29/09/2025 | W19: 1285227 | X19: Đã TT | Z19: 2621 | AA19: 648000 | AB19: 20000 | AC19: 1931623 | AD19: 6119 | AE19: không lấy HĐ | AF19: 1500000 | AG19: no | AH19: 0 | AI19: no | AJ19: 0 | AK19: no | AL19: 0 | AM19: no | AN19: 0 | AO19: no | AP19: 0 | AQ19: Đã TT | AS19: 3705 18/10/2025 | AT19: 26250000 | AV19: Rồi
B20: Nine United | C20: 142502762202 | D20: NNH-NU-2025-002-1408 | E20: NNH-NU-2025-002-1408 | F20: Lô 83 | H20: 9041 | I20: =655372/1.1 -> 595792.73 | J20: Đã TT | L20: 37840502 | M20: 54832196 | O20: / | P20: no | R20: 261408 22/09/2025 | S20: 5443400 | T20: 269651 29/09/2025 & 269074 26/09/2025 | U20: 220000 | V20: 6361 07/10/2025 | W20: 3456000 | X20: Đã TT | Z20: 2675 | AA20: 1188000 | AB20: 20000 | AC20: 1915261 | AD20: 250000 | AE20: no | AF20: 0 | AG20: no | AH20: 0 | AI20: 4854 & 4831 | AJ20: 794000 | AK20: 1288529 | AL20: 1248000 | AM20: 1300172 Long hoàng | AN20: 1410000 | AO20: 285158 long hoàng | AP20: 999000 | AQ20: Đã TT | AV20: Rồi
B21: ECOLUX 6 | C21: SVLCL202509395 | D21: NNH-EC-2025-006-0208-STOCK | E21: NNH-EC-2025-006 | F21: Lô 84 | H21: 9760 | I21: =1357013/1.1 -> 1233648.2 | J21: Đã TT | L21: 0 | M21: 68195985 | O21: Long Hoàng | P21: 6274 02/10/2025 | Q21: 26435 | R21: no | S21: 0 | T21: no | U21: 0 | V21: 6697 20/10/2025 | W21: 970693 | X21: Đã TT | Z21: 2723 | AA21: 648000 | AB21: 20000 | AC21: 2031178 | AD21: 25718 | AE21: no | AF21: 0 | AG21: no | AH21: 0 | AI21: no | AJ21: 0 | AK21: no | AL21: 0 | AM21: no | AN21: 0 | AO21: no | AP21: 0 | AQ21: Đã TT | AV21: Rồi
B22: ECOLUX 7-9 | C22: SVLCL202509251 | D22: NNH-EC-2025-007-0208-DH-0003828 NNH-EC-2025-009-0708-DH-0003753 | E22: NNH-EC-2025-007-9 | F22: Lô 85 | H22: 9378 | I22: =713879/1.1 -> 648980.91 | J22: Đã TT | L22: 0 | M22: 52532981 | O22: Long Hoàng | P22: 6323 03/10/2025 | Q22: 26420 | R22: no | S22: 0 | T22: no | U22: 0 | V22: no | W22: 0 | X22: Đã TT | Z22: 2747 | AA22: 648000 | AB22: 20000 | AC22: 2043528 | AD22: 11768 | AE22: no | AF22: 0 | AG22: no | AH22: 0 | AI22: no | AJ22: 0 | AK22: no | AL22: 0 | AM22: no | AN22: 0 | AO22: no | AP22: 0 | AQ22: Đã TT | AV22: Rồi
B23: ECOLUX routine | C23: SVLCL202510307 | D23: NNH-EC-2025-013-0910-DH-0004233 | E23: NNH-EC-2025-013-0910 | F23: Lô 86 | H23: no | I23: 0 | J23: / | L23: 0 | M23: 7580631 | O23: Long hoàng | P23: 7052 03/11/2025 đã cấn trừ 1USD cho lô sau | Q23: 26347 | R23: no | S23: 0 | T23: no | U23: 0 | V23: no | W23: 0 | X23: Đã TT | Z23: 3099 | AA23: 648000 | AB23: 20000 | AD23: 2108 | AE23: no | AG23: no | AH23: 0 | AI23: no | AJ23: 0 | AK23: no | AL23: 0 | AM23: no | AO23: no | AQ23: Đã TT | AV23: Rồi
B24: Frizt hansen 002 | C24: 251084200 | D24: NNH-FH-2025-002-2708 | E24: 200112233 | F24: Lô 87 | H24: 9168 | I24: =4815029/1.1 -> 4377299.1 | J24: Đã TT | L24: 0 | M24: 354564477 | O24: POCO | P24: 2652 31/10/2025 | Q24: 29769850 | R24: 2850 25/11/2025 | S24: 7397676 | T24: no | U24: 0 | V24: 2850 25/11/2025 | W24: 5690520 | X24: Đã TT | Z24: 3067 | AA24: 648000 | AB24: 20000 | AC24: 2291769 | AD24: 500000 | AE24: không lấy HĐ | AF24: 1800000 | AG24: no | AH24: 0 | AI24: no | AJ24: 0 | AK24: no | AL24: 0 | AM24: 239277 poco đã chi hộ | AN24: 1103000 | AO24: 403793 poco đã chi hộ | AP24: 1500000 | AQ24: Đã TT | AV24: Rồi
B25: Flos SPRING CP | C25: SMIL00449992 | D25: NNH-FLOS-2025-003-2504-SPRING CP | E25: NNH-FLOS-2025-003-2504 | F25: Lô 88 | H25: 8912 | I25: =345096/1.1 -> 313723.64 | J25: Đã TT | L25: 8927886 | M25: 34411273 | O25: DB | P25: 4068 29/10/2025 | Q25: 4514532 | R25: 4069 29/10/2025 | S25: 886283 | T25: no | U25: 0 | V25: no | W25: 0 | X25: Đã TT | Z25: 3066 | AA25: 648000 | AB25: 20000 | AC25: no | AD25: 0 | AE25: no | AF25: 0 | AG25: no | AH25: 0 | AI25: no | AJ25: 0 | AK25: no | AL25: 0 | AQ25: Đã TT | AV25: Rồi
B26: Cassina/1 | C26: SMIL00447392 | D26: 001-002-003(1)-004(1) | E26: NNH-CS-2025-001.002.003-01 | F26: Lô 89 | H26: 8913 | I26: =7657089/1.1 -> 6960990 | J26: Đã TT | L26: =74027345+42692470+79864961 -> 196584776 | M26: =217363830+293807946+70942766 -> 582114542 | O26: DB | P26: 4066 29/10/2025 | Q26: 42314749 | R26: 4067 29/10/2025 +90K | S26: =8306698 +90000 -> 8396698 | T26: 00311168 | U26: =225000 -> 225000 | V26: no | W26: 0 | X26: Đã TT | Z26: 3068 | AA26: =1728000 -> 1728000 | AB26: 60000 | AC26: 2277589 | AD26: 500000 | AE26: no | AF26: 0 | AG26: no | AH26: 0 | AI26: no | AJ26: 0 | AK26: no | AL26: 0 | AM26: 1476121 D.B | AN26: 2182000 | AO26: 329438 D.B | AP26: 1512000 | AQ26: Đã TT | AV26: Rồi
B27: USM Fedex | C27: 885573901972 | D27: NNH-USM-2025-014-0610 | E27: 102089408 | F27: Lô 90 | H27: no | I27: 0 | J27: / | L27: 1115995 | M27: 982076 | O27: FEDEX | P27: 40294 24/11/2025 | Q27: 4714934 | R27: no | S27: 0 | T27: no | U27: 0 | V27: no | W27: 0 | X27: Đã TT | Z27: no | AA27: 0 | AB27: - | AC27: no | AD27: 0 | AE27: no | AF27: 0 | AG27: no | AH27: 0 | AI27: no | AJ27: 0 | AK27: no | AL27: 0 | AM27: no | AN27: 0 | AO27: no | AP27: 0 | AQ27: Đã TT | AV27: Rồi
B28: ECOLUX thủ thiêm | C28: SMLCL25100078 | D28: NNH-EC-2025-012-2609-DH-0003985 | E28: NNH-EC-2025-012-2609 | F28: Lô 91 | H28: no | I28: 0 | J28: / | L28: 0 | M28: 4522871 | O28: POCO | P28: 2742 11/11/2025 | Q28: 3955950 | R28: 2851 25/11/2025 | S28: 1424142 | T28: no | U28: 0 | V28: 2851 25/11/2025 | W28: 712071 | X28: Đã TT | Z28: 3145 600k chi ngoài hải quan | AA28: 1296000 | AB28: 20000 | AC28: 2344766 | AD28: 1785 | AE28: no | AF28: 0 | AG28: no | AH28: 0 | AI28: no | AJ28: 0 | AK28: no | AL28: 0 | AM28: no | AN28: 0 | AO28: no | AP28: 0 | AQ28: Đã TT | AV28: Rồi
B29: USM-008 | C29: 01/25/300417 | D29: NNH-USM-2025-008-2708 | E29: 102089058 | F29: Lô 92 | H29: 9776 | I29: =3433287/1.1 -> 3121170 | J29: Đã TT | L29: 313833301 | M29: 276173305 | O29: REAL | P29: 7374 25/11/2025 | Q29: 38558073 | R29: 7373 25/11/2025 | S29: 14326352 | T29: no | U29: 0 | V29: 8281 02/12/2025 | W29: 3414830 | X29: Đã TT | Z29: no | AA29: 0 | AB29: 20000 | AC29: 2459987 | AD29: 101115 | AE29: no | AF29: 0 | AG29: no | AH29: 0 | AI29: no | AJ29: 0 | AK29: no | AL29: 0 | AM29: no | AN29: 0 | AO29: no | AP29: 0 | AQ29: Đã TT | AV29: Rồi
B30: Fritz hansen 006 | C30: 072505392 | D30: NNH-FH-2025-006-2608 | E30: NNH-FH-2025-006-2608 | F30: Lô 93 | H30: 10371 | I30: =965674/1.1 -> 877885.45 | J30: Đã TT | L30: 22497760 | M30: 74729194 | O30: TCI | P30: 11452 03/12/2025 | Q30: 21841070 | R30: 11451 03/12/2025 | S30: 5704560 | T30: no | U30: 0 | V30: 11769 16/12/2025 | W30: 6026296 | X30: Đã TT | Z30: 3451 | AA30: 648000 | AB30: 20000 | AC30: 2539756 | AD30: 250000 | AE30: no | AF30: 0 | AG30: no | AH30: 0 | AI30: no | AJ30: 0 | AK30: no | AL30: 0 | AM30: 269526 TCI đã chi hộ | AN30: 631000 | AO30: 271148 TCI đã chi hộ | AP30: 382000 | AQ30: Đã TT | AV30: Rồi
B31: Ecolux Akyn | C31: SVLCL202511313 | D31: NNH-EC-2025-015-2510-DH-0003934 | E31: NNH-EC-2025-015-2510 | F31: Lô 94 | H31: no | I31: 0 | J31: / | L31: 0 | M31: 13232740 | O31: Long Hoàng | P31: 7871 08/12/2025 đã cấn trừ 1USD cho lô sau | Q31: 26409 | R31: no | S31: 0 | T31: no | U31: 0 | V31: no | W31: 0 | X31: Đã TT | Z31: 3466 | AA31: 648000 | AB31: 20000 | AC31: 2580057 | AD31: 4275 | AE31: no | AF31: 0 | AG31: no | AH31: 0 | AI31: no | AJ31: 0 | AK31: no | AL31: 0 | AM31: no | AN31: 0 | AO31: no | AP31: 0 | AQ31: Đã TT | AV31: Rồi
B32: Cassina/2 | C32: EM000180 | D32: 003(2)-004(2) | E32: NNH-CS-2025-001.002.003-02 | F32: Lô 95 | H32: 10680 | I32: =2094918/1.1 -> 1904470.9 | J32: Đã TT | L32: 29771420 | M32: 161367678 | O32: POCO | P32: 3111 ngày 15/12/2025 | Q32: 33006250 | R32: 3221 25/12/2025 | S32: =1140696+3422088+570348 -> 5133132 | T32: no | U32: 0 | V32: 3221 25/12/2025 | W32: 4277610 | X32: Đã TT | Z32: 3545 | AA32: 648000 | AB32: 20000 | AC32: 2624063 | AD32: 250000 | AE32: no | AF32: 0 | AG32: no | AH32: 0 | AI32: no | AJ32: 0 | AK32: no | AL32: 0 | AM32: 377148 | AN32: 999000 | AO32: 1689041 | AP32: 497000 | AQ32: Đã TT | AV32: Rồi
B33: HERMAN MILLER | C33: 4190287643 | D33: NNH-HM-2025-001-1010 | E33: N2072109 | F33: Lô 96 | H33: 1596 | I33: 250000 | J33: Đã TT | L33: 0 | M33: 6675432 | O33: EXPEDITORS | P33: 207216 ngày 16/12/2025 | Q33: 14541407 | R33: 207215 ngày 16/12/2025 | S33: 1080000 | T33: 382088 18/12/2025 | U33: 487971 | V33: 10063 25/12/2025 | W33: 864000 | X33: Đã TT | Z33: 3541 | AA33: 648000 | AB33: 20000 | AC33: no | AD33: 0 | AE33: no | AF33: 0 | AG33: no | AH33: 0 | AI33: no | AJ33: 0 | AK33: no | AL33: 0 | AM33: no | AN33: 0 | AO33: no | AP33: 0 | AQ33: Đã TT | AV33: Rồi
B34: Vitra Akyn | C34: 25-EXP-1854 | D34: NNH-VT-2025-003-2807-DH-0003526 | E34: 5086505 / 1 | F34: Lô 97 | H34: 10882 | I34: =327291/1.1 -> 297537.27 | J34: Đã TT | L34: 0 | M34: 25692561 | O34: VOLTRANS | P34: 11883 ngày 15/12/2025 | Q34: 17906658 | R34: 12108 19/12/2025 | S34: 5582580 | T34: no | U34: 0 | V34: 12108 19/12/2025 | W34: 1605438 | X34: Đã TT | Z34: 3531 | AA34: 648000 | AB34: 20000 | AC34: 2625295 | AD34: 7755 | AE34: no | AF34: 0 | AG34: no | AH34: 0 | AI34: no | AJ34: 0 | AK34: no | AL34: 0 | AM34: no | AN34: 0 | AO34: no | AP34: 0 | AQ34: Đã TT | AV34: Rồi
B35: Ecolux | C35: / | D35: NNH-EC-2025-010-1709-DH-0004084 | E35: / | F35: Lô 98 | H35: no | I35: 0 | J35: / | O35: tiểu ngạch | P35: no | Q35: 0 | R35: no | S35: 0 | T35: no | U35: 0 | V35: no | W35: 0 | X35: / | Z35: no | AA35: 0 | AB35: - | AC35: no | AD35: 0 | AE35: no | AF35: 0 | AG35: no | AH35: 0 | AI35: no | AJ35: 0 | AK35: no | AL35: 0 | AM35: no | AN35: 0 | AO35: no | AP35: 0 | AQ35: Đã TT | AV35: Rồi
B36: USM | C36: 887078081910 | D36: NNH-USM-2025-015-0610 NNH-USM-2025-016-1011 | E36: 102089607 | F36: Lô 99 | H36: no | I36: 0 | J36: / | L36: 13525041 | M36: 11902036 | O36: SAVINO | P36: no | Q36: 0 | R36: 12111 26/12/2025 | S36: 12831858 | T36: no | U36: 0 | V36: no | W36: 0 | X36: Đã TT | Z36: no | AA36: 0 | AB36: 20000 | AC36: no | AD36: 0 | AE36: no | AF36: 0 | AG36: no | AH36: 0 | AI36: no | AJ36: 0 | AK36: no | AL36: 0 | AM36: no | AN36: 0 | AO36: no | AP36: 0 | AQ36: Đã TT | AV36: Rồi
B37: Flos Euroluce | C37: HBL-202500838 | D37: NNH-FLOS-2025-003-2504-SPRING CP NNH-FLOS-2025-010-2909 NNH-FLOS-2025-011-0910 NNH-FLOS-2025-012-1110-DH-0004264 | E37: NNH-FLOS-2025-012-2410 | F37: Lô 100 | H37: 1022 | I37: =699333/1.1 -> 635757.27 | J37: Đã TT | L37: 1987226 | M37: 54504469 | O37: POCO | P37: 23 ngày 05/01/2026 | Q37: 11473995 | R37: 137 15/01/2026 | S37: 4928279 | T37: no | U37: 0 | V37: 137 15/01/2026 | W37: 3190562 | X37: Đã TT | Z37: 17 | AA37: 648000 | AB37: 20000 | AC37: 2821326 | AD37: 5420 | AE37: no | AF37: 0 | AG37: no | AH37: 0 | AI37: no | AJ37: 0 | AK37: no | AL37: 0 | AM37: no | AN37: 0 | AO37: no | AP37: 0 | AQ37: Đã TT | AV37: Rồi
B38: Louis Poulsen | C38: 072506655 | D38: NNH-LPS-2025-005-3110 | E38: NNH-LPS-2025-005-3110 | F38: Lô 101 | H38: 1733 | I38: =797220/1.1 -> 724745.45 | J38: Đã TT | L38: 0 | M38: 60097224 | O38: TCI | P38: 267 ngày 15/01/2026 | Q38: 12613578 | R38: 266 15/01/2026 | S38: 3958968 | T38: 7241 19/01/2026 | U38: 270579 | V38: 501 23/01/2026 | W38: 945000 | X38: Đã TT | Z38: 88 | AA38: 648000 | AB38: 20000 | AC38: no | AD38: 0 | AE38: no | AF38: 0 | AG38: no | AH38: 0 | AI38: no | AJ38: 0 | AK38: no | AL38: 0 | AM38: no | AN38: 0 | AO38: no | AP38: 0 | AQ38: Đã TT | AV38: Rồi
B39: Cassina | C39: 3195731571 | D39: NNH-CS-2025-0512-005 | E39: V1/2025/023358 | F39: Lô 102 | H39: no | I39: 0 | J39: / | L39: 0 | M39: 4459430 | O39: / | P39: no | Q39: 0 | R39: no | S39: 0 | T39: no | U39: 0 | V39: no | W39: 0 | X39: Đã TT | Z39: 3560 | AA39: 648000 | AB39: 20000 | AC39: no | AD39: 0 | AE39: no | AF39: 0 | AG39: no | AH39: 0 | AI39: no | AJ39: 0 | AK39: no | AL39: 0 | AM39: no | AN39: 0 | AO39: no | AP39: 0 | AQ39: Đã TT | AV39: Rồi
B40: Louis Poulsen | C40: 057-53274443 | D40: NNH-LPS-2026-001-1201-DH-0005305 | E40: NNH-LPS-2026-001-1201 | F40: Lô 103 | H40: 1432 | I40: =275000/1.1 -> 250000 | J40: Đã TT | L40: 0 | M40: 14853193 | O40: POCO | P40: 364 ngày 02/02/2026 | Q40: 15321348 | R40: '428 ngày 09/02/2026 | S40: =522200*2*1.08 -> 1127952 | U40: =201168*1.08 -> 217261.44 | V40: 428 ngày 09/02/2026 | W40: =783300*1.08 -> 845964 | X40: Đã TT | Z40: 220 | AA40: 648000 | AB40: 20000 | AC40: no | AD40: 0 | AE40: no | AF40: 0 | AG40: no | AH40: 0 | AI40: no | AJ40: 0 | AK40: no | AL40: 0 | AM40: no | AN40: 0 | AO40: no | AP40: 0 | AQ40: Đã TT | AV40: Rồi
B41: Ecolux | C41: CNSHELGA0003 | D41: NNH-EC-2025-017-1112 | E41: NNH-EC-2025-017-1112 | F41: Lô 104 | H41: no | I41: 0 | J41: / | L41: 741824 | M41: 11847657 | O41: Long hoàng | P41: 747 ngày 03/02/2026 | Q41: 3481940 | R41: 879 ngày 09/02/2026 | S41: 2120580 | T41: 16650 05/02/2026 | U41: 11782 | V41: no | W41: 0 | X41: Đã TT | Z41: 242 | AA41: 648000 | AB41: 20000 | AC41: no | AD41: 0 | AE41: no | AF41: 0 | AG41: no | AH41: 0 | AI41: no | AJ41: 0 | AK41: no | AL41: 0 | AM41: no | AN41: 0 | AO41: no | AP41: 0 | AQ41: Đã TT | AV41: Rồi
B42: Santa cole | C42: MADSGN260301 | D42: NNH-S&C-2025-002-3112-DH-0004403 | E42: NNH-S&C-2025-002-3112 | F42: Lô 105 | H42: 2851 | I42: =275000/1.1 -> 250000 | J42: Đã TT | L42: 0 | M42: 3210779 | O42: Glotrans | P42: 1327 ngày 16/03/2026 | Q42: 10183470 | R42: 1494 ngày 25/03/2026 | S42: 569354 | T42: 73200 ngày 19/03/2026 | U42: 340200 | V42: 1495 ngày 25/03/2026 | W42: 1138709 | X42: Đã TT | Z42: 511 | AA42: 648000 | AB42: 20000 | AC42: no | AD42: 0 | AE42: không lấy hóa đơn | AF42: 1000000 | AG42: no | AH42: 0 | AI42: no | AJ42: 0 | AK42: no | AL42: 0 | AM42: no | AN42: 0 | AO42: no | AP42: 0 | AQ42: Đã TT | AV42: Rồi
B43: Flos | C43: CNL/000159409 | D43: NNH-FLOS-2026-001-0201-DH-0005239 NNH-FLOS-2026-002-1002-DH-0005565 | E43: NNH-FLOS-2026-001-002 | F43: Lô 106 | H43: 2886 | I43: =275000/1.1 -> 250000 | J43: Đã TT | L43: 0 | M43: 12294132 | O43: TCI | P43: 2191 ngày 19/03/2026 | Q43: 37199653 | R43: 2526 ngày 30/03/2026 | S43: =658000+52640 -> 710640 | T43: 88102 23/03/2026 | U43: 1539198 | V43: 2527 ngày 30/03/2026 | W43: =756000 -> 756000 | X43: Đã TT | Z43: 537 | AA43: 648000 | AB43: 20000 | AC43: no | AD43: 0 | AE43: no | AF43: 0 | AG43: no | AH43: 0 | AI43: no | AJ43: 0 | AK43: no | AL43: 0 | AM43: no | AN43: 0 | AO43: no | AP43: 0 | AQ43: Đã TT | AV43: Rồi
B44: Martineli luce | C44: 889383677395 | D44: NNH-ML-2025-001-1112-DH-0003626 | E44: NNH-ML-2025-001-1112 | F44: Lô 107 | H44: no | I44: 0 | J44: / | L44: 0 | M44: 944732 | O44: Fedex | P44: 22371 ngày 30/03/2026 | Q44: 7893879 | R44: no | S44: 0 | T44: no | U44: 0 | V44: no | W44: 0 | X44: Đã TT | Z44: 501 | AA44: 648000 | AB44: 20000 | AC44: no | AD44: 0 | AE44: no | AF44: 0 | AG44: no | AH44: 0 | AI44: no | AJ44: 0 | AK44: no | AL44: 0 | AM44: no | AN44: 0 | AO44: no | AP44: 0 | AQ44: Đã TT | AV44: Rồi
B45: Ecolux | C45: / | D45: NNH-EC-2026-001-2701-DH-0005203 | E45: / | F45: Lô 108 | H45: no | I45: 0 | J45: / | L45: 0 | M45: 0 | O45: tiểu ngạch | P45: không HĐ | Q45: 1135420 | R45: no | S45: 0 | T45: no | U45: 0 | V45: no | W45: 0 | X45: Đã TT | Z45: no | AA45: 0 | AB45: no | AC45: no | AD45: 0 | AE45: no | AF45: 0 | AG45: no | AH45: 0 | AI45: no | AJ45: 0 | AK45: no | AL45: 0 | AM45: no | AN45: 0 | AO45: no | AP45: 0 | AQ45: Đã TT | AV45: Rồi
B46: Ecolux | C46: / | D46: NNH-EC-2026-001-2701-DH-0005203 | E46: / | F46: Lô 109 | H46: no | I46: 0 | J46: / | L46: 0 | M46: 0 | O46: tiểu ngạch | P46: không HĐ | Q46: 316000 | R46: no | S46: 0 | T46: no | U46: 0 | V46: no | W46: 0 | X46: Đã TT | Z46: no | AA46: 0 | AB46: no | AC46: no | AD46: 0 | AE46: no | AF46: 0 | AG46: no | AH46: 0 | AI46: no | AJ46: 0 | AK46: no | AL46: 0 | AM46: no | AN46: 0 | AO46: no | AP46: 0 | AQ46: Đã TT | AV46: Rồi
B47: Louis Poulsen | C47: 7913938992 | D47: NNH-LPS-2025-005-3110 | E47: 1019012991 | F47: Lô 110 | H47: no | I47: 0 | J47: / | L47: 0 | M47: 3743798 | O47: DAP HDL | P47: no | Q47: 0 | R47: no | S47: 0 | T47: no | U47: 0 | V47: no | W47: 0 | X47: / | Z47: 551 | AA47: 648000 | AB47: 20000 | AC47: no | AD47: 0 | AE47: no | AF47: 0 | AG47: no | AH47: 0 | AI47: no | AJ47: 0 | AK47: no | AL47: 0 | AM47: no | AN47: 0 | AO47: no | AP47: 0 | AQ47: Đã TT | AV47: Rồi
B48: FRITZ HANSEN | C48: 1Z514A946796451959 | D48: PO-NNH-FH-2026-002-1601 | E48: 100176056 | F48: Lô 111 | H48: no | I48: 0 | J48: / | L48: 0 | M48: 264406 | O48: UPS | P48: no | Q48: 0 | R48: no | S48: 0 | T48: no | U48: 0 | V48: no | W48: 0 | X48: / | Z48: 487 | AA48: 648000 | AB48: 20000 | AC48: no | AD48: 0 | AE48: no | AF48: 0 | AG48: no | AH48: 0 | AI48: no | AJ48: 0 | AK48: no | AL48: 0 | AM48: no | AN48: 0 | AO48: no | AP48: 0 | AQ48: Đã TT | AV48: Rồi
B49: VIABIZZUNO | C49: 738-05977296 | D49: NNH-VB-2025-002-2912-DH-0005096 | E49: 1.054/03 | F49: Lô 112 | H49: 3398 | I49: =275000/1.1 -> 250000 | J49: Đã TT | L49: 0 | M49: 7487087 | O49: POCO | P49: 794 ngày 31/03/2026 | Q49: 8961380 | R49: 795 ngày 31/03/2026 | S49: 1138622 | T49: 104145 | U49: 464308 | V49: 864 ngày 06/04/2026 | W49: 1366347 | X49: Đã TT | Z49: 736 | AA49: 648000 | AB49: 20000 | AC49: no | AD49: 0 | AE49: không lấy hóa đơn | AF49: 500000 | AG49: no | AH49: 0 | AI49: no | AJ49: 0 | AK49: no | AL49: 0 | AM49: no | AN49: 0 | AO49: no | AP49: 0 | AQ49: Đã TT | AV49: Rồi
B50: Knoll | C50: 126303674 | D50: NNH-KN-2025-004-3010-DH-0004200 | E50: NNH-KN-2025-004-3010 | F50: Lô 113 | H50: 2840 | I50: =290321/1.1 -> 263928.18 | J50: Đã TT | L50: 0 | M50: 22033534 | O50: REAL | P50: 10897 ngày 07/05/2026 | Q50: 7290752 | R50: 10896 ngày 07/05/2026 | S50: 4550695 | T50: no | U50: 0 | V50: 12642 ngày 27/05/2026 | W50: 854323 | X50: Đã TT | Z50: 1076 | AA50: 648000 | AB50: 20000 | AC50: no | AD50: 0 | AE50: no | AF50: 0 | AG50: no | AH50: 0 | AI50: no | AJ50: 0 | AK50: no | AL50: 0 | AM50: no | AN50: 0 | AO50: no | AP50: 0 | AQ50: Đã TT | AV50: Rồi
B51: Nine United Akyn | C51: LSHSGN2603912 | D51: NNH-NU-2026-001-0104 | E51: NNH-NU-2026-001-0104 | F51: Lô 114 | H51: 4634 | I51: =275000/1.1 -> 250000 | J51: Đã TT | L51: 6972323 | M51: 16988147 | O51: D.B | P51: 1997 ngày 05/05/2026 | Q51: 12194738 | R51: 1996 ngày 05/05/2026 | S51: 8357812 | T51: 57398 | U51: 193768 | V51: no | W51: 0 | X51: Đã TT | Z51: 1077 | AA51: 648000 | AB51: 20000 | AC51: no | AD51: 0 | AE51: không lấy hóa đơn | AF51: 800000 | AG51: no | AH51: 0 | AI51: no | AJ51: 0 | AK51: no | AL51: 0 | AM51: no | AN51: 0 | AO51: no | AP51: 0 | AQ51: Đã TT | AV51: Rồi
B52: Santa&Cole | C52: 1742836933 | D52: / | E52: SCN-FV26-03563 | F52: Lô 115 | H52: no | I52: 0 | J52: / | L52: 0 | M52: 59163 | O52: DHL | P52: 86156 ngày 20/05/2026 | Q52: 4314872 | R52: no | S52: 10000 | T52: no | U52: 0 | V52: no | W52: 0 | X52: Đã TT | Z52: no | AA52: 0 | AB52: no | AC52: no | AD52: 0 | AE52: no | AF52: 0 | AG52: no | AH52: 0 | AI52: no | AJ52: 0 | AK52: no | AL52: 0 | AM52: no | AN52: 0 | AO52: no | AP52: 0 | AQ52: Đã TT | AV52: Rồi
B53: FRITZ HANSEN | C53: 26-E-11-03-5047-90A | D53: NNH-FH-2026-001-1601-DH-0005233 | E53: 100179013 | F53: Lô 116 | H53: 3568 | I53: =275000/1.1 -> 250000 | J53: Đã TT | L53: 0 | M53: 6491553 | O53: POCO | P53: 1277 ngày 20/05/2026 | Q53: 8048645 | R53: 1357 ngày 28/05/2026 | S53: 3420014 | T53: no | U53: 0 | V53: no | W53: 0 | X53: Đã TT | Z53: 1164 | AA53: 648000 | AB53: 20000 | AC53: no | AD53: 0 | AE53: no | AF53: 0 | AG53: no | AH53: 0 | AI53: no | AJ53: 0 | AK53: no | AL53: 0 | AM53: no | AN53: 0 | AO53: no | AP53: 0 | AQ53: Đã TT | AV53: Rồi
B54: CASSINA | C54: SMIL00502305 | D54: NNH-CS-2025-003-2805-SR NNH-CS-2025-004-0407-STOCK & Appendix NNH-CS-2025-004-0407-STOCK NNH-CS-2025-006-0512-DH-0005097 | E54: NNH-CS-2026-003.004.006 | F54: Lô 117 | H54: 4038 | I54: =431771/1.1 -> 392519.09 | J54: Đã TT | L54: 4428381 | M54: 36826314 | O54: D.B | P54: 2452 ngày 02/06/2026 | Q54: 4441223 | R54: 2453 ngày 02/06/2026 | S54: 6374076 | T54: 69456 | U54: 47531 | V54: 2652 ngày 16/06/2026 | W54: 1510850 | X54: Đã TT | Z54: 1350 | AA54: 648000 | AB54: 20000 | AC54: no | AD54: 0 | AE54: không lấy hóa đơn | AF54: 1500000 | AG54: no | AH54: 0 | AI54: no | AJ54: 0 | AK54: no | AL54: 0 | AM54: no | AN54: 0 | AO54: no | AP54: 0 | AQ54: Đã TT | AV54: Rồi
B55: FONTANA ARTE | C55: 61 6018 0876 | D55: NNH-FA-2026-001-2804 | E55: IX2600224 | F55: Lô 118 | H55: no | I55: 0 | J55: / | L55: 0 | M55: 1198821 | O55: DHL | P55: 102092 ngày 10/06/2026 | Q55: 6150992 | R55: không HĐ | S55: 10000 | T55: 28703 | U55: 226800 | V55: no | W55: 0 | X55: Đã TT | Z55: 1243 | AA55: 648000 | AB55: 20000 | AC55: no | AD55: 0 | AE55: no | AF55: 0 | AG55: no | AH55: 0 | AI55: no | AJ55: 0 | AK55: no | AL55: 0 | AM55: no | AN55: 0 | AO55: no | AP55: 0 | AQ55: Đã TT | AV55: Rồi
B56: ECOLUX | C56: / | D56: NNH-EC-2026-005-1804-DH-0005693 NNH-EC-2026-006-2504-DH-0005761 | E56: / | F56: Lô 119 | H56: no | I56: 0 | J56: / | L56: 0 | M56: 0 | O56: Tiểu ngạch | P56: không HĐ | Q56: 5016960 | R56: no | S56: 0 | T56: no | U56: 0 | V56: no | W56: 0 | X56: / | Z56: no | AA56: 0 | AB56: no | AC56: no | AD56: 0 | AE56: no | AF56: 0 | AG56: no | AH56: 0 | AI56: no | AJ56: 0 | AK56: no | AL56: 0 | AM56: no | AN56: 0 | AO56: no | AP56: 0 | AQ56: Đã TT | AV56: Rồi
B57: USM | C57: BSL50019202 | D57: NNH-USM-2026-001-1201; NNH-USM-2026-002-0503 | E57: 102091049 | F57: Lô 120 | H57: 7051 | I57: =275000/1.1 -> 250000 | J57: Đã TT | L57: 8513547 | M57: 7491921 | O57: D.B | P57: 2771 ngày 23/06/2026 | Q57: 17829576 | R57: 2770 ngày 23/06/2026 | S57: 428360 | T57: 203745 ngày 26/06/2026 | U57: 807104 | V57: 2938 ngày 30/06/2026 | W57: 2162078 | X57: Đã TT | Z57: no | AA57: 0 | AB57: 20000 | AC57: no | AD57: 0 | AE57: no | AF57: 0 | AG57: no | AH57: 0 | AI57: no | AJ57: 0 | AK57: no | AL57: 0 | AM57: no | AN57: 0 | AO57: no | AP57: 0 | AQ57: Đã TT | AV57: Rồi
B58: B&B Hồ Chí Minh 1st | C58: 627/2026/01 | D58: NNH-B&B-2026-001-0302 & NNH-B&B-2026-002-1102 | E58: NNH-B&B-2026-001.002-01 | F58: Lô 121 | H58: 5415 | I58: =5287911/1.1 -> 4807191.8 | J58: Đã TT | L58: =7023981+5064718 -> 12088699 | M58: =341657603+48903258 -> 390560861 | O58: POCO | P58: 1610 ngày 22/06/2026 | Q58: 62001800 | R58: 1611 ngày 22/06/2026 | S58: 15277032 | T58: chung với HĐ trucking | V58: 1716 ngày 30/06/2026 | W58: 15683237 | X58: Đã TT | Z58: 1477 | AA58: 1620000 | AB58: 40000 | AC58: 710800 | AD58: 750000 | AE58: no | AF58: 0 | AG58: no | AH58: 0 | AI58: no | AJ58: 0 | AK58: no | AL58: 0 | AM58: 873722 ngày 27/06/2026 | AN58: 3586000 | AO58: 142835 ngày 29/06/2026 | AP58: 1225000 | AQ58: Đã TT | AV58: Rồi
B59: B&B Ha Noi 1st | C59: 628/2026/01 | D59: NNH-B&B-2026-003-2402 | E59: NNH-B&B-2026-003-01 | F59: Lô 122 | H59: 5414 ngày 15/05/2026 | I59: 3164840 | J59: Đã TT | O59: POCO | W59: =W56/26395 -> 0
B60: ECOLUX STOCK | F60: Lô 123 | O60: REAL
B61: FLOS | F61: Lô 124 | O61: POCO
B62: VITRA | F62: Lô 125 | H62: 7020 ngày 17/06/2026 | I62: =275000/1.1 -> 250000 | J62: Đã TT | O62: GLOTRANS
B63: B&B HCM 2RD | C63: HBL-202600502 | D63: NNH-B&B-2026-001-0302 NNH-B&B-2026-002-1102 & Appendix AP-NNH-B&B-2026-001-2503 | E63: NNH-B&B-2026-001.002-02 | F63: Lô 126 | H63: 7279 ngày 23/06/2026 | I63: =1199351/1.1 -> 1090319.1 | J63: Đã TT | O63: POCO
B64: B&B HN 2RD | C64: 866/2026/01 | D64: NNH-B&B-2026-003-2402 NNH-B&B-2026-005-2402 | E64: NNH-B&B-2026-003-005-02 | F64: Lô 127 | H64: 7777 ngày 02/07/2026 | I64: =2600566/1.1 -> 2364150.9 | J64: Gửi tt | O64: POCO
B65: CASSINA | F65: Lô 128 | O65: POCO
B66: B&B HN 3RD | F66: Lô 129 | O66: Long Hoàng

Sheet Tong hop hop dong
F1: =SUBTOTAL(109,F3:F84) -> 8831.7 | R1: DEPOSIT
B2: NCC | C2: CONTRACT NO. | D2: PO NO. | E2: Order confirmation No. | F2: TOTAL CONTRACT VALUE | G2: TOTAL CONTRACT VALUE FROM DETAIL LIST | H2: NGOẠI TỆ | J2: LOADING' | K2: Tình trạng | L2: FWD | M2: SHIPPING TYPE (CBM-LCL/20/40) | N2: ATD | O2: ATA | P2: Ghi chú | R2: % DPS | S2: DEPOSIT VALUE | T2: DEPOSIT DATE | U2: TIỀN CỌC CÒN LẠI | W2: CONTRACT NO. | X2: INVOICE | Y2: NGÀY | Z2: AMOUNT INVOICE | AA2: AMOUNT INVOICE FROM LOADING LIST DETAILS | AB2: SỐ TIỀN THANH TOÁN THỰC TẾ | AC2: NGÀY THANH TOÁN | AD2: BALANCE
B3: VITRA | C3: NNH-VT-03-231224-DH-0002612 | D3: NNH-VT-03-231224-DH-0002612 | F3: 1499.4 | H3: EUR | J3: Full loading | K3: Done | L3: SAVINO | M3: CONT 40 | N3: 45821 | O3: 45865 | P3: Bill: SDBJOS016565 | U3: =IF(F3="","",F3-S3) -> 1499.4 | W3: NNH-VT-03-231224-DH-0002612 | X3: 5084714 / 1 | Z3: 1499.4 | AA3: {=IF(X3="","",SUMPRODUCT(--(#REF!=#REF!),--(X3=#REF!),#REF!))} -> #REF! | AB3: 1499.4 | AD3: {=IF(C3=0,"",U3-SUMPRODUCT(--(#REF!=#REF!),$AB$2:$AB$121))} -> #REF!
B4: VITRA | C4: SC-VT-2025-180125-STOCK | D4: PO-VT-2025-180125-STOCK | F4: 43069.8 | H4: EUR | J4: Full loading | K4: Done | L4: SAVINO | M4: CONT 40 | N4: 45821 | O4: 45865 | U4: =IF(F4="","",F4-S4) -> 43069.8 | W4: SC-VT-2025-180125-STOCK | X4: 5084714 / 1 | Z4: 43069.63 | AA4: {=IF(X4="","",SUMPRODUCT(--(#REF!=#REF!),--(X4=#REF!),#REF!))} -> #REF! | AB4: 43069.63 | AD4: {=IF(C4=0,"",U4-SUMPRODUCT(--(#REF!=#REF!),$AB$2:$AB$121))} -> #REF!
B5: VITRA | C5: NNH-VT-2025-002-1906-RIMOWA | D5: NNH-VT-2025-002-1906-RIMOWA | F5: 3880.8 | H5: EUR | J5: Full loading | K5: Done | L5: BÁCH VIỆT | M5: AIR | O5: 45856 | P5: Đã nhập kho | U5: =IF(F5="","",F5-S5) -> 3880.8 | W5: NNH-VT-2025-002-1906-RIMOWA | X5: 5085293 | Z5: 3880.8 | AA5: {=IF(X5="","",SUMPRODUCT(--(#REF!=#REF!),--(X5=#REF!),#REF!))} -> #REF! | AB5: 3880.8 | AD5: {=IF(C5=0,"",U5-SUMPRODUCT(--(#REF!=#REF!),$AB$2:$AB$121))} -> #REF!
B6: USM | C6: NNH-USM-2025-004-1503 | D6: NNH-USM-2025-004-1503 | F6: 12489.369 | G6: {=IF(C6="",SUMPRODUCT(--(D6=LDL!$E$4:$E$2661),LDL!$AC$4:$AC$2661),SUMPRODUCT(--(C6=LDL!$D$4:$D$2661),LDL!$AC$4:$AC$2661))} -> 12489.449 | H6: EUR | J6: 1st loading | K6: Done | P6: / | W6: NNH-USM-2025-004-1503 | X6: 102087668-102088128 | Y6: 45768 | Z6: 907.23 | AA6: {=IF(X6="","",SUMPRODUCT(--(W6=LDL!$D$4:$D$1641),--(X6=LDL!$AJ$4:$AJ$1641),LDL!$AC$4:$AC$1641))} -> 907.23 | AF6: 102088938, 102089021, 102089057
J7: 2rd loading | K7: Done | L7: BÁCH VIỆT | M7: LCL | N7: 45832 | O7: 45885 | P7: Bill: 01/25/300247 | U7: =IF(F7="","",F7-S7) | W7: NNH-USM-2025-004-1503 | X7: 102087998 | Y7: 45820 | Z7: 11582.35 | AA7: {=IF(X7="","",SUMPRODUCT(--(W7=LDL!$D$4:$D$1641),--(X7=LDL!$AJ$4:$AJ$1641),LDL!$AC$4:$AC$1641))} -> 11582.219 | AD7: {=IF(C7=0,"",U7-SUMPRODUCT(--(#REF!=#REF!),$AB$2:$AB$121))} | AF7: 102088866
B8: USM | C8: NNH-USM-2025-007-2406 | D8: NNH-USM-2025-007-1106-DH-0003293; NNH-USM-2025-008-0307-02; NNH-USM-2025-007-2406-DH-0003650 | F8: 3525.92 | G8: {=IF(C8="",SUMPRODUCT(--(D8=LDL!$E$4:$E$2661),LDL!$AC$4:$AC$2661),SUMPRODUCT(--(C8=LDL!$D$4:$D$2661),LDL!$AC$4:$AC$2661))} -> 3525.92 | H8: EUR | J8: Full loading | K8: Done | L8: POCO | M8: AIR | N8: E: 29.07.25 | O8: E: 31.07.25 | P8: the cost differs EUR 4.28 Khi hàng về Tạo mã tủ mới cho CA để lấy mã đó xuất bán cho khách hàng + đổi hình Chưa có chứng từ ETD ZRH: 29.07.25 ETA SGN: 31.07.25 102089021 | U8: =IF(F8="","",F8-S8) -> 3525.92 | W8: NNH-USM-2025-007-2406 | X8: Chưa có | AA8: {=IF(X8="","",SUMPRODUCT(--(W8=LDL!$D$4:$D$1641),--(X8=LDL!$AJ$4:$AJ$1641),LDL!$AC$4:$AC$1641))} -> 0 | AB8: 3525.92 | AE8: TT đủ, thiếu 4.28 eur so với SO USM gửi, sẽ TT vào HĐ 008 sea | AF8: DH-0003650 (SO: 102088938) (1,040.41 eur) DH-0003293 (SO: 102088814) (405.59 + 47.88 (102088866) (bổ sung sau) = 453.47 eur Total: 1,493.88 eur 1 shipment - air (-02) 2.036,32 eur (SO: 102089057) | AG8: Khi hàng về Tạo mã tủ mới cho CA để lấy mã đó xuất bán cho khách hàng
B9: Fritz Hansen | C9: NNH-FH-2025-001-2103-DH-0002924 | D9: NNH-FH-2025-001-2103-DH-0002924 | F9: 8318.75 | G9: {=IF(C9="",SUMPRODUCT(--(D9=LDL!$E$4:$E$2661),LDL!$AC$4:$AC$2661),SUMPRODUCT(--(C9=LDL!$D$4:$D$2661),LDL!$AC$4:$AC$2661))} -> 8318.75 | H9: EUR | J9: Full loading | K9: Done | L9: macnel | M9: LCL | N9: 45827 | O9: 45882 | P9: Đã nhập kho | W9: NNH-FH-2025-001-2103-DH-0002924 | X9: 100150372 | Y9: 45818 | Z9: 8318.75 | AA9: {=IF(X9="","",SUMPRODUCT(--(W9=LDL!$D$4:$D$1641),--(X9=LDL!$AJ$4:$AJ$1641),LDL!$AC$4:$AC$1641))} -> 8318.75 | AB9: 8318.75 | AC9: 45783 | AD9: Done
B10: Santa&Cole | C10: SC-S&C-01-281224-DH-SHOWROOM | D10: SC-S&C-01-281224-DH-SHOWROOM | F10: 21678.53 | G10: {=IF(C10="",SUMPRODUCT(--(D10=LDL!$E$4:$E$2661),LDL!$AC$4:$AC$2661),SUMPRODUCT(--(C10=LDL!$D$4:$D$2661),LDL!$AC$4:$AC$2661))} -> 21678.6 | H10: EUR | J10: 1st loading | K10: Done | M10: SEA | P10: / | W10: SC-S&C-01-281224-DH-SHOWROOM | X10: SC-S&C-01-281224-DH-SHOWROOM | Y10: 28/12/2025 | Z10: 21678.6 | AA10: {=IF(X10="","",SUMPRODUCT(--(W10=LDL!$D$4:$D$1641),--(X10=LDL!$AJ$4:$AJ$1641),LDL!$AC$4:$AC$1641))} -> 19349.59 | AD10: Done
J11: 2rd loading | K11: Done | L11: CP WORD | M11: SEA | N11: 45825 | O11: E: 17/08 | P11: Bill: 250402065/0413 | U11: =IF(F11="","",F11-S11) | W11: SC-S&C-01-281224-DH-SHOWROOM | X11: SCN-FV25-03354 | Y11: 45754 | Z11: 2328975 | AA11: {=IF(X11="","",SUMPRODUCT(--(W11=LDL!$D$4:$D$1641),--(X11=LDL!$AJ$4:$AJ$1641),LDL!$AC$4:$AC$1641))} -> 2329.01 | AD11: Done
B12: Knoll | C12: NNH-KN-2025-002-1103-DH-0002924 | D12: NNH-KN-2025-002-1103-DH-0002924 | F12: 2033 | G12: {=IF(C12="",SUMPRODUCT(--(D12=LDL!$E$4:$E$2661),LDL!$AC$4:$AC$2661),SUMPRODUCT(--(C12=LDL!$D$4:$D$2661),LDL!$AC$4:$AC$2661))} -> 2033 | H12: EUR | J12: Full loading | K12: Done | L12: DB GROUP | M12: SEA | N12: 45842 | O12: 45890 | R12: 0.5 | S12: 1016.5 | U12: =IF(F12="","",F12-S12) -> 1016.5 | W12: NNH-KN-2025-002-1103-DH-0002924 | X12: 053617 - 053920 | Y12: 45821 | Z12: 2033 | AA12: {=IF(X12="","",SUMPRODUCT(--(W12=LDL!$D$4:$D$1641),--(X12=LDL!$AJ$4:$AJ$1641),LDL!$AC$4:$AC$1641))} -> 2033 | AB12: 1016.5 | AD12: Done
B13: Knoll | C13: NNH-KN-2025-003-2503-SR | D13: NNH-KN-2025-003-2503-SR | F13: 2839 | G13: {=IF(C13="",SUMPRODUCT(--(D13=LDL!$E$4:$E$2661),LDL!$AC$4:$AC$2661),SUMPRODUCT(--(C13=LDL!$D$4:$D$2661),LDL!$AC$4:$AC$2661))} -> 2839 | H13: EUR | J13: Full loading | K13: Done | R13: 0.5 | S13: 1419.5 | U13: =IF(F13="","",F13-S13) -> 1419.5 | W13: NNH-KN-2025-003-2503-SR | X13: 053617 - 053920 | Y13: 45821 | Z13: 2839 | AA13: {=IF(X13="","",SUMPRODUCT(--(W13=LDL!$D$4:$D$1641),--(X13=LDL!$AJ$4:$AJ$1641),LDL!$AC$4:$AC$1641))} -> 2839 | AB13: 1419.5 | AD13: Done
B14: VIABIZZUNO S.P.A | C14: NNH-VB-2025-001-1503-DH-0003027 | D14: NNH-VB-2025-001-1503-DH-0003027 | F14: 28531.1 | G14: {=IF(C14="",SUMPRODUCT(--(D14=LDL!$E$4:$E$2661),LDL!$AC$4:$AC$2661),SUMPRODUCT(--(C14=LDL!$D$4:$D$2661),LDL!$AC$4:$AC$2661))} -> 28531.1 | H14: EUR | J14: Full loading | K14: Done | L14: DB GROUP | M14: AIR | N14: 45849 | P14: Còn 1 lô chưa về tới 25/07 | R14: 0.5 | S14: =R14*F14 -> 14265.55 | U14: =IF(F14="","",F14-S14) -> 14265.55 | W14: NNH-VB-2025-001-1503-DH-0003027 | X14: NNNH-VB-2025-001-2.377/03 | Y14: 45838 | AA14: {=IF(X14="","",SUMPRODUCT(--(W14=LDL!$D$4:$D$1641),--(X14=LDL!$AJ$4:$AJ$1641),LDL!$AC$4:$AC$1641))} -> 26050.8
B15: Flos | C15: NNH-FLOS-2025-006-1408-DH-0003915 | D15: NNH-FLOS-2025-006-1408-DH-0003915 | F15: 740.88 | G15: {=IF(C15="",SUMPRODUCT(--(D15=LDL!$E$4:$E$2661),LDL!$AC$4:$AC$2661),SUMPRODUCT(--(C15=LDL!$D$4:$D$2661),LDL!$AC$4:$AC$2661))} -> 740.88 | H15: EUR | J15: Full loading | K15: Done | L15: Long Hoàng | M15: AIR | N15: 45902 | P15: MINI BUTTON | W15: NNH-FLOS-2025-006-1408-DH-0003915 | X15: chưa | AB15: 740.88 | AC15: 15/08/2025 DA2FT252272JGB4 | AD15: Done
B16: Louis Poulsen | C16: NNH-LPS-2025-004-0108-DH-0003788 | D16: NNH-LPS-2025-004-0108-DH-0003788 | E16: 927088 | F16: 1260 | G16: {=IF(C16="",SUMPRODUCT(--(D16=LDL!$E$4:$E$2661),LDL!$AC$4:$AC$2661),SUMPRODUCT(--(C16=LDL!$D$4:$D$2661),LDL!$AC$4:$AC$2661))} -> 1260 | H16: EUR | J16: Full loading | K16: Done | L16: POCO | M16: AIR | N16: 45888 | O16: 45892 | W16: NNH-LPS-2025-004-0108-DH-0003788 | X16: 1019012434 | Y16: 45882 | Z16: 1260 | AA16: {=IF(X16="","",SUMPRODUCT(--(W16=LDL!$D$4:$D$1641),--(X16=LDL!$AJ$4:$AJ$1641),LDL!$AC$4:$AC$1641))} -> 1260 | AB16: Chưa
B17: FONTANA ARTE | C17: NNH-FA-2025-001 | D17: NNH-FA-2025-001 | E17: SO2504153-2 | F17: 105 | G17: {=IF(C17="",SUMPRODUCT(--(D17=LDL!$E$4:$E$2661),LDL!$AC$4:$AC$2661),SUMPRODUCT(--(C17=LDL!$D$4:$D$2661),LDL!$AC$4:$AC$2661))} -> 105 | H17: EUR | J17: Full loading | K17: Done | M17: AIR
B18: ECOLUX | D18: NNH-EC-2025-008-0208-SAMPLE | F18: 101.9 | G18: {=IF(C18="",SUMPRODUCT(--(D18=LDL!$E$4:$E$2661),LDL!$AC$4:$AC$2661),SUMPRODUCT(--(C18=LDL!$D$4:$D$2661),LDL!$AC$4:$AC$2661))} -> 0 | H18: RMB | J18: Full loading | K18: Done | P18: tiểu ngạch
B19: NINE UNITED | C19: NNH-NU-2025-002-1408 | D19: NNH-NU-2025-002-1807-DH-0003701 NNH-NU-2025-003-2207-DH-0003785 NNH-NU-2025-004-2507-DH-0003806 + Stock | G19: {=IF(C19="",SUMPRODUCT(--(D19=LDL!$E$4:$E$2661),LDL!$AC$4:$AC$2661),SUMPRODUCT(--(C19=LDL!$D$4:$D$2661),LDL!$AC$4:$AC$2661))} -> 24691.48 | H19: USD | K19: Done | L19: / | M19: SEA | N19: 45914 | O19: E: 19/09/2025 | AA19: {=IF(X19="","",SUMPRODUCT(--(W19=LDL!$D$4:$D$1641),--(X19=LDL!$AJ$4:$AJ$1641),LDL!$AC$4:$AC$1641))}
B20: ECOLUX | C20: NNH-EC-2025-006-0208-STOCK | D20: NNH-EC-2025-006-0208-STOCK | F20: 32421 | G20: {=IF(C20="",SUMPRODUCT(--(D20=LDL!$E$4:$E$2661),LDL!$AC$4:$AC$2661),SUMPRODUCT(--(C20=LDL!$D$4:$D$2661),LDL!$AC$4:$AC$2661))} -> 32451 | H20: USD | K20: Done | L20: Long Hoàng
B21: ECOLUX | C21: NNH-EC-2025-007-0208-DH-0003828 | D21: NNH-EC-2025-007-0208-DH-0003828 | F21: 24693.21 | G21: {=IF(C21="",SUMPRODUCT(--(D21=LDL!$E$4:$E$2661),LDL!$AC$4:$AC$2661),SUMPRODUCT(--(C21=LDL!$D$4:$D$2661),LDL!$AC$4:$AC$2661))} -> 24693.21 | H21: USD | K21: Done | L21: Long Hoàng | M21: SEA | N21: 45918 | O21: E: 22/09/2025
B22: ECOLUX | C22: NNH-EC-2025-009-0708-DH-0003753 | D22: NNH-EC-2025-009-0708-DH-0003753 | F22: 315.82 | G22: {=IF(C22="",SUMPRODUCT(--(D22=LDL!$E$4:$E$2661),LDL!$AC$4:$AC$2661),SUMPRODUCT(--(C22=LDL!$D$4:$D$2661),LDL!$AC$4:$AC$2661))} -> 315.82 | H22: USD
B23: ECOLUX | D23: NNH-EC-2025-010-1709-DH-0004084 | F23: 3284.8 | K23: Done | L23: tiểu ngạch
B24: Louis Poulsen | C24: NNH-LPS-2025-002-2702-PANTHELLA | D24: PO-NNH-LPS-2025-001-1801-DROP1; NNH-LPS-2025-002-2702-PANTHELLA; NNH-LPS-2025-003-1905-DH-0003379 | F24: 25178.5 | G24: {=IF(C24="",SUMPRODUCT(--(D24=LDL!$E$4:$E$2661),LDL!$AC$4:$AC$2661),SUMPRODUCT(--(C24=LDL!$D$4:$D$2661),LDL!$AC$4:$AC$2661))} -> 26785.15 | H24: EUR | J24: Full loading | K24: Done | L24: Long Hoàng | M24: SEA | N24: E: 07/08/2025 | O24: E: 30/09/2025 | W24: NNH-LPS-2025-002-2702-PANTHELLA | X24: NNH-LPS-2025-001 | Y24: 45842 | Z24: 25178.5 | AA24: {=IF(X24="","",SUMPRODUCT(--(W24=LDL!$D$4:$D$1641),--(X24=LDL!$AJ$4:$AJ$1641),LDL!$AC$4:$AC$1641))} -> 26785.15 | AB24: 25178.5 | AC24: 07/09/2025 DA2FT25190K9PTN | AD24: Done
B25: STOFF | C25: NNH-ST-2025-001-1706 | D25: NNH-ST-2025-001-1706 | F25: 7804.44 | G25: {=IF(C25="",SUMPRODUCT(--(D25=LDL!$E$4:$E$2661),LDL!$AC$4:$AC$2661),SUMPRODUCT(--(C25=LDL!$D$4:$D$2661),LDL!$AC$4:$AC$2661))} -> 7804.44 | H25: EUR | J25: Full loading | K25: Done | L25: Long Hoàng | M25: SEA | N25: E: 07/08/2025 | O25: E: 30/09/2025 | W25: NNH-ST-2025-001-1706 | X25: 289375 | Y25: 45862 | Z25: 7804.44 | AA25: {=IF(X25="","",SUMPRODUCT(--(W25=LDL!$D$4:$D$1641),--(X25=LDL!$AJ$4:$AJ$1641),LDL!$AC$4:$AC$1641))} -> 7804.44 | AB25: 7804.44 | AC25: 25/06/2025 NCTFT25176QMDT0 | AD25: Done
B26: USM | C26: NNH-USM-2025-014-0610 | D26: NNH-USM-2025-014-0708-DH-0003871 | E26: 102089408 | F26: 45.51 | G26: {=IF(C26="",SUMPRODUCT(--(D26=LDL!$E$4:$E$2661),LDL!$AC$4:$AC$2661),SUMPRODUCT(--(C26=LDL!$D$4:$D$2661),LDL!$AC$4:$AC$2661))} -> 224.08 | H26: EUR | J26: Full loading | K26: Done | L26: FEDEX | M26: AIR | N26: 45961 | O26: 45964 | P26: Gửi chứng từ cho XNK | X26: Chưa | AA26: {=IF(X26="","",SUMPRODUCT(--(W26=LDL!$D$4:$D$1641),--(X26=LDL!$AJ$4:$AJ$1641),LDL!$AC$4:$AC$1641))} -> 0
B27: USM | D27: NNH-USM-2025-016-0109-DH-0004048 | E27: 102089682 | F27: 178.55 | G27: {=IF(C27="",SUMPRODUCT(--(D27=LDL!$E$4:$E$2661),LDL!$AC$4:$AC$2661),SUMPRODUCT(--(C27=LDL!$D$4:$D$2661),LDL!$AC$4:$AC$2661))} -> 178.56 | H27: EUR | X27: Chưa
B28: Flos | C28: NNH-FLOS-2025-003-2504-SPRING CP | D28: NNH-FLOS-2025-003-2504-SPRING CP | F28: 10710.42 | G28: {=IF(C28="",SUMPRODUCT(--(D28=LDL!$E$4:$E$2661),LDL!$AC$4:$AC$2661),SUMPRODUCT(--(C28=LDL!$D$4:$D$2661),LDL!$AC$4:$AC$2661))} -> 14099.12 | H28: EUR | J28: 1st | K28: Done | L28: DB GROUP | M28: SEA | N28: 45906 | O28: 45958 | P28: sửa hợp đồng, mã dòng số 2+3 bỏ bóng, lệch 68.2 sẽ làm phụ lục hợp đồng thay đổi giá dòng 2 và 3 lúc làm chứng từ theo đơn giá mới 3 cái spring cm rớt, F1040009 (2pcs), + F1040015 (1pcs), | W28: NNH-FLOS-2025-003-2504-SPRING CP | X28: chưa | AA28: {=IF(X28="","",SUMPRODUCT(--(W28=LDL!$D$4:$D$1641),--(X28=LDL!$AJ$4:$AJ$1641),LDL!$AC$4:$AC$1641))} -> 0 | AB28: 10710.42 | AC28: 09/07/2025 DA2FT25190YRXQW | AD28: Done
B29: Cassina | C29: NNH-CS-2025-001-1203-DH-0002924 | D29: NNH-CS-2025-001-1203-DH-0002924 | F29: 21634.29 | G29: {=IF(C29="",SUMPRODUCT(--(D29=LDL!$E$4:$E$2661),LDL!$AC$4:$AC$2661),SUMPRODUCT(--(C29=LDL!$D$4:$D$2661),LDL!$AC$4:$AC$2661))} -> 21634.29 | H29: EUR | J29: Full loading | K29: Done | L29: DB GROUP | M29: SEA | N29: 45906 | O29: E: 30/10/2025 | R29: 0.3 | S29: 6490.287 | T29: 45744 | U29: =IF(F29="","",F29-S29) -> 15144.003 | W29: NNH-CS-2025-001-1203-DH-0002924 | AA29: {=IF(X29="","",SUMPRODUCT(--(W29=LDL!$D$4:$D$1641),--(X29=LDL!$AJ$4:$AJ$1641),LDL!$AC$4:$AC$1641))} | AB29: 15144 | AC29: 45907 | AD29: Done
B30: Cassina | C30: NNH-CS-2025-002-1404-DH-0003174 | D30: NNH-CS-2025-002-1404-DH-0003174 | F30: 8871.39 | G30: {=IF(C30="",SUMPRODUCT(--(D30=LDL!$E$4:$E$2661),LDL!$AC$4:$AC$2661),SUMPRODUCT(--(C30=LDL!$D$4:$D$2661),LDL!$AC$4:$AC$2661))} -> 8871.39 | H30: EUR | J30: Full loading | R30: 0.3 | S30: 2661.417 | T30: 45768 | U30: =IF(F30="","",F30-S30) -> 6209.973 | W30: NNH-CS-2025-002-1404-DH-0003174 | AA30: {=IF(X30="","",SUMPRODUCT(--(W30=LDL!$D$4:$D$1641),--(X30=LDL!$AJ$4:$AJ$1641),LDL!$AC$4:$AC$1641))} | AB30: =4337.3+1872.67 -> 6209.97 | AC30: 45907 | AD30: Done
B31: Cassina | C31: NNH-CS-2025-003-2805-SR | D31: NNH-CS-2025-003-2805-SR | F31: 225025.37 | G31: {=IF(C31="",SUMPRODUCT(--(D31=LDL!$E$4:$E$2661),LDL!$AC$4:$AC$2661),SUMPRODUCT(--(C31=LDL!$D$4:$D$2661),LDL!$AC$4:$AC$2661))} -> 225035.37 | H31: EUR | J31: 1st loading | R31: 0.3 | S31: 67507.611 | T31: 45820 | U31: =IF(F31="","",F31-S31) -> 157517.76 | W31: NNH-CS-2025-003-2805-SR | AA31: {=IF(X31="","",SUMPRODUCT(--(W31=LDL!$D$4:$D$1641),--(X31=LDL!$AJ$4:$AJ$1641),LDL!$AC$4:$AC$1641))} | AB31: 60714.98 | AC31: 45907 | AD31: Done
B32: Cassina | C32: NNH-CS-2025-004-0407-STOCK | D32: NNH-CS-2025-004-0407-STOCK | F32: 52380.09 | G32: {=IF(C32="",SUMPRODUCT(--(D32=LDL!$E$4:$E$2661),LDL!$AC$4:$AC$2661),SUMPRODUCT(--(C32=LDL!$D$4:$D$2661),LDL!$AC$4:$AC$2661))} -> 52380.09 | H32: EUR | J32: 1st loading | S32: 15652.95 | T32: 45907 | U32: =IF(F32="","",F32-S32) -> 36727.14 | W32: NNH-CS-2025-004-0407-STOCK | AA32: {=IF(X32="","",SUMPRODUCT(--(W32=LDL!$D$4:$D$1641),--(X32=LDL!$AJ$4:$AJ$1641),LDL!$AC$4:$AC$1641))} | AD32: Done
B33: Fritz Hansen | C33: NNH-FH-2025-002-2708 | D33: NNH-FH-2025-002-0705-STOCK | E33: Superellipse+ Series 7 Stock: OC 80166685 Series 7 Concert Chairs: OC 80166687 7:14 AM: OC 80166680 PK 24 Neck cushion: OC 80166684 Series 7 leather campaign: OC 80166727 | F33: 135244.14 | G33: {=IF(C33="",SUMPRODUCT(--(D33=LDL!$E$4:$E$2661),LDL!$AC$4:$AC$2661),SUMPRODUCT(--(C33=LDL!$D$4:$D$2661),LDL!$AC$4:$AC$2661))} -> 146199.59 | H33: EUR | J33: Full loading | K33: Done | L33: POCO | M33: SEA | N33: 45917 | O33: 45960 | W33: NNH-FH-2025-002-2708 | X33: chưa | AA33: {=IF(X33="","",SUMPRODUCT(--(W33=LDL!$D$4:$D$1641),--(X33=LDL!$AJ$4:$AJ$1641),LDL!$AC$4:$AC$1641))} -> 0 | AD33: Done
B34: Fritz Hansen | D34: NNH-FH-2025-003-1605-DH-0003363 | E34: 80167383 | F34: 474.65 | G34: {=IF(C34="",SUMPRODUCT(--(D34=LDL!$E$4:$E$2661),LDL!$AC$4:$AC$2661),SUMPRODUCT(--(C34=LDL!$D$4:$D$2661),LDL!$AC$4:$AC$2661))} -> 474.65 | H34: EUR | AA34: {=IF(X34="","",SUMPRODUCT(--(W34=LDL!$D$4:$D$1641),--(X34=LDL!$AJ$4:$AJ$1641),LDL!$AC$4:$AC$1641))}
B35: Fritz Hansen | D35: NNH-FH-2025-004-1906-AKYN | E35: 80171011 | F35: 7536.1 | G35: {=IF(C35="",SUMPRODUCT(--(D35=LDL!$E$4:$E$2661),LDL!$AC$4:$AC$2661),SUMPRODUCT(--(C35=LDL!$D$4:$D$2661),LDL!$AC$4:$AC$2661))} -> 7536.1 | H35: EUR | AA35: {=IF(X35="","",SUMPRODUCT(--(W35=LDL!$D$4:$D$1641),--(X35=LDL!$AJ$4:$AJ$1641),LDL!$AC$4:$AC$1641))} | AD35: {=IF(C35=0,"",U35-SUMPRODUCT(--(#REF!=#REF!),$AB$2:$AB$121))}
B36: Fritz Hansen | D36: NNH-FH-2025-005-2006-DH-0003627 | E36: 80171150 | F36: 1153.9 | G36: {=IF(C36="",SUMPRODUCT(--(D36=LDL!$E$4:$E$2661),LDL!$AC$4:$AC$2661),SUMPRODUCT(--(C36=LDL!$D$4:$D$2661),LDL!$AC$4:$AC$2661))} -> 1153.9 | H36: EUR | AA36: {=IF(X36="","",SUMPRODUCT(--(W36=LDL!$D$4:$D$1641),--(X36=LDL!$AJ$4:$AJ$1641),LDL!$AC$4:$AC$1641))} | AD36: {=IF(C36=0,"",U36-SUMPRODUCT(--(#REF!=#REF!),$AB$2:$AB$121))}
B37: Fritz Hansen | D37: NNH-FH-2025-008-0108-DH-0003788 | E37: 80175372 | F37: 312.4 | G37: {=IF(C37="",SUMPRODUCT(--(D37=LDL!$E$4:$E$2661),LDL!$AC$4:$AC$2661),SUMPRODUCT(--(C37=LDL!$D$4:$D$2661),LDL!$AC$4:$AC$2661))} -> 312.4 | H37: EUR | AA37: {=IF(X37="","",SUMPRODUCT(--(W37=LDL!$D$4:$D$1641),--(X37=LDL!$AJ$4:$AJ$1641),LDL!$AC$4:$AC$1641))}
B38: Fritz Hansen | D38: NNH-FH-2025-009-0708-DH-0003894 | E38: 80175966 | F38: 1478.4 | G38: {=IF(C38="",SUMPRODUCT(--(D38=LDL!$E$4:$E$2661),LDL!$AC$4:$AC$2661),SUMPRODUCT(--(C38=LDL!$D$4:$D$2661),LDL!$AC$4:$AC$2661))} -> 1478.4 | H38: EUR | AA38: {=IF(X38="","",SUMPRODUCT(--(W38=LDL!$D$4:$D$1641),--(X38=LDL!$AJ$4:$AJ$1641),LDL!$AC$4:$AC$1641))}
B39: ECOLUX | D39: NNH-EC-2025-010-1709-DH-0004084 | G39: {=IF(C39="",SUMPRODUCT(--(D39=LDL!$E$4:$E$2661),LDL!$AC$4:$AC$2661),SUMPRODUCT(--(C39=LDL!$D$4:$D$2661),LDL!$AC$4:$AC$2661))} -> 3287.46 | K39: Done
B40: ECOLUX | D40: NNH-EC-2025-012-2609-DH-0003985 | G40: {=IF(C40="",SUMPRODUCT(--(D40=LDL!$E$4:$E$2661),LDL!$AC$4:$AC$2661),SUMPRODUCT(--(C40=LDL!$D$4:$D$2661),LDL!$AC$4:$AC$2661))} -> 2013.4 | K40: Done
B41: ECOLUX | D41: NNH-EC-2025-013-0910-DH-0004233 | E41: routine tầng trệt | F41: 3474.3 | G41: {=IF(C41="",SUMPRODUCT(--(D41=LDL!$E$4:$E$2661),LDL!$AC$4:$AC$2661),SUMPRODUCT(--(C41=LDL!$D$4:$D$2661),LDL!$AC$4:$AC$2661))} -> 3624.7 | K41: Done
B42: ECOLUX | D42: NNH-EC-2025-016-0511-DH TABLE | E42: PI NAN-024 | F42: 480.05 | H42: USD | K42: Done | L42: tiểu ngạch | P42: DH-0004380 hạn giao hàng 20/11/2025
